Workbook
Name Hedging_Positions_through_Futures_AS_ON_MMMM_DD__YYYY___NIL: EDBE23!#REF!
Name Hedging_Positions_through_Futures_AS_ON_MMMM_DD__YYYY___NIL: EDBE25!#REF!
Name Hedging_Positions_through_Futures_AS_ON_MMMM_DD__YYYY___NIL: EDBE30!#REF!
Name Hedging_Positions_through_Futures_AS_ON_MMMM_DD__YYYY___NIL: EDBE31!#REF!
Name Hedging_Positions_through_Futures_AS_ON_MMMM_DD__YYYY___NIL: EDBE32!#REF!
Name Hedging_Positions_through_Futures_AS_ON_MMMM_DD__YYYY___NIL: EDBPDF!#REF!
Name Hedging_Positions_through_Futures_AS_ON_MMMM_DD__YYYY___NIL: EDCG27!#REF!
Name Hedging_Positions_through_Futures_AS_ON_MMMM_DD__YYYY___NIL: EDCG37!#REF!
Name Hedging_Positions_through_Futures_AS_ON_MMMM_DD__YYYY___NIL: EDCPSF!#REF!
Name Hedging_Positions_through_Futures_AS_ON_MMMM_DD__YYYY___NIL: EDFF23!#REF!
Name Hedging_Positions_through_Futures_AS_ON_MMMM_DD__YYYY___NIL: EDFF25!#REF!
Name Hedging_Positions_through_Futures_AS_ON_MMMM_DD__YYYY___NIL: EDFF30!#REF!
Name Hedging_Positions_through_Futures_AS_ON_MMMM_DD__YYYY___NIL: EDFF31!#REF!
Name Hedging_Positions_through_Futures_AS_ON_MMMM_DD__YYYY___NIL: EDFF32!#REF!
Name Hedging_Positions_through_Futures_AS_ON_MMMM_DD__YYYY___NIL: EDGSEC!#REF!
Name Hedging_Positions_through_Futures_AS_ON_MMMM_DD__YYYY___NIL: EDNP27!#REF!
Name Hedging_Positions_through_Futures_AS_ON_MMMM_DD__YYYY___NIL: EDNPSF!#REF!
Name Hedging_Positions_through_Futures_AS_ON_MMMM_DD__YYYY___NIL: EDONTF!#REF!
Name Hedging_Positions_through_Futures_AS_ON_MMMM_DD__YYYY___NIL: EEARBF!#REF!
Name Hedging_Positions_through_Futures_AS_ON_MMMM_DD__YYYY___NIL: EEARFD!#REF!
Name Hedging_Positions_through_Futures_AS_ON_MMMM_DD__YYYY___NIL: EEDGEF!#REF!
Name Hedging_Positions_through_Futures_AS_ON_MMMM_DD__YYYY___NIL: EEECRF!#REF!
Name Hedging_Positions_through_Futures_AS_ON_MMMM_DD__YYYY___NIL: EEELSS!#REF!
Name Hedging_Positions_through_Futures_AS_ON_MMMM_DD__YYYY___NIL: EEEQTF!#REF!
Name Hedging_Positions_through_Futures_AS_ON_MMMM_DD__YYYY___NIL: EEESCF!#REF!
Name Hedging_Positions_through_Futures_AS_ON_MMMM_DD__YYYY___NIL: EEESSF!#REF!
Name Hedging_Positions_through_Futures_AS_ON_MMMM_DD__YYYY___NIL: EEFOCF!#REF!
Name Hedging_Positions_through_Futures_AS_ON_MMMM_DD__YYYY___NIL: EEIF30!#REF!
Name Hedging_Positions_through_Futures_AS_ON_MMMM_DD__YYYY___NIL: EEIF50!#REF!
Name Hedging_Positions_through_Futures_AS_ON_MMMM_DD__YYYY___NIL: EELMIF!#REF!
Name Hedging_Positions_through_Futures_AS_ON_MMMM_DD__YYYY___NIL: EEMOF1!#REF!
Name Hedging_Positions_through_Futures_AS_ON_MMMM_DD__YYYY___NIL: EENFBA!#REF!
Name Hedging_Positions_through_Futures_AS_ON_MMMM_DD__YYYY___NIL: EEPRUA!#REF!
Name Hedging_Positions_through_Futures_AS_ON_MMMM_DD__YYYY___NIL: EESMCF!#REF!
Name Hedging_Positions_through_Futures_AS_ON_MMMM_DD__YYYY___NIL: EGSFOF!#REF!
Name Hedging_Positions_through_Futures_AS_ON_MMMM_DD__YYYY___NIL: ELLIQF!#REF!
Name Hedging_Positions_through_Futures_AS_ON_MMMM_DD__YYYY___NIL: EOASEF!#REF!
Name Hedging_Positions_through_Futures_AS_ON_MMMM_DD__YYYY___NIL: EOCHIF!#REF!
Name Hedging_Positions_through_Futures_AS_ON_MMMM_DD__YYYY___NIL: EODWHF!#REF!
Name Hedging_Positions_through_Futures_AS_ON_MMMM_DD__YYYY___NIL: EOEDOF!#REF!
Name Hedging_Positions_through_Futures_AS_ON_MMMM_DD__YYYY___NIL: EOEMOP!#REF!
Name Hedging_Positions_through_Futures_AS_ON_MMMM_DD__YYYY___NIL: EOUSEF!#REF!
Name Hedging_Positions_through_Futures_AS_ON_MMMM_DD__YYYY___NIL: EOUSTF!#REF!
Name Hedging_Positions_through_Futures_AS_ON_MMMM_DD__YYYY___NIL: EDACBF!#REF!
Name JPM_Footer_disp: EDBE23!#REF!
Name JPM_Footer_disp: EDBE25!#REF!
Name JPM_Footer_disp: EDBE30!#REF!
Name JPM_Footer_disp: EDBE31!#REF!
Name JPM_Footer_disp: EDBE32!#REF!
Name JPM_Footer_disp: EDBPDF!#REF!
Name JPM_Footer_disp: EDCG27!#REF!
Name JPM_Footer_disp: EDCG37!#REF!
Name JPM_Footer_disp: EDCPSF!#REF!
Name JPM_Footer_disp: EDFF23!#REF!
Name JPM_Footer_disp: EDFF25!#REF!
Name JPM_Footer_disp: EDFF30!#REF!
Name JPM_Footer_disp: EDFF31!#REF!
Name JPM_Footer_disp: EDFF32!#REF!
Name JPM_Footer_disp: EDGSEC!#REF!
Name JPM_Footer_disp: EDNP27!#REF!

Sheet Index
A1: EDELWEISS MUTUAL FUND
A2: PORTFOLIO STATEMENT as on 31 Oct 02022
A3: Fund Id | B3: Fund Desc | C3: Scheme Risk- O - Meter | D3: Benchmark of the Scheme | E3: Benchmark Risk-o-meter | F3: Benchmark of the Scheme | G3: Benchmark Risk-o-meter
A4: EDACBF | B4: =HYPERLINK("[EDEL_Portfolio Monthly Notes 31-Oct-2022.xlsx]EDACBF!A1","Edelweiss Money Market Fund") -> Edelweiss Money Market Fund | D4: NIFTY Money Market Index B-I (TIER-1) | F4: NIFTY Money Market Index A-I (TIER-2)
A5: EDBE23 | B5: =HYPERLINK("[EDEL_Portfolio Monthly Notes 31-Oct-2022.xlsx]EDBE23!A1","BHARAT Bond ETF - April 2023") -> BHARAT Bond ETF - April 2023 | D5: NIFTY BHARAT Bond Index - April 2023
A6: EDBE25 | B6: =HYPERLINK("[EDEL_Portfolio Monthly Notes 31-Oct-2022.xlsx]EDBE25!A1","BHARAT Bond ETF - April 2025") -> BHARAT Bond ETF - April 2025 | D6: NIFTY BHARAT Bond Index - April 2025
A7: EDBE30 | B7: =HYPERLINK("[EDEL_Portfolio Monthly Notes 31-Oct-2022.xlsx]EDBE30!A1","BHARAT Bond ETF - April 2030") -> BHARAT Bond ETF - April 2030 | D7: NIFTY BHARAT Bond Index - April 2030
A8: EDBE31 | B8: =HYPERLINK("[EDEL_Portfolio Monthly Notes 31-Oct-2022.xlsx]EDBE31!A1","BHARAT Bond ETF - April 2031") -> BHARAT Bond ETF - April 2031 | D8: NIFTY BHARAT Bond Index - April 2031
A9: EDBE32 | B9: =HYPERLINK("[EDEL_Portfolio Monthly Notes 31-Oct-2022.xlsx]EDBE32!A1","BHARAT Bond ETF - April 2032") -> BHARAT Bond ETF - April 2032 | D9: Nifty BHARAT Bond Index – April 2032
A10: EDBPDF | B10: =HYPERLINK("[EDEL_Portfolio Monthly Notes 31-Oct-2022.xlsx]EDBPDF!A1","Edelweiss Banking and PSU Debt Fund") -> Edelweiss Banking and PSU Debt Fund | D10: NIFTY Banking and PSU Debt Index (TIER - 1) | F10: Nifty Banking & PSU Debt Index - A-III (TIER - 2)
A11: EDCG27 | B11: =HYPERLINK("[EDEL_Portfolio Monthly Notes 31-Oct-2022.xlsx]EDCG27!A1","Edelweiss CRISIL IBX 50 50 Gilt Plus SDL June 2027 Index Fund") -> Edelweiss CRISIL IBX 50 50 Gilt Plus SDL June 2027 Index Fund | D11: (CRISIL IBX 50:50 Gilt Plus SDL Index – June 2027
A12: EDCG37 | B12: =HYPERLINK("[EDEL_Portfolio Monthly Notes 31-Oct-2022.xlsx]EDCG37!A1","Edelweiss_CRISIL IBX 50 50 Gilt Plus SDL April 2037 Index Fund") -> Edelweiss_CRISIL IBX 50 50 Gilt Plus SDL April 2037 Index Fund | D12: CRISIL IBX 50:50 Gilt Plus SDL Index – April 2037
A13: EDCPSF | B13: =HYPERLINK("[EDEL_Portfolio Monthly Notes 31-Oct-2022.xlsx]EDCPSF!A1","Edelweiss CRL PSU PL SDL 50 50 Oct-25 FD") -> Edelweiss CRL PSU PL SDL 50 50 Oct-25 FD | D13: CRISIL [IBX] 50:50 PSU + SDL Index - October 2025
A14: EDFF23 | B14: =HYPERLINK("[EDEL_Portfolio Monthly Notes 31-Oct-2022.xlsx]EDFF23!A1","BHARAT Bond FOF - April 2023") -> BHARAT Bond FOF - April 2023 | D14: NIFTY BHARAT Bond Index - April 2023
A15: EDFF25 | B15: =HYPERLINK("[EDEL_Portfolio Monthly Notes 31-Oct-2022.xlsx]EDFF25!A1","BHARAT Bond FOF - April 2025") -> BHARAT Bond FOF - April 2025 | D15: Nifty BHARAT Bond Index – April 2025
A16: EDFF30 | B16: =HYPERLINK("[EDEL_Portfolio Monthly Notes 31-Oct-2022.xlsx]EDFF30!A1","BHARAT Bond FOF - April 2030") -> BHARAT Bond FOF - April 2030 | D16: NIFTY BHARAT Bond Index - April 2030
A17: EDFF31 | B17: =HYPERLINK("[EDEL_Portfolio Monthly Notes 31-Oct-2022.xlsx]EDFF31!A1","BHARAT Bond FOF - April 2031") -> BHARAT Bond FOF - April 2031 | D17: NIFTY BHARAT Bond Index - April 2031
A18: EDFF32 | B18: =HYPERLINK("[EDEL_Portfolio Monthly Notes 31-Oct-2022.xlsx]EDFF32!A1","BHARAT Bond FOF - April 2032") -> BHARAT Bond FOF - April 2032 | D18: Nifty BHARAT Bond Index – April 2032
A19: EDGSEC | B19: =HYPERLINK("[EDEL_Portfolio Monthly Notes 31-Oct-2022.xlsx]EDGSEC!A1","Edelweiss Government Securities Fund") -> Edelweiss Government Securities Fund | D19: NIFTY All Duration G-Sec Index (TIER - 1) | F19: Nifty G -Sec Index A -III (TIER - 2)
A20: EDNP27 | B20: =HYPERLINK("[EDEL_Portfolio Monthly Notes 31-Oct-2022.xlsx]EDNP27!A1","Edelweiss Nifty PSU Bond Plus SDL Apr2027 50 50 Index") -> Edelweiss Nifty PSU Bond Plus SDL Apr2027 50 50 Index | D20: Nifty PSU Bond Plus SDL Apr 2027 50:50 Index
A21: EDNPSF | B21: =HYPERLINK("[EDEL_Portfolio Monthly Notes 31-Oct-2022.xlsx]EDNPSF!A1","Edelweiss Nifty PSU Bond Plus SDL Apr2026 50 50 Index Fund") -> Edelweiss Nifty PSU Bond Plus SDL Apr2026 50 50 Index Fund | D21: Nifty PSU Bond Plus SDL Apr 2026 50:50 Index
A22: EDONTF | B22: =HYPERLINK("[EDEL_Portfolio Monthly Notes 31-Oct-2022.xlsx]EDONTF!A1","EDELWEISS OVERNIGHT FUND") -> EDELWEISS OVERNIGHT FUND | D22: NIFTY 1D Rate Index
A23: EEARBF | B23: =HYPERLINK("[EDEL_Portfolio Monthly Notes 31-Oct-2022.xlsx]EEARBF!A1","Edelweiss Arbitrage Fund") -> Edelweiss Arbitrage Fund | D23: Nifty 50 Arbitrage PR Index
A24: EEARFD | B24: =HYPERLINK("[EDEL_Portfolio Monthly Notes 31-Oct-2022.xlsx]EEARFD!A1","Edelweiss Balanced Advantage Fund") -> Edelweiss Balanced Advantage Fund | D24: NIFTY 50 Hybrid Composite debt 50:50 Index
A25: EEDGEF | B25: =HYPERLINK("[EDEL_Portfolio Monthly Notes 31-Oct-2022.xlsx]EEDGEF!A1","Edelweiss Large Cap Fund") -> Edelweiss Large Cap Fund | D25: Nifty 100 TRI
A26: EEECRF | B26: =HYPERLINK("[EDEL_Portfolio Monthly Notes 31-Oct-2022.xlsx]EEECRF!A1","Edelweiss Flexi-Cap Fund") -> Edelweiss Flexi-Cap Fund | D26: Nifty 500 Total Return Index
A27: EEELSS | B27: =HYPERLINK("[EDEL_Portfolio Monthly Notes 31-Oct-2022.xlsx]EEELSS!A1","Edelweiss Long Term Equity Fund") -> Edelweiss Long Term Equity Fund | D27: Nifty 500 Total Return Index
A28: EEEQTF | B28: =HYPERLINK("[EDEL_Portfolio Monthly Notes 31-Oct-2022.xlsx]EEEQTF!A1","Edelweiss Large & Mid Cap Fund") -> Edelweiss Large & Mid Cap Fund | D28: Nifty Large Midcap 250 Index - Total Return Index
A29: EEESCF | B29: =HYPERLINK("[EDEL_Portfolio Monthly Notes 31-Oct-2022.xlsx]EEESCF!A1","Edelweiss Small Cap Fund") -> Edelweiss Small Cap Fund | D29: Nifty Smallcap 250 TR Index
A30: EEESSF | B30: =HYPERLINK("[EDEL_Portfolio Monthly Notes 31-Oct-2022.xlsx]EEESSF!A1","Edelweiss Equity Savings Fund") -> Edelweiss Equity Savings Fund | D30: NIFTY Equity Savings Index
A31: EEFOCF | B31: =HYPERLINK("[EDEL_Portfolio Monthly Notes 31-Oct-2022.xlsx]EEFOCF!A1","Edelweiss Focused Equity Fund") -> Edelweiss Focused Equity Fund | D31: NIFTY 500 Total Return Index
A32: EEIF30 | B32: =HYPERLINK("[EDEL_Portfolio Monthly Notes 31-Oct-2022.xlsx]EEIF30!A1","Edelweiss Nifty 100 Quality 30 Index Fnd") -> Edelweiss Nifty 100 Quality 30 Index Fnd | D32: Nifty 100 Quality 30 TRI
A33: EEIF50 | B33: =HYPERLINK("[EDEL_Portfolio Monthly Notes 31-Oct-2022.xlsx]EEIF50!A1","Edelweiss Nifty 50 Index Fund") -> Edelweiss Nifty 50 Index Fund | D33: Nifty 50 TRI
A34: EELMIF | B34: =HYPERLINK("[EDEL_Portfolio Monthly Notes 31-Oct-2022.xlsx]EELMIF!A1","Edelweiss NIFTY Large Mid Cap 250 Index Fund") -> Edelweiss NIFTY Large Mid Cap 250 Index Fund | D34: NIFTY LargeMidcap 250 Index Total Return Index
A35: EEMOF1 | B35: =HYPERLINK("[EDEL_Portfolio Monthly Notes 31-Oct-2022.xlsx]EEMOF1!A1","EDELWEISS RECENTLY LISTED IPO FUND") -> EDELWEISS RECENTLY LISTED IPO FUND | D35: India Recent 100 IPO Index TRI
A36: EENFBA | B36: =HYPERLINK("[EDEL_Portfolio Monthly Notes 31-Oct-2022.xlsx]EENFBA!A1","Edelweiss ETF - Nifty Bank") -> Edelweiss ETF - Nifty Bank | D36: Nifty Bank TRI
A37: EEPRUA | B37: =HYPERLINK("[EDEL_Portfolio Monthly Notes 31-Oct-2022.xlsx]EEPRUA!A1","Edelweiss Aggressive Hybrid Fund") -> Edelweiss Aggressive Hybrid Fund | D37: CRISIL Hybrid 35+65 - Aggressive Index
A38: EESMCF | B38: =HYPERLINK("[EDEL_Portfolio Monthly Notes 31-Oct-2022.xlsx]EESMCF!A1","Edelweiss Mid Cap Fund") -> Edelweiss Mid Cap Fund | D38: Nifty Midcap 150 Total Return Index
A39: EGSFOF | B39: =HYPERLINK("[EDEL_Portfolio Monthly Notes 31-Oct-2022.xlsx]EGSFOF!A1","Edelweiss Gold and Silver ETF FOF") -> Edelweiss Gold and Silver ETF FOF | D39: LBMA Prices
A40: ELLIQF | B40: =HYPERLINK("[EDEL_Portfolio Monthly Notes 31-Oct-2022.xlsx]ELLIQF!A1","Edelweiss Liquid Fund") -> Edelweiss Liquid Fund | D40: NIFTY Liquid Index B-I (TIER-1) | F40: NIFTY Liquid Index A-I (TIER-2)
A41: EOASEF | B41: =HYPERLINK("[EDEL_Portfolio Monthly Notes 31-Oct-2022.xlsx]EOASEF!A1","Edelweiss ASEAN Equity Off-shore Fund") -> Edelweiss ASEAN Equity Off-shore Fund | D41: MSCI AC ASEAN 10/40 Index (Total Return Net)
A42: EOCHIF | B42: =HYPERLINK("[EDEL_Portfolio Monthly Notes 31-Oct-2022.xlsx]EOCHIF!A1","Edelweiss Greater China Equity Off-shore Fund") -> Edelweiss Greater China Equity Off-shore Fund | D42: MSCI Golden Dragon Index (Total Return Net)
A43: EODWHF | B43: =HYPERLINK("[EDEL_Portfolio Monthly Notes 31-Oct-2022.xlsx]EODWHF!A1","Edelweiss MSCI (I) DM & WD HC 45 ID Fund") -> Edelweiss MSCI (I) DM & WD HC 45 ID Fund | D43: MSCI India Domestic & World Healthcare 45 Index
A44: EOEDOF | B44: =HYPERLINK("[EDEL_Portfolio Monthly Notes 31-Oct-2022.xlsx]EOEDOF!A1","Edelweiss Europe Dynamic Equity Offshore Fund") -> Edelweiss Europe Dynamic Equity Offshore Fund | D44: MSCI Europe Index (Total Return Net)
A45: EOEMOP | B45: =HYPERLINK("[EDEL_Portfolio Monthly Notes 31-Oct-2022.xlsx]EOEMOP!A1","Edelweiss Emerging Markets Opportunities Equity Offshore Fund") -> Edelweiss Emerging Markets Opportunities Equity Offshore Fund | D45: MSCI Emerging Market Index
A46: EOUSEF | B46: =HYPERLINK("[EDEL_Portfolio Monthly Notes 31-Oct-2022.xlsx]EOUSEF!A1","Edelweiss US Value Equity Off-shore Fund") -> Edelweiss US Value Equity Off-shore Fund | D46: Russell 1000 Value Index
A47: EOUSTF | B47: =HYPERLINK("[EDEL_Portfolio Monthly Notes 31-Oct-2022.xlsx]EOUSTF!A1","EDELWEISS US TECHNOLOGY EQUITY FOF") -> EDELWEISS US TECHNOLOGY EQUITY FOF | D47: Russell 1000 Equal Weighted Technology Index

Sheet EDACBF
A1: PORTFOLIO STATEMENT OF EDELWEISS MONEY MARKET FUND AS ON OCTOBER 31, 2022 | H1: =HYPERLINK("[EDEL_Portfolio Monthly Notes 31-Oct-2022.xlsx]Index!A1","Index") -> Index
A2: (An open-ended debt scheme investing in money market instruments)
A4: Name of the Instrument | B4: ISIN | C4: Rating/Industry | D4: Quantity | E4: Market/Fair Value(Rs. In Lacs) | F4: % to Net Assets | G4: YIELD
A7: Equity & Equity related | E7: NIL | F7: NIL
A9: Money Market Instruments
A11: Treasury bills
A12: 364 DAYS TBILL RED 20-07-2023 | B12: IN002022Z168 | C12: SOVEREIGN | D12: 2500000 | E12: 2383.1 | F12: 0.0732 | G12: 0.0686
A13: Sub Total | E13: 2383.1 | F13: 0.0732
A14: Certificate of Deposit
A15: SIDBI CD RED 30-05-2023#** | B15: INE556F16960 | C15: CRISIL A1+ | D15: 2500000 | E15: 2399.04 | F15: 0.0737 | G15: 0.07315
A16: EXIM BANK CD RED 22-06-2023#** | B16: INE514E16CB6 | C16: CRISIL A1+ | D16: 2500000 | E16: 2388.4 | F16: 0.0734 | G16: 0.0732
A17: BANK OF BARODA CD RED 17-08-2023#** | B17: INE028A16CT7 | C17: ICRA A1+ | D17: 2500000 | E17: 2360.48 | F17: 0.0725 | G17: 0.07465
A18: CANARA BANK CD RED 18-08-2023#** | B18: INE476A16TV8 | C18: CRISIL A1+ | D18: 2500000 | E18: 2360.11 | F18: 0.0725 | G18: 0.0746
A19: KOTAK MAHINDRA BANK CD RED 17-08-2023#** | B19: INE237A169P8 | C19: CRISIL A1+ | D19: 2500000 | E19: 2359.84 | F19: 0.0725 | G19: 0.075016
A20: IDFC FIRST BANK LTD. CD RED 24-08-2023#** | B20: INE092T16SS1 | C20: CRISIL A1+ | D20: 2500000 | E20: 2353.52 | F20: 0.0723 | G20: 0.07675
A21: STATE BK OF INDIA CD 12-09-23#** | B21: INE062A16465 | C21: ICRA A1+ | D21: 2500000 | E21: 2350.69 | F21: 0.0722 | G21: 0.0736
A22: AXIS BANK LTD CD RED 07-09-2023#** | B22: INE238AD6025 | C22: CRISIL A1+ | D22: 2500000 | E22: 2348.98 | F22: 0.0722 | G22: 0.0757
A23: HDFC BANK CD RED 12-09-2023#** | B23: INE040A16DK9 | C23: CARE A1+ | D23: 2500000 | E23: 2347.07 | F23: 0.0721 | G23: 0.0755
A24: Sub Total | E24: 21268.13 | F24: 0.6534
A26: Commercial Paper
A27: LIC HSG FIN CP RED 20-06-2023** | B27: INE115A14DT5 | C27: CRISIL A1+ | D27: 2500000 | E27: 2386.57 | F27: 0.0733 | G27: 0.0751
A28: HDFC LTD CP RED 25-07-2023** | B28: INE001A14ZE2 | C28: CRISIL A1+ | D28: 2500000 | E28: 2368.48 | F28: 0.0728 | G28: 0.076199
A29: RELIANCE JIO INFO LTD CP 29-09-23** | B29: INE110L14RD7 | C29: CRISIL A1+ | D29: 2500000 | E29: 2336.47 | F29: 0.0718 | G29: 0.07695
A30: Sub Total | E30: 7091.52 | F30: 0.2179
A32: TOTAL | E32: 30742.75 | F32: 0.9445
A35: TREPS / Reverse Repo
A36: Clearing Corporation of India Ltd. | E36: 1926.68 | F36: 0.0592 | G36: 0.061074
A37: Sub Total | E37: 1926.68 | F37: 0.0592
A39: TOTAL | E39: 1926.68 | F39: 0.0592
A40: Accrued Interest | E40: 0.3223833 | F40: 9e-06
A41: Net Receivables/(Payables) | E41: -114.54238 | F41: -0.003709 | G41: 0.061074
A42: GRAND TOTAL | E42: 32555.21 | F42: 1
A44: # Unlisted Security
A45: **Non Traded Security
A47: Notes:
A48: 1. Security in default beyond its maturiy date | B48: NIL
A49: 2. NAV at the beginning of the period (Rs. per unit)
A50: Plan /option (Face Value 10) | B50: As on | C50: As on
B51: 44834 | C51: 44865
A52: Direct Plan Annual IDCW Option | B52: 25.7044 | C52: 25.7848
A53: Direct Plan Bonus Option | B53: ^ | C53: ^
A54: Direct Plan Growth Option | B54: 25.7074 | C54: 25.788
A55: Direct Plan IDCW Option | B55: 23.9731 | C55: 24.0482
A56: Institutional Annual IDCW Option | B56: ^ | C56: ^
A57: Institutional Growth Option | B57: 20.3396 | C57: 20.3906
A58: Institutional IDCW Option | B58: ^ | C58: ^
A59: Regular Plan - Annual IDCW Option | B59: 23.5681 | C59: 23.6274
A60: Regular Plan - Bonus Option | B60: ^ | C60: ^
A61: Regular Plan - Growth | B61: 23.7661 | C61: 23.8257
A62: Regular Plan - IDCW Option | B62: 22.3551 | C62: 22.4112
A63: Regular Plan Bonus Option | B63: ^ | C63: ^
A64: ^ There were no investors in this option.
A66: 3. Total Dividend (Net) declared during the month | B66: NIL
A67: 4. Bonus was declared during the month | B67: NIL
A68: 5. Investment in Repo of Corporate Debt Securities during the month ended October 31, 2022 | B68: NIL
A69: 6. Investment in foreign securities/ADRs/GDRs at the end of the month | B69: NIL
A70: 7. Average Portfolio Maturity | B70: 0.723115
A71: 8. Total gross exposure to derivative instruments (excluding reversed positions) at the end of the month (Rs. in Lakhs) | B71: NIL
A72: 9. Margin Deposits includes Margin money placed on derivatives other than margin money placed with bank | B72: NIL
A73: 10. Value of investment made by other schemes under same management (Rs. In Lakhs) | B73: NIL
A74: 11. Number of instance of deviation In valuation of securities | B74: NIL
A75: 12. Total value and percentage of illiquid equity shares / securities | B75: NIL
A78: Scheme Name | B78: Risk- O - Meter | C78: Benchmark of the Scheme | D78: Benchmark Risk-o-meter | E78: Benchmark of the Scheme | F78: Benchmark Risk-o-meter
A79: Edelweiss Money Market Fund | C79: NIFTY Money Market Index B-I (TIER-1) | E79: NIFTY Money Market Index A-I (TIER-2)

Sheet EDBE23
A1: PORTFOLIO STATEMENT OF BHARAT BOND ETF – APRIL 2023 AS ON OCTOBER 31, 2022 | H1: =HYPERLINK("[EDEL_Portfolio Monthly Notes 31-Oct-2022.xlsx]Index!A1","Index") -> Index
A2: (An open ended Target Maturity Exchange Traded Bond Fund predominately investing in constituents of Nifty BHARAT Bond Index - April 2023)
A4: Name of the Instrument | B4: ISIN | C4: Rating/Industry | D4: Quantity | E4: Market/Fair Value(Rs. In Lacs) | F4: % to Net Assets | G4: YIELD
A7: Equity & Equity related | E7: NIL | F7: NIL
A9: Debt Instruments
A10: (a)Listed / Awaiting listing on stock Exchanges
A11: 6.59% IRFC NCD RED 14-04-2023** | B11: INE053F07BZ2 | C11: CRISIL AAA | D11: 100500000 | E11: 100177.6 | F11: 0.1475 | G11: 0.07305
A12: 6.44% INDIAN OIL CORP NCD RED 14-04-2023** | B12: INE242A08445 | C12: CRISIL AAA | D12: 77000000 | E12: 76726.73 | F12: 0.1129 | G12: 0.0728
A13: 7.04% PFC LTD NCD RED 14-04-2023** | B13: INE134E08KJ6 | C13: CRISIL AAA | D13: 70000000 | E13: 69915.37 | F13: 0.1029 | G13: 0.07345
A14: 6.79% HUDCO NCD RED 14-04-2023** | B14: INE031A08764 | C14: ICRA AAA | D14: 68000000 | E14: 67857.47 | F14: 0.0999 | G14: 0.07285
A15: 6.72% NABARD NCD RED 14-04-2023** | B15: INE261F08BW6 | C15: ICRA AAA | D15: 64300000 | E15: 64065.05 | F15: 0.0943 | G15: 0.072901
A16: 7.12% REC LTD. NCD RED 31-03-2023** | B16: INE020B08CH4 | C16: CRISIL AAA | D16: 44000000 | E16: 43935.67 | F16: 0.0647 | G16: 0.07185
A17: 6.38% HPCL NCD RED 12-04-2023** | B17: INE094A08051 | C17: CRISIL AAA | D17: 36500000 | E17: 36364.48 | F17: 0.0535 | G17: 0.07245
A18: 8.82% REC LTD NCD RED 12-04-23** | B18: INE020B08831 | C18: CARE AAA | D18: 33000000 | E18: 33158.1 | F18: 0.0488 | G18: 0.073451
A19: 6.64% MANGALORE REF & PET NCD 14-04-2023** | B19: INE103A08027 | C19: CRISIL AAA | D19: 26000000 | E19: 25915.24 | F19: 0.0381 | G19: 0.07415
A20: 8.8% POWER GRID CORP NCD RED 13-03-2023** | B20: INE752E07KN9 | C20: CRISIL AAA | D20: 22500000 | E20: 22600.71 | F20: 0.0333 | G20: 0.071299
A21: 8.5% NABARD NCD RED 31-01-2023 | B21: INE261F08AT4 | C21: CRISIL AAA | D21: 18000000 | E21: 18045.67 | F21: 0.0266 | G21: 0.070169
A22: 6.35% POWER GRID CORP NCD RED 14-04-2023** | B22: INE752E08627 | C22: CRISIL AAA | D22: 10000000 | E22: 9965.08 | F22: 0.0147 | G22: 0.07185
... A35: 8.9% POWER FIN CORP NCD RED 18-03-2023** | B35: INE134E08FN8 | C35: CRISIL AAA | D35: 500000 | E35: 502.45 | F35: 0.0007 | G35: 0.0716
A36: Sub Total | E36: 616867.1 | F36: 0.908
A38: (b)Privately Placed/Unlisted
A39: Sub Total | E39: NIL | F39: NIL
A41: (c)Securitised Debt Instruments
A42: Sub Total | E42: NIL | F42: NIL
A44: TOTAL | E44: 616867.1 | F44: 0.908
A46: Money Market Instruments
A47: Certificate of Deposit
A48: SIDBI CD RED 23-03-2023#** | B48: INE556F16952 | C48: CRISIL A1+ | D48: 12500000 | E48: 12166.78 | F48: 0.0179 | G48: 0.0704
A49: NABARD CD RED 08-02-2023# | B49: INE261F16637 | C49: CRISIL A1+ | D49: 10000000 | E49: 9812.72 | F49: 0.0144 | G49: 0.070365
A50: SIDBI CD RED 03-03-2023#** | B50: INE556F16945 | C50: CRISIL A1+ | D50: 10000000 | E50: 9770.1 | F50: 0.0144 | G50: 0.0704
A51: EXIM BANK CD RED 17-03-2023#** | B51: INE514E16BY0 | C51: CRISIL A1+ | D51: 5000000 | E51: 4872.64 | F51: 0.0072 | G51: 0.070151
A52: Sub Total | E52: 36622.24 | F52: 0.0539
A54: TOTAL | E54: 36622.24 | F54: 0.0539
A57: TREPS / Reverse Repo
A58: Clearing Corporation of India Ltd. | E58: 2708.55 | F58: 0.004 | G58: 0.061074
A59: Sub Total | E59: 2708.55 | F59: 0.004
A61: TOTAL | E61: 2708.55 | F61: 0.004
A62: Accrued Interest | E62: 25672.343 | F62: 0.037787
A63: Net Receivables/(Payables) | E63: -2485.4127 | F63: -0.003687 | G63: 0.061074
A64: GRAND TOTAL | E64: 679384.82 | F64: 1
A66: # Unlisted Security
A67: **Non Traded Security
A69: Notes:
A70: 1. Security in default beyond its maturiy date | B70: NIL
A71: 2. NAV at the beginning of the period (Rs. per unit)
A72: Plan /option (Face Value 1000) | B72: As on | C72: As on
B73: 44834 | C73: 44865
A74: Growth Option | B74: 1188.3683 | C74: 1193.4978
A76: 3. Total Dividend (Net) declared during the month | B76: NIL
A77: 4. Bonus was declared during the month | B77: NIL
A78: 5. Investment in Repo of Corporate Debt Securities during the month ended October 31, 2022 | B78: NIL
A79: 6. Investment in foreign securities/ADRs/GDRs at the end of the month | B79: NIL
A80: 7. Average Portfolio Maturity | B80: 0.42289279
A81: 8. Total gross exposure to derivative instruments (excluding reversed positions) at the end of the month (Rs. in Lakhs) | B81: NIL
A82: 9. Margin Deposits includes Margin money placed on derivatives other than margin money placed with bank | B82: NIL
A83: 10. Value of investment made by other schemes under same management (Rs. In Lakhs) | B83: =EDFF23!E11 -> 329431.29
A84: 11. Number of instance of deviation In valuation of securities | B84: NIL
A85: 12. Total value and percentage of illiquid equity shares / securities | B85: NIL
A87: Scheme Name | B87: Risk- O - Meter | C87: Benchmark of the Scheme | D87: Benchmark Risk-o-meter
A88: BHARAT Bond ETF - April 2023 | C88: NIFTY BHARAT Bond Index - April 2023

Sheet EDBE25
A1: PORTFOLIO STATEMENT OF BHARAT BOND ETF – APRIL 2025 AS ON OCTOBER 31, 2022 | H1: =HYPERLINK("[EDEL_Portfolio Monthly Notes 31-Oct-2022.xlsx]Index!A1","Index") -> Index
A2: (An open ended Target Maturity Exchange Traded Bond Fund predominantly investing in constituents of Nifty BHARAT Bond Index - April 2025)
A4: Name of the Instrument | B4: ISIN | C4: Rating/Industry | D4: Quantity | E4: Market/Fair Value(Rs. In Lacs) | F4: % to Net Assets | G4: YIELD
A7: Equity & Equity related | E7: NIL | F7: NIL
A9: Debt Instruments
A10: (a)Listed / Awaiting listing on stock Exchanges
A11: 5.4% INDIAN OIL CORP NCD 11-04-25** | B11: INE242A08478 | C11: CRISIL AAA | D11: 85000000 | E11: 81121.11 | F11: 0.0807 | G11: 0.07515
A12: 5.36% HPCL NCD RED 11-04-2025** | B12: INE094A08077 | C12: CRISIL AAA | D12: 83500000 | E12: 79674.45 | F12: 0.0793 | G12: 0.074825
A13: 5.59% SIDBI NCD RED 21-02-2025** | B13: INE556F08JU6 | C13: CARE AAA | D13: 72500000 | E13: 69566.58 | F13: 0.0692 | G13: 0.07545
A14: 5.90% REC LTD. NCD RED 31-03-2025** | B14: INE020B08CZ6 | C14: CRISIL AAA | D14: 71500000 | E14: 68984.84 | F14: 0.0686 | G14: 0.0755
A15: 5.47% NABARD NCD RED 11-04-2025** | B15: INE261F08CI3 | C15: ICRA AAA | D15: 66500000 | E15: 63498.92 | F15: 0.0632 | G15: 0.0754
A16: 5.77% PFC LTD NCD RED 11-04-2025** | B16: INE134E08KX7 | C16: CRISIL AAA | D16: 65000000 | E16: 62502.96 | F16: 0.0622 | G16: 0.0755
A17: 5.23% NABARD NCD RED 31-01-2025** | B17: INE261F08DI1 | C17: CRISIL AAA | D17: 61000000 | E17: 58159.23 | F17: 0.0579 | G17: 0.0754
A18: 6.88% NHB LTD NCD RED 21-01-2025** | B18: INE557F08FH9 | C18: CRISIL AAA | D18: 55500000 | E18: 54855.03 | F18: 0.0546 | G18: 0.07445
A19: 5.35% HUDCO NCD RED 11-04-2025** | B19: INE031A08814 | C19: ICRA AAA | D19: 54000000 | E19: 51444.02 | F19: 0.0512 | G19: 0.07545
A20: 6.35% EXIM BANK OF INDIA NCD 18-02-2025** | B20: INE514E08FT8 | C20: CRISIL AAA | D20: 46000000 | E20: 44980.96 | F20: 0.0448 | G20: 0.0741
A21: 5.25% ONGC NCD RED 11-04-2025** | B21: INE213A08016 | C21: ICRA AAA | D21: 41500000 | E21: 39562.2 | F21: 0.0394 | G21: 0.0741
A22: 5.34% NLC INDIA LTD. NCD 11-04-25** | B22: INE589A08027 | C22: CRISIL AAA | D22: 39500000 | E22: 37666.53 | F22: 0.0375 | G22: 0.074898
... A60: 8.10% PFC LTD NCD RED 04-06-2024** | B60: INE134E08KD9 | C60: CRISIL AAA | D60: 500000 | E60: 503.62 | F60: 0.0005 | G60: 0.0755
A61: Sub Total | E61: 973790.02 | F61: 0.9687
A63: (b)Privately Placed/Unlisted
A64: Sub Total | E64: NIL | F64: NIL
A66: (c)Securitised Debt Instruments
A67: Sub Total | E67: NIL | F67: NIL
A69: TOTAL | E69: 973790.02 | F69: 0.9687
A72: TREPS / Reverse Repo
A73: Clearing Corporation of India Ltd. | E73: 6160.97 | F73: 0.0061 | G73: 0.061074
A74: Sub Total | E74: 6160.97 | F74: 0.0061
A76: TOTAL | E76: 6160.97 | F76: 0.0061
A77: Accrued Interest | E77: 29557.76 | F77: 0.029409
A78: Net Receivables/(Payables) | E78: -4471.2101 | F78: -0.004209 | G78: 0.061074
A79: GRAND TOTAL | E79: 1005037.5 | F79: 1
A81: **Non Traded Security
A84: Notes:
A85: 1. Security in default beyond its maturiy date | B85: NIL
A86: 2. NAV at the beginning of the period (Rs. per unit)
A87: Plan /option (Face Value 1000) | B87: As on | C87: As on
B88: 44834 | C88: 44865
A89: Growth Option | B89: 1078.3791 | C89: 1082.7518
A91: 3. Total Dividend (Net) declared during the month | B91: NIL
A92: 4. Bonus was declared during the month | B92: NIL
A93: 5. Investment in Repo of Corporate Debt Securities during the month ended October 31, 2022 | B93: NIL
A94: 6. Investment in foreign securities/ADRs/GDRs at the end of the month | B94: NIL
A95: 7. Average Portfolio Maturity | B95: 2.3138026
A96: 8. Total gross exposure to derivative instruments (excluding reversed positions) at the end of the month (Rs. in Lakhs) | B96: NIL
A97: 9. Margin Deposits includes Margin money placed on derivatives other than margin money placed with bank | B97: NIL
A98: 10. Value of investment made by other schemes under same management (Rs. In Lakhs) | B98: =EDFF25!E11 -> 394173.32
A99: 11. Number of instance of deviation In valuation of securities | B99: NIL
A100: 12. Total value and percentage of illiquid equity shares / securities | B100: NIL
A103: Scheme Name | B103: Risk- O - Meter | C103: Benchmark of the Scheme | D103: Benchmark Risk-o-meter
A104: BHARAT Bond ETF - April 2025 | C104: NIFTY BHARAT Bond Index - April 2025

Sheet EDBE30
A1: PORTFOLIO STATEMENT OF BHARAT BOND ETF – APRIL 2030 AS ON OCTOBER 31, 2022 | H1: =HYPERLINK("[EDEL_Portfolio Monthly Notes 31-Oct-2022.xlsx]Index!A1","Index") -> Index
A2: (An open ended Target Maturity Exchange Traded Bond Fund predominately investing in constituents of Nifty BHARAT Bond Index - April 2030)
A4: Name of the Instrument | B4: ISIN | C4: Rating/Industry | D4: Quantity | E4: Market/Fair Value(Rs. In Lacs) | F4: % to Net Assets | G4: YIELD
A7: Equity & Equity related | E7: NIL | F7: NIL
A9: Debt Instruments
A10: (a)Listed / Awaiting listing on stock Exchanges
A11: 7.03% HPCL NCD RED 12-04-2030** | B11: INE094A08069 | C11: CRISIL AAA | D11: 97500000 | E11: 94001.02 | F11: 0.0647 | G11: 0.076724
A12: 7.41% POWER FIN CORP NCD RED 25-02-2030** | B12: INE134E08KL2 | C12: CRISIL AAA | D12: 89500000 | E12: 88179.34 | F12: 0.0606 | G12: 0.0767
A13: 7.89% REC LTD. NCD RED 30-03-2030** | B13: INE020B08CI2 | C13: CRISIL AAA | D13: 81000000 | E13: 81900.15 | F13: 0.0563 | G13: 0.07675
A14: 7.34% NPCIL NCD RED 23-01-2030** | B14: INE206D08469 | C14: ICRA AAA | D14: 83000000 | E14: 81548.99 | F14: 0.0561 | G14: 0.07655
A15: 7.55% IRFC NCD RED 12-04-2030** | B15: INE053F07BY5 | C15: CRISIL AAA | D15: 80500000 | E15: 80188.95 | F15: 0.0552 | G15: 0.07625
A16: 7.86% PFC LTD NCD RED 12-04-2030** | B16: INE134E08KK4 | C16: CRISIL AAA | D16: 75000000 | E16: 75773.48 | F16: 0.0521 | G16: 0.0767
A17: 7.54% NHAI NCD RED 25-01-2030** | B17: INE906B07HK9 | C17: CRISIL AAA | D17: 73000000 | E17: 72510.17 | F17: 0.0499 | G17: 0.07655
A18: 7.4% MANGALORE REF & PET NCD 12-04-2030** | B18: INE103A08019 | C18: CRISIL AAA | D18: 61500000 | E18: 60508.07 | F18: 0.0416 | G18: 0.076898
A19: 7.70% NHAI NCD RED 13-09-2029** | B19: INE906B07HH5 | C19: CRISIL AAA | D19: 54500000 | E19: 54652.16 | F19: 0.0376 | G19: 0.0764
A20: 7.41% IOC NCD RED 22-10-2029** | B20: INE242A08437 | C20: FITCH AAA | D20: 48000000 | E20: 47378.88 | F20: 0.0326 | G20: 0.07655
A21: 7.50% REC LTD. NCD RED 28-02-2030** | B21: INE020B08CP7 | C21: CRISIL AAA | D21: 41200000 | E21: 40781.86 | F21: 0.028 | G21: 0.07675
A22: 7.32% NTPC LTD NCD RED 17-07-2029** | B22: INE733E07KL3 | C22: CRISIL AAA | D22: 39500000 | E22: 38933.33 | F22: 0.0268 | G22: 0.0759
... A60: 8.4% POWER GRID NCD RED 26-05-2029** | B60: INE752E07MV8 | C60: CRISIL AAA | D60: 500000 | E60: 519.33 | F60: 0.0004 | G60: 0.07615
A61: Sub Total | E61: 1268743.7 | F61: 0.8727
A63: Government Securities
A64: 7.10% GOVT OF INDIA RED 18-04-2029 | B64: IN0020220011 | C64: SOVEREIGN | D64: 68500000 | E64: 67360.02 | F64: 0.0463 | G64: 0.07428
A65: 6.45% GOVT OF INDIA RED 07-10-2029 | B65: IN0020190362 | C65: SOVEREIGN | D65: 33000000 | E65: 31273.11 | F65: 0.0215 | G65: 0.074281
A66: 6.79% GOVT OF INDIA RED 26-12-2029 | B66: IN0020160118 | C66: SOVEREIGN | D66: 25500000 | E66: 24569.71 | F66: 0.0169 | G66: 0.074549
A67: 7.88% GOVT OF INDIA RED 19-03-2030 | B67: IN0020150028 | C67: SOVEREIGN | D67: 4000000 | E67: 4099.99 | F67: 0.0028 | G67: 0.074317
A68: Sub Total | E68: 127302.83 | F68: 0.0875
A70: (b)Privately Placed/Unlisted
A71: Sub Total | E71: NIL | F71: NIL
A73: (c)Securitised Debt Instruments
A74: Sub Total | E74: NIL | F74: NIL
A76: TOTAL | E76: 1396046.5 | F76: 0.9602
A79: TREPS / Reverse Repo
A80: Clearing Corporation of India Ltd. | E80: 8111.64 | F80: 0.0056 | G80: 0.061074
A81: Sub Total | E81: 8111.64 | F81: 0.0056
A83: TOTAL | E83: 8111.64 | F83: 0.0056
A84: Accrued Interest | E84: 49745.215 | F84: 0.034213
A85: Net Receivables/(Payables) | E85: 46.315332 | F85: -1.3e-05 | G85: 0.061074
A86: GRAND TOTAL | E86: 1453949.7 | F86: 1
A88: **Non Traded Security
A91: Notes:
A92: 1. Security in default beyond its maturiy date | B92: NIL
A93: 2. NAV at the beginning of the period (Rs. per unit)
A94: Plan /option (Face Value 1000) | B94: As on | C94: As on
B95: 44834 | C95: 44865
A96: Growth Option | B96: 1204.1492 | C96: 1210.5522
A98: 3. Total Dividend (Net) declared during the month | B98: NIL
A99: 4. Bonus was declared during the month | B99: NIL
A100: 5. Investment in Repo of Corporate Debt Securities during the month ended October 31, 2022 | B100: NIL
A101: 6. Investment in foreign securities/ADRs/GDRs at the end of the month | B101: NIL
A102: 7. Average Portfolio Maturity | B102: 7.0990079
A103: 8. Total gross exposure to derivative instruments (excluding reversed positions) at the end of the month (Rs. in Lakhs) | B103: NIL
A104: 9. Margin Deposits includes Margin money placed on derivatives other than margin money placed with bank | B104: NIL
A105: 10. Value of investment made by other schemes under same management (Rs. In Lakhs) | B105: =EDFF30!E11 -> 461517.96
A106: 11. Number of instance of deviation In valuation of securities | B106: NIL
A107: 12. Total value and percentage of illiquid equity shares / securities | B107: NIL
A109: Scheme Name | B109: Risk- O - Meter | C109: Benchmark of the Scheme | D109: Benchmark Risk-o-meter
A110: BHARAT Bond ETF - April 2030 | C110: NIFTY BHARAT Bond Index - April 2030

Sheet EDBE31
A1: PORTFOLIO STATEMENT OF BHARAT BOND ETF – APRIL 2031 AS ON OCTOBER 31, 2022 | H1: =HYPERLINK("[EDEL_Portfolio Monthly Notes 31-Oct-2022.xlsx]Index!A1","Index") -> Index
A2: (An open ended Target Maturity Exchange Traded Bond Fund predominantly investing in constituents of Nifty BHARAT Bond Index - April 2031)
A4: Name of the Instrument | B4: ISIN | C4: Rating/Industry | D4: Quantity | E4: Market/Fair Value(Rs. In Lacs) | F4: % to Net Assets | G4: YIELD
A7: Equity & Equity related | E7: NIL | F7: NIL
A9: Debt Instruments
A10: (a)Listed / Awaiting listing on stock Exchanges
A11: 6.41% IRFC NCD RED 11-04-2031** | B11: INE053F07CR7 | C11: CRISIL AAA | D11: 102000000 | E11: 94253.1 | F11: 0.084 | G11: 0.07655
A12: 6.90% REC LTD. NCD RED 31-03-2031** | B12: INE020B08DA7 | C12: CRISIL AAA | D12: 97500000 | E12: 92780.9 | F12: 0.0827 | G12: 0.077
A13: 6.45% NABARD NCD RED 11-04-2031** | B13: INE261F08CJ1 | C13: ICRA AAA | D13: 100000000 | E13: 92329 | F13: 0.0823 | G13: 0.0771
A14: 6.50% NHAI NCD RED 11-04-2031** | B14: INE906B07IE0 | C14: CRISIL AAA | D14: 98500000 | E14: 91426.12 | F14: 0.0815 | G14: 0.07685
A15: 6.80% NPCL NCD RED 21-03-2031** | B15: INE206D08477 | C15: ICRA AAA | D15: 96000000 | E15: 90840.38 | F15: 0.081 | G15: 0.076833
A16: 6.88% PFC LTD NCD RED 11-04-2031** | B16: INE134E08KY5 | C16: CRISIL AAA | D16: 95500000 | E16: 90775.52 | F16: 0.0809 | G16: 0.07695
A17: 6.4% ONGC NCD RED 11-04-2031** | B17: INE213A08024 | C17: ICRA AAA | D17: 82000000 | E17: 76019.74 | F17: 0.0678 | G17: 0.075999
A18: 6.29% NTPC LTD NCD RED 11-04-2031** | B18: INE733E08155 | C18: CRISIL AAA | D18: 80000000 | E18: 73420.56 | F18: 0.0655 | G18: 0.07645
A19: 6.63% HPCL NCD RED 11-04-2031** | B19: INE094A08093 | C19: CRISIL AAA | D19: 71500000 | E19: 66787.79 | F19: 0.0596 | G19: 0.077123
A20: 6.65% FOOD CORP GOI GRNT NCD 23-10-2030** | B20: INE861G08076 | C20: ICRA AAA(CE) | D20: 67000000 | E20: 63028.17 | F20: 0.0562 | G20: 0.0767
A21: 6.28% POWER GRID CORP NCD 11-04-31** | B21: INE752E08650 | C21: CRISIL AAA | D21: 38500000 | E21: 35245.09 | F21: 0.0314 | G21: 0.07675
A22: 7.55% REC LTD. NCD RED 10-05-2030** | B22: INE020B08CU7 | C22: CRISIL AAA | D22: 24000000 | E22: 23816.66 | F22: 0.0212 | G22: 0.07675
... A38: 6.75% HUDCO NCD RED 29-05-2030** | B38: INE031A08806 | C38: ICRA AAA | D38: 500000 | E38: 473.59 | F38: 0.0004 | G38: 0.07685
A39: Sub Total | E39: 974293.05 | F39: 0.8688
A41: Government Securities
A42: 7.61% GOVT OF INDIA RED 09-05-2030 | B42: IN0020160019 | C42: SOVEREIGN | D42: 57000000 | E42: 57615.32 | F42: 0.0514 | G42: 0.074196
A43: 7.10% GOVT OF INDIA RED 18-04-2029 | B43: IN0020220011 | C43: SOVEREIGN | D43: 54000000 | E43: 53101.33 | F43: 0.0474 | G43: 0.07428
A44: Sub Total | E44: 110716.65 | F44: 0.0988
A46: (b)Privately Placed/Unlisted
A47: Sub Total | E47: NIL | F47: NIL
A49: (c)Securitised Debt Instruments
A50: Sub Total | E50: NIL | F50: NIL
A52: TOTAL | E52: 1085009.7 | F52: 0.9676
A55: TREPS / Reverse Repo
A56: Clearing Corporation of India Ltd. | E56: 9210.46 | F56: 0.0082 | G56: 0.061074
A57: Sub Total | E57: 9210.46 | F57: 0.0082
A59: TOTAL | E59: 9210.46 | F59: 0.0082
A60: Accrued Interest | E60: 27158.772 | F60: 0.024217
A61: Net Receivables/(Payables) | E61: 54.637718 | F61: -1.7e-05 | G61: 0.061074
A62: GRAND TOTAL | E62: 1121433.6 | F62: 1
A64: **Non Traded Security
A67: Notes:
A68: 1. Security in default beyond its maturiy date | B68: NIL
A69: 2. NAV at the beginning of the period (Rs. per unit)
A70: Plan /option (Face Value 1000) | B70: As on | C70: As on
B71: 44834 | C71: 44865
A72: Growth Option | B72: 1071.8013 | C72: 1079.1361
A74: 3. Total Dividend (Net) declared during the month | B74: NIL
A75: 4. Bonus was declared during the month | B75: NIL
A76: 5. Investment in Repo of Corporate Debt Securities during the month ended October 31, 2022 | B76: NIL
A77: 6. Investment in foreign securities/ADRs/GDRs at the end of the month | B77: NIL
A78: 7. Average Portfolio Maturity | B78: 8.1404853
A79: 8. Total gross exposure to derivative instruments (excluding reversed positions) at the end of the month (Rs. in Lakhs) | B79: NIL
A80: 9. Margin Deposits includes Margin money placed on derivatives other than margin money placed with bank | B80: NIL
A81: 10. Value of investment made by other schemes under same management (Rs. In Lakhs) | B81: =EDFF31!$E$11 -> 326244.72
A82: 11. Number of instance of deviation In valuation of securities | B82: NIL
A83: 12. Total value and percentage of illiquid equity shares / securities | B83: NIL
A85: Scheme Name | B85: Risk- O - Meter | C85: Benchmark of the Scheme | D85: Benchmark Risk-o-meter
A86: BHARAT Bond ETF - April 2031 | C86: NIFTY BHARAT Bond Index - April 2031

Sheet EDBE32
A1: PORTFOLIO STATEMENT OF BHARAT BOND ETF – APRIL 2032 AS ON OCTOBER 31, 2022 | H1: =HYPERLINK("[EDEL_Portfolio Monthly Notes 31-Oct-2022.xlsx]Index!A1","Index") -> Index
A2: (An open ended Target Maturity Exchange Traded Bond Fund predominantly investing in constituents of Nifty BHARAT Bond Index - April 2032)
A4: Name of the Instrument | B4: ISIN | C4: Rating/Industry | D4: Quantity | E4: Market/Fair Value(Rs. In Lacs) | F4: % to Net Assets | G4: YIELD
A7: Equity & Equity related | E7: NIL | F7: NIL
A9: Debt Instruments
A10: (a)Listed / Awaiting listing on stock Exchanges
A11: 7.48% MANGALORE REF&PET 14-04-2032** | B11: INE103A08050 | C11: CARE AAA | D11: 83700000 | E11: 82379.63 | F11: 0.1062 | G11: 0.077198
A12: 6.74% NTPC LTD RED 14-04-2032** | B12: INE733E08205 | C12: CRISIL AAA | D12: 84500000 | E12: 79401.19 | F12: 0.1024 | G12: 0.0766
A13: 6.87% NHAI NCD RED 14-04-2032** | B13: INE906B07JA6 | C13: CRISIL AAA | D13: 82000000 | E13: 77620.05 | F13: 0.1001 | G13: 0.07685
A14: 6.92% POWER FINANCE NCD 14-04-32** | B14: INE134E08LN6 | C14: CRISIL AAA | D14: 80000000 | E14: 75938.72 | F14: 0.0979 | G14: 0.07695
A15: 6.92% REC LTD NCD RED 20-03-2032** | B15: INE020B08DV3 | C15: CRISIL AAA | D15: 80000000 | E15: 75888.48 | F15: 0.0978 | G15: 0.077
A16: 6.87% IRFC NCD RED 14-04-2032** | B16: INE053F08163 | C16: CRISIL AAA | D16: 75000000 | E16: 71154.68 | F16: 0.0917 | G16: 0.07655
A17: 7.79% IOC NCD RED 12-04-2032** | B17: INE242A08528 | C17: CRISIL AAA | D17: 50500000 | E17: 50691.55 | F17: 0.0654 | G17: 0.077249
A18: 6.85% NABARD NCD RED 14-04-2032** | B18: INE261F08DL5 | C18: CRISIL AAA | D18: 50000000 | E18: 47155.8 | F18: 0.0608 | G18: 0.0771
A19: 7.81% HPCL NCD RED 13-04-2032** | B19: INE094A08119 | C19: CRISIL AAA | D19: 39500000 | E19: 39734.47 | F19: 0.0512 | G19: 0.077123
A20: 6.85% NLC INDIA RED 13-04-2032** | B20: INE589A08043 | C20: CRISIL AAA | D20: 38000000 | E20: 35813.63 | F20: 0.0462 | G20: 0.0773
A21: 6.92% IRFC NCD SR 161 RED 29-08-2031** | B21: INE053F08122 | C21: CRISIL AAA | D21: 16500000 | E21: 15736.73 | F21: 0.0203 | G21: 0.07655
A22: 6.89% IRFC NCD RED 18-07-2031** | B22: INE053F08106 | C22: CRISIL AAA | D22: 14000000 | E22: 13331.58 | F22: 0.0172 | G22: 0.07655
... A26: 8.24% NHPC LTD SER U NCD RED 27-06-2031** | B26: INE848E07914 | C26: CARE AAA | D26: 1000000 | E26: 1032.53 | F26: 0.0013 | G26: 0.077
A27: Sub Total | E27: 686629.43 | F27: 0.8852
A29: Government Securities
A30: 6.54% GOVT OF INDIA RED 17-01-2032 | B30: IN0020210244 | C30: SOVEREIGN | D30: 51500000 | E30: 48307.15 | F30: 0.0623 | G30: 0.074812
A31: Sub Total | E31: 48307.15 | F31: 0.0623
A33: (b)Privately Placed/Unlisted
A34: Sub Total | E34: NIL | F34: NIL
A36: (c)Securitised Debt Instruments
A37: Sub Total | E37: NIL | F37: NIL
A39: TOTAL | E39: 734936.58 | F39: 0.9475
A42: TREPS / Reverse Repo
A43: Clearing Corporation of India Ltd. | E43: 8078.65 | F43: 0.0104 | G43: 0.061074
A44: Sub Total | E44: 8078.65 | F44: 0.0104
A46: TOTAL | E46: 8078.65 | F46: 0.0104
A47: Accrued Interest | E47: 32579.306 | F47: 0.042002
A48: Net Receivables/(Payables) | E48: 52.54425 | F48: 9.8e-05 | G48: 0.061074
A49: GRAND TOTAL | E49: 775647.08 | F49: 1
A51: **Non Traded Security
A54: Notes:
A55: 1. Security in default beyond its maturiy date | B55: NIL
A56: 2. NAV at the beginning of the period (Rs. per unit)
A57: Plan /option (Face Value 1000) | B57: As on | C57: As on
B58: 44834 | C58: 44865
A59: Growth Option | B59: 1003.5227 | C59: 1010.0076
A61: 3. Total Dividend (Net) declared during the month | B61: NIL
A62: 4. Bonus was declared during the month | B62: NIL
A63: 5. Investment in Repo of Corporate Debt Securities during the month ended October 31, 2022 | B63: NIL
A64: 6. Investment in foreign securities/ADRs/GDRs at the end of the month | B64: NIL
A65: 7. Average Portfolio Maturity | B65: 9.2945352
A66: 8. Total gross exposure to derivative instruments (excluding reversed positions) at the end of the month (Rs. in Lakhs) | B66: NIL
A67: 9. Margin Deposits includes Margin money placed on derivatives other than margin money placed with bank | B67: NIL
A68: 10. Value of investment made by other schemes under same management (Rs. In Lakhs) | B68: =EDFF32!E11 -> 223094.81
A69: 11. Number of instance of deviation In valuation of securities | B69: NIL
A70: 12. Total value and percentage of illiquid equity shares / securities | B70: NIL
A72: Scheme Name | B72: Risk- O - Meter | C72: Benchmark of the Scheme | D72: Benchmark Risk-o-meter
A73: BHARAT Bond ETF - April 2032 | C73: Nifty BHARAT Bond Index – April 2032

Sheet EDBPDF
A1: PORTFOLIO STATEMENT OF EDELWEISS BANKING AND PSU DEBT FUND AS ON OCTOBER 31, 2022 | H1: =HYPERLINK("[EDEL_Portfolio Monthly Notes 31-Oct-2022.xlsx]Index!A1","Index") -> Index
A2: (An open ended debt scheme predominantly investing in Debt Instruments of Banks, Public Sector Undertakings, Public Financial Institutions and Municipal Bonds.)
A4: Name of the Instrument | B4: ISIN | C4: Rating/Industry | D4: Quantity | E4: Market/Fair Value(Rs. In Lacs) | F4: % to Net Assets | G4: YIELD
A7: Equity & Equity related | E7: NIL | F7: NIL
A9: Debt Instruments
A10: (a)Listed / Awaiting listing on stock Exchanges
A11: 8.37% HUDCO NCD RED 23-03-2029** | B11: INE031A08707 | C11: ICRA AAA | D11: 3000000 | E11: 3127.37 | F11: 0.0874 | G11: 0.076611
A12: 7.48% IRFC NCD RED 13-08-2029** | B12: INE053F07BU3 | C12: CRISIL AAA | D12: 3000000 | E12: 2976.67 | F12: 0.0832 | G12: 0.07625
A13: 7.41% IOC NCD RED 22-10-2029** | B13: INE242A08437 | C13: FITCH AAA | D13: 3000000 | E13: 2961.18 | F13: 0.0828 | G13: 0.07655
A14: 8.3% NTPC LTD NCD RED 15-01-2029** | B14: INE733E07KJ7 | C14: CRISIL AAA | D14: 2500000 | E14: 2584.09 | F14: 0.0722 | G14: 0.0759
A15: 8.85% REC LTD. NCD RED 16-04-2029** | B15: INE020B08BQ7 | C15: CRISIL AAA | D15: 1850000 | E15: 1956 | F15: 0.0547 | G15: 0.07675
A16: 7.03% HPCL NCD RED 12-04-2030** | B16: INE094A08069 | C16: CRISIL AAA | D16: 1990000 | E16: 1918.58 | F16: 0.0536 | G16: 0.076724
A17: 7.64% FOOD CORP GOI GRNT NCD 12-12-2029** | B17: INE861G08050 | C17: CRISIL AAA(CE) | D17: 1900000 | E17: 1896.42 | F17: 0.053 | G17: 0.0767
A18: 7.49% NHAI NCD RED 01-08-2029** | B18: INE906B07HG7 | C18: CRISIL AAA | D18: 1300000 | E18: 1289.34 | F18: 0.036 | G18: 0.0764
A19: 8.83% EXIM BK OF INDIA NCD RED 03-11-29** | B19: INE514E08EE3 | C19: CRISIL AAA | D19: 1000000 | E19: 1063.3 | F19: 0.0297 | G19: 0.0763
A20: 8.13% NUCLEAR POWER CORP NCD 28-03-2029** | B20: INE206D08386 | C20: CRISIL AAA | D20: 1000000 | E20: 1030.74 | F20: 0.0288 | G20: 0.076553
A21: 8.12% NHPC NCD GOI SERVICED 22-03-2029** | B21: INE848E08136 | C21: CARE AAA | D21: 1000000 | E21: 1030.67 | F21: 0.0288 | G21: 0.076503
A22: 8.27% NHAI NCD RED 28-03-2029** | B22: INE906B07GP0 | C22: CRISIL AAA | D22: 1000000 | E22: 1030.26 | F22: 0.0288 | G22: 0.0764
... A32: 8.7% LIC HOUS FIN NCD RED 23-03-2029** | B32: INE115A07OB4 | C32: CRISIL AAA | D32: 10000 | E32: 10.35 | F32: 0.0003 | G32: 0.0796
A33: Sub Total | E33: 28859 | F33: 0.8064
A35: Government Securities
A36: 7.10% GOVT OF INDIA RED 18-04-2029 | B36: IN0020220011 | C36: SOVEREIGN | D36: 5000000 | E36: 4916.79 | F36: 0.1374 | G36: 0.07428
A37: Sub Total | E37: 4916.79 | F37: 0.1374
A39: (b)Privately Placed/Unlisted
A40: Sub Total | E40: NIL | F40: NIL
A42: (c)Securitised Debt Instruments
A43: Sub Total | E43: NIL | F43: NIL
A45: TOTAL | E45: 33775.79 | F45: 0.9438
A48: TREPS / Reverse Repo
A49: Clearing Corporation of India Ltd. | E49: 877.85 | F49: 0.0245 | G49: 0.061074
A50: Sub Total | E50: 877.85 | F50: 0.0245
A52: TOTAL | E52: 877.85 | F52: 0.0245
A53: Accrued Interest | E53: 1026.7213 | F53: 0.028692
A54: Net Receivables/(Payables) | E54: 103.46868 | F54: 0.003008 | G54: 0.061074
A55: GRAND TOTAL | E55: 35783.83 | F55: 1
A57: **Non Traded Security
A60: Notes:
A61: 1. Security in default beyond its maturiy date | B61: NIL
A62: 2. NAV at the beginning of the period (Rs. per unit)
A63: Plan /option (Face Value 10) | B63: As on | C63: As on
B64: 44834 | C64: 44865
A65: Direct Plan Bonus Option | B65: ^ | C65: ^
A66: Direct Plan Fortnightly IDCW Option | B66: 14.6004 | C66: 14.5748
A67: Direct Plan Growth Option | B67: 20.5907 | C67: 20.6615
A68: Direct Plan IDCW Option | B68: 18.198 | C68: 17.9605
A69: Direct Plan Monthly IDCW Option | B69: 10.9126 | C69: 10.9082
A70: Direct Plan Weekly IDCW Option | B70: 10.4397 | C70: 10.4756
A71: Regular Plan Bonus Option | B71: ^ | C71: ^
A72: Regular Plan Fortnightly IDCW Option | B72: 14.2259 | C72: 14.2006
A73: Regular Plan Growth Option | B73: 20.0449 | C73: 20.1078
A74: Regular Plan IDCW Option | B74: 17.6602 | C74: 17.4156
A75: Regular Plan Monthly IDCW Option | B75: 11.0963 | C75: 11.1311
A76: Regular Plan Weekly IDCW Option | B76: 10.0392 | C76: 10.0707
A77: ^ There were no investors in this option.
A79: 3. Total Dividend (Net) declared during the month
A81: Plan/Option Name | C81: individual & HUF | D81: others
A82: Direct Plan - IDCW | C82: 0.3 | D82: 0.3
A83: Direct Plan Fortnightly IDCW | C83: 0.0758461 | D83: 0.0758461
A84: Direct Plan Monthly IDCW | C84: 0.0418539 | D84: 0.0418539
A85: Regular Plan Fortnightly IDCW | C85: 0.0699511 | D85: 0.0699511
A86: Regular Plan IDCW | C86: 0.3 | D86: 0.3
A88: 4. Bonus was declared during the month | B88: NIL
A89: 5. Investment in Repo of Corporate Debt Securities during the month ended October 31, 2022 | B89: NIL
A90: 6. Investment in foreign securities/ADRs/GDRs at the end of the month | B90: NIL
A91: 7. Average Portfolio Maturity | B91: 6.5177586
A92: 8. Total gross exposure to derivative instruments (excluding reversed positions) at the end of the month (Rs. in Lakhs) | B92: NIL
A93: 9. Margin Deposits includes Margin money placed on derivatives other than margin money placed with bank | B93: NIL
A94: 10. Value of investment made by other schemes under same management (Rs. In Lakhs) | B94: NIL
A95: 11. Number of instance of deviation In valuation of securities | B95: NIL
A96: 12. Total value and percentage of illiquid equity shares / securities | B96: NIL
A99: Scheme Name | B99: Risk- O - Meter | C99: Benchmark of the Scheme | D99: Benchmark Risk-o-meter | E99: Benchmark of the Scheme | F99: Benchmark Risk-o-meter
A100: Edelweiss Banking and PSU Debt Fund | C100: NIFTY Banking and PSU Debt Index (TIER - 1) | E100: Nifty Banking & PSU Debt Index - A-III (TIER - 2)

Sheet EDCG27
A1: PORTFOLIO STATEMENT OF EDELWEISS CRISIL IBX 50:50 GILT PLUS SDL JUNE 2027 INDEX FUND AS ON OCTOBER 31, 2022 | H1: =HYPERLINK("[EDEL_Portfolio Monthly Notes 31-Oct-2022.xlsx]Index!A1","Index") -> Index
A2: (An open-ended target maturity Index Fund investing in the constituents of CRISIL IBX 50:50 Gilt Plus SDL Index – June 2027. A relatively high interest)
A4: Name of the Instrument | B4: ISIN | C4: Rating/Industry | D4: Quantity | E4: Market/Fair Value(Rs. In Lacs) | F4: % to Net Assets | G4: YIELD
A7: Equity & Equity related | E7: NIL | F7: NIL
A8: Debt Instruments
A9: (a) Listed / Awaiting listing on Stock Exchanges
A10: Sub Total | E10: NIL | F10: NIL
A12: Government Securities
A13: 7.38% GOVT OF INDIA RED 20-06-2027 | B13: IN0020220037 | C13: SOVEREIGN | D13: 2000000 | E13: 1999.88 | F13: 0.4573 | G13: 0.073781
A14: Sub Total | E14: 1999.88 | F14: 0.4573
A16: State Development Loan
A17: 7.16% TAMILNADU SDL RED 11-01-2027 | B17: IN3120160178 | C17: SOVEREIGN | D17: 2000000 | E17: 1977.28 | F17: 0.4522 | G17: 0.074761
A18: 7.67% UTTAR PRADESH SDL 12-04-2027 | B18: IN3320170019 | C18: SOVEREIGN | D18: 200000 | E18: 200.94 | F18: 0.046 | G18: 0.075416
A19: Sub Total | E19: 2178.22 | F19: 0.4982
A22: (b)Privately Placed/Unlisted
A23: Sub Total | E23: NIL | F23: NIL
A25: (c)Securitised Debt Instruments
A26: Sub Total | E26: NIL | F26: NIL
A28: TOTAL | E28: 4178.1 | F28: 0.9555
A31: TREPS / Reverse Repo
A32: Clearing Corporation of India Ltd. | E32: 229.96 | F32: 0.0526 | G32: 0.061074
A33: Sub Total | E33: 229.96 | F33: 0.0526
A35: TOTAL | E35: 229.96 | F35: 0.0526
A36: Accrued Interest | E36: 98.313645 | F36: 0.022482
A37: Net Receivables/(Payables) | E37: -133.54365 | F37: -0.030582 | G37: 0.061074
A38: GRAND TOTAL | E38: 4372.83 | F38: 1
A40: **Non Traded Security
A43: Notes:
A44: 1. Security in default beyond its maturiy date | B44: NIL
A45: 2. NAV at the beginning of the period (Rs. per unit)
A46: Plan /option (Face Value 10) | B46: As on | C46: As on
B47: 44834 | C47: 44865
A48: Direct Plan Growth Option | B48: ^ | C48: 10.0244
A49: Direct Plan IDCW Option | B49: ^ | C49: 10.0244
A50: Regular Plan Growth Option | B50: ^ | C50: 10.0234
A51: Regular Plan IDCW Option | B51: ^ | C51: 10.0234
A52: ^ There were no investors in this option.
A54: 3. Total Dividend (Net) declared during the month | B54: NIL
A55: 4. Bonus was declared during the month | B55: NIL
A56: 5. Investment in Repo of Corporate Debt Securities during the month ended October 31, 2022 | B56: NIL
A57: 6. Investment in foreign securities/ADRs/GDRs at the end of the month | B57: NIL
A58: 7. Average Portfolio Maturity | B58: 4.322044
A59: 8. Total gross exposure to derivative instruments (excluding reversed positions) at the end of the month (Rs. in Lakhs) | B59: NIL
A60: 9. Margin Deposits includes Margin money placed on derivatives other than margin money placed with bank | B60: NIL
A61: 10. Value of investment made by other schemes under same management (Rs. In Lakhs) | B61: NIL
A62: 11. Number of instance of deviation In valuation of securities | B62: NIL
A63: 12. Total value and percentage of illiquid equity shares / securities | B63: NIL
A65: Scheme Name | B65: Risk- O - Meter | C65: Benchmark of the Scheme | D65: Benchmark Risk-o-meter
A66: =HYPERLINK("[EDEL_Portfolio Monthly Notes 31-Oct-2022.xlsx]EDCG27!A1","Edelweiss CRISIL IBX 50 50 Gilt Plus SDL June 2027 Index Fund") -> Edelweiss CRISIL IBX 50 50 Gilt Plus SDL June 2027 Index Fund | C66: (CRISIL IBX 50:50 Gilt Plus SDL Index – June 2027

Sheet EDCG37
A1: PORTFOLIO STATEMENT OF EDELWEISS CRISIL IBX 50:50 GILT PLUS SDL APRIL 2037 INDEX FUND AS ON OCTOBER 31, 2022 | H1: =HYPERLINK("[EDEL_Portfolio Monthly Notes 31-Oct-2022.xlsx]Index!A1","Index") -> Index
A2: (An open-ended target maturity Index Fund investing in the constituents of CRISIL IBX 50:50 Gilt Plus SDL Index – April 2037. A relatively high interes)
A4: Name of the Instrument | B4: ISIN | C4: Rating/Industry | D4: Quantity | E4: Market/Fair Value(Rs. In Lacs) | F4: % to Net Assets | G4: YIELD
A7: Equity & Equity related | E7: NIL | F7: NIL
A8: Debt Instruments
A9: (a) Listed / Awaiting listing on Stock Exchanges
A10: Sub Total | E10: NIL | F10: NIL
A12: State Development Loan
A13: 7.89% TELANGANA SDL RED 27-10-2036 | B13: IN4520220224 | C13: SOVEREIGN | D13: 3500000 | E13: 3513.65 | F13: 0.5761 | G13: 0.078434
A14: 7.83% TELANGANA SDL RED 04-10-2036 | B14: IN4520220216 | C14: SOVEREIGN | D14: 2500000 | E14: 2501.28 | F14: 0.4101 | G14: 0.078228
A15: Sub Total | E15: 6014.93 | F15: 0.9862
A18: (b)Privately Placed/Unlisted
A19: Sub Total | E19: NIL | F19: NIL
A21: (c)Securitised Debt Instruments
A22: Sub Total | E22: NIL | F22: NIL
A24: TOTAL | E24: 6014.93 | F24: 0.9862
A27: TREPS / Reverse Repo
A28: Clearing Corporation of India Ltd. | E28: 79.99 | F28: 0.0131 | G28: 0.061074
A29: Sub Total | E29: 79.99 | F29: 0.0131
A31: TOTAL | E31: 79.99 | F31: 0.0131
A32: Accrued Interest | E32: 17.762967 | F32: 0.002912
A33: Net Receivables/(Payables) | E33: -13.642967 | F33: -0.002212 | G33: 0.061074
A34: GRAND TOTAL | E34: 6099.04 | F34: 1
A36: **Non Traded Security
A39: Notes:
A40: 1. Security in default beyond its maturiy date | B40: NIL
A41: 2. NAV at the beginning of the period (Rs. per unit)
A42: Plan /option (Face Value 10) | B42: As on | C42: As on
B43: 44834 | C43: 44865
A44: Direct Plan Growth Option | B44: ^ | C44: 10.0545
A45: Direct Plan IDCW Option | B45: ^ | C45: 10.0544
A46: Regular Plan Growth Option | B46: ^ | C46: 10.0532
A47: Regular Plan IDCW Option | B47: ^ | C47: 10.0531
A48: ^ There were no investors in this option.
A50: 3. Total Dividend (Net) declared during the month | B50: NIL
A51: 4. Bonus was declared during the month | B51: NIL
A52: 5. Investment in Repo of Corporate Debt Securities during the month ended October 31, 2022 | B52: NIL
A53: 6. Investment in foreign securities/ADRs/GDRs at the end of the month | B53: NIL
A54: 7. Average Portfolio Maturity | B54: 13.818954
A55: 8. Total gross exposure to derivative instruments (excluding reversed positions) at the end of the month (Rs. in Lakhs) | B55: NIL
A56: 9. Margin Deposits includes Margin money placed on derivatives other than margin money placed with bank | B56: NIL
A57: 10. Value of investment made by other schemes under same management (Rs. In Lakhs) | B57: NIL
A58: 11. Number of instance of deviation In valuation of securities | B58: NIL
A59: 12. Total value and percentage of illiquid equity shares / securities | B59: NIL
A61: Scheme Name | B61: Risk- O - Meter | C61: Benchmark of the Scheme | D61: Benchmark Risk-o-meter
A62: =HYPERLINK("[EDEL_Portfolio Monthly Notes 31-Oct-2022.xlsx]EDCG37!A1","Edelweiss_CRISIL IBX 50 50 Gilt Plus SDL April 2037 Index Fund") -> Edelweiss_CRISIL IBX 50 50 Gilt Plus SDL April 2037 Index Fund | C62: CRISIL IBX 50:50 Gilt Plus SDL Index – April 2037

Sheet EDCPSF
A1: PORTFOLIO STATEMENT OF EDELWEISS CRL PSU PL SDL 50:50 OCT-25 FD AS ON OCTOBER 31, 2022 | H1: =HYPERLINK("[EDEL_Portfolio Monthly Notes 31-Oct-2022.xlsx]Index!A1","Index") -> Index
A2: (An open-ended target maturity Index Fund investing in the constituents of CRISIL [IBX] 50:50 PSU + SDL Index – October 2025. A moderate interest rate risk and relatively low credit risk.)
A4: Name of the Instrument | B4: ISIN | C4: Rating/Industry | D4: Quantity | E4: Market/Fair Value(Rs. In Lacs) | F4: % to Net Assets | G4: YIELD
A7: Equity & Equity related | E7: NIL | F7: NIL
A9: Debt Instruments
A10: (a)Listed / Awaiting listing on stock Exchanges
A11: 7.20% EXIM NCD RED 05-06-2025** | B11: INE514E08FY8 | C11: CRISIL AAA | D11: 6000000 | E11: 5967.39 | F11: 0.0714 | G11: 0.0741
A12: 8.11% REC LTD NCD 07-10-2025 SR136** | B12: INE020B08963 | C12: CRISIL AAA | D12: 5000000 | E12: 5071.96 | F12: 0.0607 | G12: 0.0755
A13: 7.25% SIDBI NCD RED 31-07-2025** | B13: INE556F08KA6 | C13: ICRA AAA | D13: 5000000 | E13: 4961.99 | F13: 0.0594 | G13: 0.07545
A14: 5.7% NABARD NCD RED SR 22D 31-07-2025** | B14: INE261F08DK7 | C14: CRISIL AAA | D14: 4500000 | E14: 4299.58 | F14: 0.0514 | G14: 0.0754
A15: 7.34% NHB LTD NCD RED 07-08-2025** | B15: INE557F08FN7 | C15: CRISIL AAA | D15: 3500000 | E15: 3489.94 | F15: 0.0418 | G15: 0.07445
A16: 7.50% NHPC LTD SR Y STR A NCD 07-10-2025** | B16: INE848E07AO4 | C16: ICRA AAA | D16: 2500000 | E16: 2505.32 | F16: 0.03 | G16: 0.0741
A17: 7.20% NABARD NCD RED 23-09-2025 | B17: INE261F08DR2 | C17: ICRA AAA | D17: 2500000 | E17: 2477.77 | F17: 0.0296 | G17: 0.0754
A18: 6.50% POWER FIN CORP NCD RED 17-09-2025** | B18: INE134E08LD7 | C18: CRISIL AAA | D18: 2500000 | E18: 2433.69 | F18: 0.0291 | G18: 0.0755
A19: 7.12% HPCL NCD RED 30-07-2025** | B19: INE094A08127 | C19: CRISIL AAA | D19: 2000000 | E19: 1981.7 | F19: 0.0237 | G19: 0.074825
A20: 7.17% POWER FIN COR NCD SR 202B 22-05-25** | B20: INE134E08KT5 | C20: CRISIL AAA | D20: 2000000 | E20: 1981.64 | F20: 0.0237 | G20: 0.0755
A21: 7.15% SIDBI NCD RED 02-06-2025** | B21: INE556F08JY8 | C21: ICRA AAA | D21: 1000000 | E21: 990.39 | F21: 0.0119 | G21: 0.07545
A22: 8.75% REC LTD NCD RED 12-07-2025** | B22: INE020B08443 | C22: CRISIL AAA | D22: 500000 | E22: 513.81 | F22: 0.0061 | G22: 0.0755
... A24: 7.30% NMDC LTD SR I NCD RED 28-08-2025** | B24: INE584A08010 | C24: ICRA AAA | D24: 500000 | E24: 494.84 | F24: 0.0059 | G24: 0.07705
A25: Sub Total | E25: 37680.33 | F25: 0.4508
A27: Government Securities
A28: 5.22% GOVT OF INDIA RED 15-06-2025 | B28: IN0020200112 | C28: SOVEREIGN | D28: 3500000 | E28: 3337.82 | F28: 0.0399 | G28: 0.071867
A29: Sub Total | E29: 3337.82 | F29: 0.0399
A30: State Development Loan
A31: 8.20% GUJARAT SDL RED 24-06-2025 | B31: IN1520150021 | C31: SOVEREIGN | D31: 5000000 | E31: 5090.73 | F31: 0.0609 | G31: 0.074258
A32: 8.31% ANDHRA PRADESH SDL RED 29-07-2025 | B32: IN1020150042 | C32: SOVEREIGN | D32: 3500000 | E32: 3570.92 | F32: 0.0427 | G32: 0.07472
A33: 8.31% UTTAR PRADESH SDL 29-07-2025 | B33: IN3320150250 | C33: SOVEREIGN | D33: 2500000 | E33: 2549.86 | F33: 0.0305 | G33: 0.074848
A34: 8.27% KERALA SDL RED 12-08-2025 | B34: IN2020150073 | C34: SOVEREIGN | D34: 2500000 | E34: 2549.77 | F34: 0.0305 | G34: 0.074565
A35: 8.30% JHARKHAND SDL RED 29-07-2025 | B35: IN3720150017 | C35: SOVEREIGN | D35: 2500000 | E35: 2548.53 | F35: 0.0305 | G35: 0.074965
A36: 8.21% WEST BENGAL SDL RED 24-06-2025 | B36: IN3420150036 | C36: SOVEREIGN | D36: 2500000 | E36: 2543.28 | F36: 0.0304 | G36: 0.074705
A37: 7.99% MAHARASHTRA SDL RED 28-10-2025 | B37: IN2220150113 | C37: SOVEREIGN | D37: 2500000 | E37: 2536.51 | F37: 0.0304 | G37: 0.074362
A38: 7.97% TAMIL NADU SDL RED 14-10-2025 | B38: IN3120150112 | C38: SOVEREIGN | D38: 2500000 | E38: 2533.5 | F38: 0.0303 | G38: 0.074537
A39: 7.89% GUJARAT SDL RED 15-05-2025 | B39: IN1520190043 | C39: SOVEREIGN | D39: 2500000 | E39: 2526.89 | F39: 0.0302 | G39: 0.074152
A40: 8.24% KERALA SDL RED 13-05-2025 | B40: IN2020150032 | C40: SOVEREIGN | D40: 2000000 | E40: 2036.24 | F40: 0.0244 | G40: 0.0744
A41: 8.22% TAMIL NADU SDL RED 13-05-2025 | B41: IN3120150039 | C41: SOVEREIGN | D41: 2000000 | E41: 2035.78 | F41: 0.0244 | G41: 0.074302
A42: 8.20% RAJASTHAN SDL RED 24-06-2025 | B42: IN2920150157 | C42: SOVEREIGN | D42: 2000000 | E42: 2033.89 | F42: 0.0243 | G42: 0.074759
... A50: 8% TAMIL NADU SDL RED 28-10-2025 | B50: IN3120150120 | C50: SOVEREIGN | D50: 500000 | E50: 507.2 | F50: 0.0061 | G50: 0.074537
A51: Sub Total | E51: 40135.6 | F51: 0.4803
A54: (b)Privately Placed/Unlisted
A55: Sub Total | E55: NIL | F55: NIL
A57: (c)Securitised Debt Instruments
A58: Sub Total | E58: NIL | F58: NIL
A60: TOTAL | E60: 81153.75 | F60: 0.971
A63: TREPS / Reverse Repo
A64: Clearing Corporation of India Ltd. | E64: 844.86 | F64: 0.0101 | G64: 0.061074
A65: Sub Total | E65: 844.86 | F65: 0.0101
A67: TOTAL | E67: 844.86 | F67: 0.0101
A68: Accrued Interest | E68: 1623.9324 | F68: 0.019431
A69: Net Receivables/(Payables) | E69: -49.292414 | F69: -0.000531 | G69: 0.061074
A70: GRAND TOTAL | E70: 83573.25 | F70: 1
A72: **Non Traded Security
A75: Notes:
A76: 1. Security in default beyond its maturiy date | B76: NIL
A77: 2. NAV at the beginning of the period (Rs. per unit)
A78: Plan /option (Face Value 10) | B78: As on | C78: As on
B79: 44834 | C79: 44865
A80: Direct Plan Growth Option | B80: 10.0004 | C80: 10.0509
A81: Direct Plan IDCW Option | B81: 10.0006 | C81: 10.0511
A82: Regular Plan Growth Option | B82: 9.9893 | C82: 10.038
A83: Regular Plan IDCW Option | B83: 9.9895 | C83: 10.0383
A85: 3. Total Dividend (Net) declared during the month | B85: NIL
A86: 4. Bonus was declared during the month | B86: NIL
A87: 5. Investment in Repo of Corporate Debt Securities during the month ended October 31, 2022 | B87: NIL
A88: 6. Investment in foreign securities/ADRs/GDRs at the end of the month | B88: NIL
A89: 7. Average Portfolio Maturity | B89: 2.7115012
A90: 8. Total gross exposure to derivative instruments (excluding reversed positions) at the end of the month (Rs. in Lakhs) | B90: NIL
A91: 9. Margin Deposits includes Margin money placed on derivatives other than margin money placed with bank | B91: NIL
A92: 10. Value of investment made by other schemes under same management (Rs. In Lakhs) | B92: NIL
A93: 11. Number of instance of deviation In valuation of securities | B93: NIL
A94: 12. Total value and percentage of illiquid equity shares / securities | B94: NIL
A97: Scheme Name | B97: Risk- O - Meter | C97: Benchmark of the Scheme | D97: Benchmark Risk-o-meter
A98: Edelweiss CRL PSU PL SDL 50 50 Oct-25 FD | C98: CRISIL [IBX] 50:50 PSU + SDL Index - October 2025

Sheet EDFF23
A1: PORTFOLIO STATEMENT OF BHARAT BOND FOF – APRIL 2023 AS ON OCTOBER 31, 2022 | H1: =HYPERLINK("[EDEL_Portfolio Monthly Notes 31-Oct-2022.xlsx]Index!A1","Index") -> Index
A2: (An open-ended Target Maturity fund of funds scheme investing in units of BHARAT Bond ETF – April 2023)
A4: Name of the Instrument | B4: ISIN | C4: Rating/Industry | D4: Quantity | E4: Market/Fair Value(Rs. In Lacs) | F4: % to Net Assets | G4: YIELD
A7: Equity & Equity related | E7: NIL | F7: NIL
A10: Investment in Mutual fund
A11: BHARAT BOND ETF-APRIL 2023-GROWTH | B11: INF754K01KN4 | D11: 27573010 | E11: 329431.29 | F11: 0.9846
A12: Sub Total | E12: 329431.29 | F12: 0.9846
A14: TOTAL | E14: 329431.29 | F14: 0.9846
A16: TREPS / Reverse Repo
A17: Clearing Corporation of India Ltd. | E17: 2534.58 | F17: 0.0076 | G17: 0.061074
A18: Sub Total | E18: 2534.58 | F18: 0.0076
A20: TOTAL | E20: 2534.58 | F20: 0.0076
A21: Accrued Interest | E21: 0.4241005 | F21: 1e-06
A22: Net Receivables/(Payables) | E22: 2627.5659 | F22: 0.007799 | G22: 0.061074
A23: GRAND TOTAL | E23: 334593.86 | F23: 1
A28: Notes:
A29: 1. Security in default beyond its maturiy date | B29: NIL
A30: 2. NAV at the beginning of the period (Rs. per unit)
A31: Plan /option (Face Value 10) | B31: As on | C31: As on
B32: 44834 | C32: 44865
A33: Direct Plan Growth Option | B33: 11.8681 | C33: 11.9225
A34: Direct Plan IDCW Option | B34: 11.8681 | C34: 11.9225
A35: Regular Plan Growth Option | B35: 11.8681 | C35: 11.9225
A36: Regular Plan IDCW Option | B36: 11.8681 | C36: 11.9225
A38: 3. Total Dividend (Net) declared during the month | B38: NIL
A39: 4. Bonus was declared during the month | B39: NIL
A40: 5. Investment in Repo of Corporate Debt Securities during the month ended October 31, 2022 | B40: NIL
A41: 6. Investment in foreign securities/ADRs/GDRs at the end of the month | B41: NIL
A42: 7. Average Portfolio Maturity | B42: 0.41636783
A43: 8. Total gross exposure to derivative instruments (excluding reversed positions) at the end of the month (Rs. in Lakhs) | B43: NIL
A44: 9. Margin Deposits includes Margin money placed on derivatives other than margin money placed with bank | B44: NIL
A45: 10. Value of investment made by other schemes under same management (Rs. In Lakhs) | B45: NIL
A46: 11. Number of instance of deviation In valuation of securities | B46: NIL
A47: 12. Total value and percentage of illiquid equity shares / securities | B47: NIL
A50: Scheme Name | B50: Risk- O - Meter | C50: Benchmark of the Scheme | D50: Benchmark Risk-o-meter
A51: BHARAT Bond FOF - April 2023 | C51: NIFTY BHARAT Bond Index - April 2023

Sheet EDFF25
A1: PORTFOLIO STATEMENT OF BHARAT BOND FOF – APRIL 2025 AS ON OCTOBER 31, 2022 | H1: =HYPERLINK("[EDEL_Portfolio Monthly Notes 31-Oct-2022.xlsx]Index!A1","Index") -> Index
A2: (An open-ended Target Maturity fund of funds scheme investing in units of BHARAT Bond ETF – April 2025)
A4: Name of the Instrument | B4: ISIN | C4: Rating/Industry | D4: Quantity | E4: Market/Fair Value(Rs. In Lacs) | F4: % to Net Assets | G4: YIELD
A7: Equity & Equity related | E7: NIL | F7: NIL
A10: Investment in Mutual fund
A11: BHARAT BOND ETF-APRIL 2025-GROWTH | B11: INF754K01LD3 | D11: 36438149 | E11: 394173.32 | F11: 0.9902
A12: Sub Total | E12: 394173.32 | F12: 0.9902
A14: TOTAL | E14: 394173.32 | F14: 0.9902
A16: TREPS / Reverse Repo
A17: Clearing Corporation of India Ltd. | E17: 393.93 | F17: 0.001 | G17: 0.061074
A18: Sub Total | E18: 393.93 | F18: 0.001
A20: TOTAL | E20: 393.93 | F20: 0.001
A21: Accrued Interest | E21: 0.0659154 | F21: 0
A22: Net Receivables/(Payables) | E22: 3520.0641 | F22: 0.0088 | G22: 0.061074
A23: GRAND TOTAL | E23: 398087.38 | F23: 1
A28: Notes:
A29: 1. Security in default beyond its maturiy date | B29: NIL
A30: 2. NAV at the beginning of the period (Rs. per unit)
A31: Plan /option (Face Value 10) | B31: As on | C31: As on
B32: 44834 | C32: 44865
A33: Direct Plan Growth Option | B33: 10.7499 | C33: 10.7952
A34: Direct Plan IDCW Option | B34: 10.7499 | C34: 10.7952
A35: Regular Plan Growth Option | B35: 10.7499 | C35: 10.7952
A36: Regular Plan IDCW Option | B36: 10.7499 | C36: 10.7952
A38: 3. Total Dividend (Net) declared during the month | B38: NIL
A39: 4. Bonus was declared during the month | B39: NIL
A40: 5. Investment in Repo of Corporate Debt Securities during the month ended October 31, 2022 | B40: NIL
A41: 6. Investment in foreign securities/ADRs/GDRs at the end of the month | B41: NIL
A42: 7. Average Portfolio Maturity | B42: 2.2910529
A43: 8. Total gross exposure to derivative instruments (excluding reversed positions) at the end of the month (Rs. in Lakhs) | B43: NIL
A44: 9. Margin Deposits includes Margin money placed on derivatives other than margin money placed with bank | B44: NIL
A45: 10. Value of investment made by other schemes under same management (Rs. In Lakhs) | B45: NIL
A46: 11. Number of instance of deviation In valuation of securities | B46: NIL
A47: 12. Total value and percentage of illiquid equity shares / securities | B47: NIL
A49: Scheme Name | B49: Risk- O - Meter | C49: Benchmark of the Scheme | D49: Benchmark Risk-o-meter
A50: BHARAT Bond FOF - April 2025 | C50: Nifty BHARAT Bond Index – April 2025

Sheet EDFF30
A1: PORTFOLIO STATEMENT OF BHARAT BOND FOF – APRIL 2030 AS ON OCTOBER 31, 2022 | H1: =HYPERLINK("[EDEL_Portfolio Monthly Notes 31-Oct-2022.xlsx]Index!A1","Index") -> Index
A2: (An open-ended Target Maturity fund of funds scheme investing in units of BHARAT Bond ETF – April 2030)
A4: Name of the Instrument | B4: ISIN | C4: Rating/Industry | D4: Quantity | E4: Market/Fair Value(Rs. In Lacs) | F4: % to Net Assets | G4: YIELD
A7: Equity & Equity related | E7: NIL | F7: NIL
A10: Investment in Mutual fund
A11: BHARAT BOND ETF-APRIL 2030-GROWTH | B11: INF754K01KO2 | D11: 38159325 | E11: 461517.96 | F11: 0.996
A12: Sub Total | E12: 461517.96 | F12: 0.996
A14: TOTAL | E14: 461517.96 | F14: 0.996
A16: TREPS / Reverse Repo
A17: Clearing Corporation of India Ltd. | E17: 2394.6 | F17: 0.0052 | G17: 0.061074
A18: Sub Total | E18: 2394.6 | F18: 0.0052
A20: TOTAL | E20: 2394.6 | F20: 0.0052
A21: Accrued Interest | E21: 0.4006788 | F21: 0
A22: Net Receivables/(Payables) | E22: -528.08068 | F22: -0.0012 | G22: 0.061074
A23: GRAND TOTAL | E23: 463384.88 | F23: 1
A28: Notes:
A29: 1. Security in default beyond its maturiy date | B29: NIL
A30: 2. NAV at the beginning of the period (Rs. per unit)
A31: Plan /option (Face Value 10) | B31: As on | C31: As on
B32: 44834 | C32: 44865
A33: Direct Plan Growth Option | B33: 12.0473 | C33: 12.0712
A34: Direct Plan IDCW Option | B34: 12.0473 | C34: 12.0712
A35: Regular Plan Growth Option | B35: 12.0473 | C35: 12.0712
A36: Regular Plan IDCW Option | B36: 12.0473 | C36: 12.0712
A38: 3. Total Dividend (Net) declared during the month | B38: NIL
A39: 4. Bonus was declared during the month | B39: NIL
A40: 5. Investment in Repo of Corporate Debt Securities during the month ended October 31, 2022 | B40: NIL
A41: 6. Investment in foreign securities/ADRs/GDRs at the end of the month | B41: NIL
A42: 7. Average Portfolio Maturity | B42: 7.0704069
A43: 8. Total gross exposure to derivative instruments (excluding reversed positions) at the end of the month (Rs. in Lakhs) | B43: NIL
A44: 9. Margin Deposits includes Margin money placed on derivatives other than margin money placed with bank | B44: NIL
A45: 10. Value of investment made by other schemes under same management (Rs. In Lakhs) | B45: NIL
A46: 11. Number of instance of deviation In valuation of securities | B46: NIL
A47: 12. Total value and percentage of illiquid equity shares / securities | B47: NIL
A50: Scheme Name | B50: Risk- O - Meter | C50: Benchmark of the Scheme | D50: Benchmark Risk-o-meter
A51: BHARAT Bond FOF - April 2030 | C51: NIFTY BHARAT Bond Index - April 2030

Sheet EDFF31
A1: PORTFOLIO STATEMENT OF BHARAT BOND FOF – APRIL 2031 AS ON OCTOBER 31, 2022 | H1: =HYPERLINK("[EDEL_Portfolio Monthly Notes 31-Oct-2022.xlsx]Index!A1","Index") -> Index
A2: (An open-ended Target Maturity fund of funds scheme investing in units of BHARAT Bond ETF – April 2031)
A4: Name of the Instrument | B4: ISIN | C4: Rating/Industry | D4: Quantity | E4: Market/Fair Value(Rs. In Lacs) | F4: % to Net Assets | G4: YIELD
A7: Equity & Equity related | E7: NIL | F7: NIL
A10: Investment in Mutual fund
A11: BHARAT BOND ETF-APRIL 2031-GROWTH | B11: INF754K01LE1 | D11: 30201692 | E11: 326244.72 | F11: 0.9968
A12: Sub Total | E12: 326244.72 | F12: 0.9968
A14: TOTAL | E14: 326244.72 | F14: 0.9968
A16: TREPS / Reverse Repo
A17: Clearing Corporation of India Ltd. | E17: 1497.75 | F17: 0.0046 | G17: 0.061074
A18: Sub Total | E18: 1497.75 | F18: 0.0046
A20: TOTAL | E20: 1497.75 | F20: 0.0046
A21: Accrued Interest | E21: 0.2506125 | F21: 0
A22: Net Receivables/(Payables) | E22: -446.37061 | F22: -0.0014 | G22: 0.061074
A23: GRAND TOTAL | E23: 327296.35 | F23: 1
A28: Notes:
A29: 1. Security in default beyond its maturiy date | B29: NIL
A30: 2. NAV at the beginning of the period (Rs. per unit)
A31: Plan /option (Face Value 10) | B31: As on | C31: As on
B32: 44834 | C32: 44865
A33: Direct Plan Growth Option | B33: 10.7353 | C33: 10.7853
A34: Direct Plan IDCW Option | B34: 10.7353 | C34: 10.7853
A35: Regular Plan Growth Option | B35: 10.7353 | C35: 10.7853
A36: Regular Plan IDCW Option | B36: 10.7353 | C36: 10.7853
A38: 3. Total Dividend (Net) declared during the month | B38: NIL
A39: 4. Bonus was declared during the month | B39: NIL
A40: 5. Investment in Repo of Corporate Debt Securities during the month ended October 31, 2022 | B40: NIL
A41: 6. Investment in foreign securities/ADRs/GDRs at the end of the month | B41: NIL
A42: 7. Average Portfolio Maturity | B42: 8.1143292
A43: 8. Total gross exposure to derivative instruments (excluding reversed positions) at the end of the month (Rs. in Lakhs) | B43: NIL
A44: 9. Margin Deposits includes Margin money placed on derivatives other than margin money placed with bank | B44: NIL
A45: 10. Value of investment made by other schemes under same management (Rs. In Lakhs) | B45: NIL
A46: 11. Number of instance of deviation In valuation of securities | B46: NIL
A47: 12. Total value and percentage of illiquid equity shares / securities | B47: NIL
A49: Scheme Name | B49: Risk- O - Meter | C49: Benchmark of the Scheme | D49: Benchmark Risk-o-meter
A50: BHARAT Bond FOF - April 2031 | C50: NIFTY BHARAT Bond Index - April 2031

Sheet EDFF32
A1: PORTFOLIO STATEMENT OF BHARAT BOND FOF – APRIL 2032 AS ON OCTOBER 31, 2022 | H1: =HYPERLINK("[EDEL_Portfolio Monthly Notes 31-Oct-2022.xlsx]Index!A1","Index") -> Index
A2: (An open-ended Target Maturity fund of funds scheme investing in units of BHARAT Bond ETF – April 2032)
A4: Name of the Instrument | B4: ISIN | C4: Rating/Industry | D4: Quantity | E4: Market/Fair Value(Rs. In Lacs) | F4: % to Net Assets | G4: YIELD
A7: Equity & Equity related | E7: NIL | F7: NIL
A10: Investment in Mutual fund
A11: BHARAT BOND ETF–APRIL 2032-GROWTH | B11: INF754K01OB1 | D11: 22003848 | E11: 223094.81 | F11: 0.9967
A12: Sub Total | E12: 223094.81 | F12: 0.9967
A14: TOTAL | E14: 223094.81 | F14: 0.9967
A16: TREPS / Reverse Repo
A17: Clearing Corporation of India Ltd. | E17: 941.84 | F17: 0.0042 | G17: 0.061074
A18: Sub Total | E18: 941.84 | F18: 0.0042
A20: TOTAL | E20: 941.84 | F20: 0.0042
A21: Accrued Interest | E21: 0.1575947 | F21: 0
A22: Net Receivables/(Payables) | E22: -212.64759 | F22: -0.0009 | G22: 0.061074
A23: GRAND TOTAL | E23: 223824.16 | F23: 1
A28: Notes:
A29: 1. Security in default beyond its maturiy date | B29: NIL
A30: 2. NAV at the beginning of the period (Rs. per unit)
A31: Plan /option (Face Value 10) | B31: As on | C31: As on
B32: 44834 | C32: 44865
A33: Direct Plan Growth Option | B33: 10.0559 | C33: 10.1449
A34: Direct Plan IDCW Option | B34: 10.0559 | C34: 10.1449
A35: Regular Plan Growth Option | B35: 10.0559 | C35: 10.1449
A36: Regular Plan IDCW Option | B36: 10.0559 | C36: 10.1449
A38: 3. Total Dividend (Net) declared during the month | B38: NIL
A39: 4. Bonus was declared during the month | B39: NIL
A40: 5. Investment in Repo of Corporate Debt Securities during the month ended October 31, 2022 | B40: NIL
A41: 6. Investment in foreign securities/ADRs/GDRs at the end of the month | B41: NIL
A42: 7. Average Portfolio Maturity | B42: 9.2642486
A43: 8. Total gross exposure to derivative instruments (excluding reversed positions) at the end of the month (Rs. in Lakhs) | B43: NIL
A44: 9. Margin Deposits includes Margin money placed on derivatives other than margin money placed with bank | B44: NIL
A45: 10. Value of investment made by other schemes under same management (Rs. In Lakhs) | B45: NIL
A46: 11. Number of instance of deviation In valuation of securities | B46: NIL
A47: 12. Total value and percentage of illiquid equity shares / securities | B47: NIL
A50: Scheme Name | B50: Risk- O - Meter | C50: Benchmark of the Scheme | D50: Benchmark Risk-o-meter
A51: BHARAT Bond FOF - April 2032 | C51: Nifty BHARAT Bond Index – April 2032

Sheet EDGSEC
A1: PORTFOLIO STATEMENT OF EDELWEISS GOVERNMENT SECURITIES FUND AS ON OCTOBER 31, 2022 | H1: =HYPERLINK("[EDEL_Portfolio Monthly Notes 31-Oct-2022.xlsx]Index!A1","Index") -> Index
A2: (An open ended debt scheme investing in government securities across maturity)
A4: Name of the Instrument | B4: ISIN | C4: Rating/Industry | D4: Quantity | E4: Market/Fair Value(Rs. In Lacs) | F4: % to Net Assets | G4: YIELD
A7: Equity & Equity related | E7: NIL | F7: NIL
A8: Debt Instruments
A9: (a) Listed / Awaiting listing on Stock Exchanges
A10: Sub Total | E10: NIL | F10: NIL
A12: Government Securities
A13: 7.38% GOVT OF INDIA RED 20-06-2027 | B13: IN0020220037 | C13: SOVEREIGN | D13: 7000000 | E13: 6999.59 | F13: 0.61 | G13: 0.073781
A14: 7.26% GOVT OF INDIA RED 22-08-2032 | B14: IN0020220060 | C14: SOVEREIGN | D14: 2000000 | E14: 1974.02 | F14: 0.172 | G14: 0.074467
A15: 6.95% GOVT OF INDIA RED 16-12-2061 | B15: IN0020210202 | C15: SOVEREIGN | D15: 389100 | E15: 359.11 | F15: 0.0313 | G15: 0.075659
A16: Sub Total | E16: 9332.72 | F16: 0.8133
A18: State Development Loan
A19: 8.38% GUJARAT SDL RED 27-02-2029 | B19: IN1520180309 | C19: SOVEREIGN | D19: 9100 | E19: 9.41 | F19: 0.0008 | G19: 0.076882
A20: Sub Total | E20: 9.41 | F20: 0.0008
A23: (b)Privately Placed/Unlisted
A24: Sub Total | E24: NIL | F24: NIL
A26: (c)Securitised Debt Instruments
A27: Sub Total | E27: NIL | F27: NIL
A29: TOTAL | E29: 9342.13 | F29: 0.8141
A32: TREPS / Reverse Repo
A33: Clearing Corporation of India Ltd. | E33: 1880.69 | F33: 0.1639 | G33: 0.061074
A34: Sub Total | E34: 1880.69 | F34: 0.1639
A36: TOTAL | E36: 1880.69 | F36: 0.1639
A37: Accrued Interest | E37: 226.40618 | F37: 0.01973
A38: Net Receivables/(Payables) | E38: 25.453824 | F38: 0.00227 | G38: 0.061074
A39: GRAND TOTAL | E39: 11474.68 | F39: 1
A41: **Non Traded Security
A44: Notes:
A45: 1. Security in default beyond its maturiy date | B45: NIL
A46: 2. NAV at the beginning of the period (Rs. per unit)
A47: Plan /option (Face Value 10) | B47: As on | C47: As on
B48: 44834 | C48: 44865
A49: Direct Plan Annual IDCW Option | B49: ^ | C49: ^
A50: Direct Plan Bonus Option | B50: ^ | C50: ^
A51: Direct Plan Fortnightly IDCW Option | B51: 20.0005 | C51: 20.0227
A52: Direct Plan Growth Option | B52: 20.8707 | C52: 20.9137
A53: Direct Plan IDCW Option | B53: 20.7875 | C53: 20.8304
A54: Direct Plan Monthly IDCW Option | B54: 16.6046 | C54: 16.6171
A55: Direct Plan Weekly IDCW Option | B55: 16.0779 | C55: 16.0394
A56: Regular Plan - Annual IDCW Option | B56: 19.9855 | C56: 20.0157
A57: Regular Plan Bonus Option | B57: ^ | C57: ^
A58: Regular Plan Fortnightly IDCW Option | B58: 19.4791 | C58: 19.4962
A59: Regular Plan Growth Option | B59: 19.9768 | C59: 20.0069
A60: Regular Plan IDCW Option | B60: 19.9897 | C60: 20.02
A61: Regular Plan Monthly IDCW Option | B61: 10.371 | C61: 10.3779
A62: Regular Plan Weekly IDCW Option | B62: 10.2175 | C62: 10.2329
A63: ^ There were no investors in this option.
A65: 3. Total Dividend (Net) declared during the month
A67: Plan/Option Name | C67: individual & HUF | D67: others
A68: Direct Plan Fortnightly IDCW | C68: 0.0191607 | D68: 0.0191607
A69: Direct Plan Monthly IDCW | C69: 0.0218626 | D69: 0.0218626
A70: Direct Plan weekly IDCW | C70: 0.0716293 | D70: 0.0716293
A71: Regular Plan Fortnightly IDCW | C71: 0.0125377 | D71: 0.0125377
A72: Regular Plan Monthly IDCW | C72: 0.0088026 | D72: 0.0088026
A74: 4. Bonus was declared during the month | B74: NIL
A75: 5. Investment in Repo of Corporate Debt Securities during the month ended October 31, 2022 | B75: NIL
A76: 6. Investment in foreign securities/ADRs/GDRs at the end of the month | B76: NIL
A77: 7. Average Portfolio Maturity | B77: 5.8808838
A78: 8. Total gross exposure to derivative instruments (excluding reversed positions) at the end of the month (Rs. in Lakhs) | B78: NIL
A79: 9. Margin Deposits includes Margin money placed on derivatives other than margin money placed with bank | B79: NIL
A80: 10. Value of investment made by other schemes under same management (Rs. In Lakhs) | B80: NIL
A81: 11. Number of instance of deviation In valuation of securities | B81: NIL
A82: 12. Total value and percentage of illiquid equity shares / securities | B82: NIL
A85: Scheme Name | B85: Risk- O - Meter | C85: Benchmark of the Scheme | D85: Benchmark Risk-o-meter | E85: Benchmark of the Scheme | F85: Benchmark Risk-o-meter
A86: Edelweiss Government Securities Fund | C86: NIFTY All Duration G-Sec Index (TIER - 1) | E86: Nifty G -Sec Index A -III (TIER - 2)

Sheet EDNP27
A1: PORTFOLIO STATEMENT OF EDELWEISS NIFTY PSU BOND PLUS SDL APR 2027 50 50 INDEX AS ON OCTOBER 31, 2022 | H1: =HYPERLINK("[EDEL_Portfolio Monthly Notes 31-Oct-2022.xlsx]Index!A1","Index") -> Index
A2: (An open-ended target Maturuty index fund predominantly investing in the constituents of Nifty PSU Bond Plus SDL April 2027 50:50 Index)
A4: Name of the Instrument | B4: ISIN | C4: Rating/Industry | D4: Quantity | E4: Market/Fair Value(Rs. In Lacs) | F4: % to Net Assets | G4: YIELD
A7: Equity & Equity related | E7: NIL | F7: NIL
A9: Debt Instruments
A10: (a)Listed / Awaiting listing on stock Exchanges
A11: 7.32% EXIM NCD RED 08-06-2026** | B11: INE514E08FZ5 | C11: CRISIL AAA | D11: 20000000 | E11: 19910.64 | F11: 0.0754 | G11: 0.07445
A12: 7.18% POWER FIN GOI SERVICD NCD 20-01-27** | B12: INE134E08IR3 | C12: CRISIL AAA | D12: 16000000 | E12: 15864.58 | F12: 0.0601 | G12: 0.0755
A13: 7.75% POWER FIN COR GOI SER NCD 22-03-27** | B13: INE134E08IX1 | C13: CRISIL AAA | D13: 15000000 | E13: 15184.86 | F13: 0.0575 | G13: 0.075575
A14: 6.14% IND OIL COR NCD 18-02-27** | B14: INE242A08502 | C14: CRISIL AAA | D14: 15000000 | E14: 14245.52 | F14: 0.054 | G14: 0.0754
A15: 7.83% IRFC LTD NCD RED 19-03-2027** | B15: INE053F07983 | C15: CRISIL AAA | D15: 11000000 | E15: 11141.54 | F15: 0.0422 | G15: 0.07485
A16: 7.89% POWER GRID CORP NCD RED 09-03-2027** | B16: INE752E07OE0 | C16: CRISIL AAA | D16: 11000000 | E16: 11139.24 | F16: 0.0422 | G16: 0.0752
A17: 7.95% RECL SR 147 NCD RED 12-03-2027** | B17: INE020B08AH8 | C17: CRISIL AAA | D17: 5000000 | E17: 5060.83 | F17: 0.0192 | G17: 0.07595
A18: 7.54% REC LTD NCD RED 30-12-2026 | B18: INE020B08AC9 | C18: CRISIL AAA | D18: 3500000 | E18: 3492.63 | F18: 0.0132 | G18: 0.0759
A19: 7.25% EXIM BANK NCD RED 01-02-2027** | B19: INE514E08FJ9 | C19: CRISIL AAA | D19: 3000000 | E19: 2964.67 | F19: 0.0112 | G19: 0.0757
A20: 7.13% NHPC STRPP B NCD 11-02-2027** | B20: INE848E07AZ0 | C20: CARE AAA | D20: 3000000 | E20: 2954.82 | F20: 0.0112 | G20: 0.0754
A21: 8.14% NUCLEAR POWER CORP NCD 25-03-2027** | B21: INE206D08279 | C21: CRISIL AAA | D21: 2700000 | E21: 2772.22 | F21: 0.0105 | G21: 0.075503
A22: 8.85% POWER GRID CORP NCD KRED 19-10-26** | B22: INE752E07KL3 | C22: CRISIL AAA | D22: 2500000 | E22: 2614.04 | F22: 0.0099 | G22: 0.07475
... A27: 6.09% HPCL NCD RED 26-02-2027** | B27: INE094A08101 | C27: CRISIL AAA | D27: 500000 | E27: 474.15 | F27: 0.0018 | G27: 0.075225
A28: Sub Total | E28: 115397.81 | F28: 0.4371
A30: Government Securities
A31: 5.74% GOVT OF INDIA RED 15-11-2026 | B31: IN0020210186 | C31: SOVEREIGN | D31: 2000000 | E31: 1891.72 | F31: 0.0072 | G31: 0.073113
A32: Sub Total | E32: 1891.72 | F32: 0.0072
A33: State Development Loan
A34: 6.58% GUJARAT SDL RED 31-03-2027 | B34: IN1520200347 | C34: SOVEREIGN | D34: 14000000 | E34: 13537.97 | F34: 0.0513 | G34: 0.074691
A35: 7.78% BIHAR SDL RED 01-03-2027 | B35: IN1320160170 | C35: SOVEREIGN | D35: 10500000 | E35: 10594.21 | F35: 0.0401 | G35: 0.075291
A36: 7.20% UTTAR PRADESH SDL 25-01-2027 | B36: IN3320160309 | C36: SOVEREIGN | D36: 10000000 | E36: 9879.9 | F36: 0.0374 | G36: 0.07532
A37: 7.80% KERALA SDL RED 15-03-2027 | B37: IN2020160155 | C37: SOVEREIGN | D37: 9500000 | E37: 9605.53 | F37: 0.0364 | G37: 0.074937
A38: 7.75% KARNATAKA SDL RED 01-03-2027 | B38: IN1920160109 | C38: SOVEREIGN | D38: 8500000 | E38: 8582.29 | F38: 0.0325 | G38: 0.0748
A39: 7.59% GUJARAT SDL RED 15-02-2027 | B39: IN1520160194 | C39: SOVEREIGN | D39: 8500000 | E39: 8529.51 | F39: 0.0323 | G39: 0.074891
A40: 8.31% RAJASTHAN SDL RED 08-04-2027 | B40: IN2920200036 | C40: SOVEREIGN | D40: 7500000 | E40: 7710.96 | F40: 0.0292 | G40: 0.075497
A41: 7.92% WEST BENGAL SDL 15-03-2027 | B41: IN3420160175 | C41: SOVEREIGN | D41: 6500000 | E41: 6592.22 | F41: 0.025 | G41: 0.075294
A42: 7.61% TAMIL NADU SDL RED 15-02-2027 | B42: IN3120160194 | C42: SOVEREIGN | D42: 5500000 | E42: 5524.67 | F42: 0.0209 | G42: 0.074811
A43: 7.59% RAJASTHAN SDL RED 15-02-2027 | B43: IN2920160412 | C43: SOVEREIGN | D43: 5500000 | E43: 5510.33 | F43: 0.0209 | G43: 0.075332
A44: 7.74% TAMIL NADU SDL RED 01-03-2027 | B44: IN3120161309 | C44: SOVEREIGN | D44: 5000000 | E44: 5046.38 | F44: 0.0191 | G44: 0.074811
A45: 7.78% WEST BENGAL SDL 01-03-2027 | B45: IN3420160167 | C45: SOVEREIGN | D45: 5000000 | E45: 5044.81 | F45: 0.0191 | G45: 0.075294
... A59: 7.64% WEST BENGAL SDL RED 29-03-2027 | B59: IN3420160183 | C59: SOVEREIGN | D59: 1000000 | E59: 1003.98 | F59: 0.0038 | G59: 0.075294
A60: Sub Total | E60: 138089.22 | F60: 0.523
A63: (b)Privately Placed/Unlisted
A64: Sub Total | E64: NIL | F64: NIL
A66: (c)Securitised Debt Instruments
A67: Sub Total | E67: NIL | F67: NIL
A69: TOTAL | E69: 255378.75 | F69: 0.9673
A72: TREPS / Reverse Repo
A73: Clearing Corporation of India Ltd. | E73: 3322.44 | F73: 0.0126 | G73: 0.061074
A74: Sub Total | E74: 3322.44 | F74: 0.0126
A76: TOTAL | E76: 3322.44 | F76: 0.0126
A77: Accrued Interest | E77: 5268.8851 | F77: 0.01996
A78: Net Receivables/(Payables) | E78: -1.9150796 | F78: 0.00014 | G78: 0.061074
A79: GRAND TOTAL | E79: 263968.16 | F79: 1
A81: **Non Traded Security
A84: Notes:
A85: 1. Security in default beyond its maturiy date | B85: NIL
A86: 2. NAV at the beginning of the period (Rs. per unit)
A87: Plan /option (Face Value 10) | B87: As on | C87: As on
B88: 44834 | C88: 44865
A89: Direct Plan Growth Option | B89: 10.118 | C89: 10.1657
A90: Direct Plan IDCW Option | B90: 10.1167 | C90: 10.1644
A91: Regular Plan Growth Option | B91: 10.1013 | C91: 10.1473
A92: Regular Plan IDCW Option | B92: 10.1015 | C92: 10.1476
A94: 3. Total Dividend (Net) declared during the month | B94: NIL
A95: 4. Bonus was declared during the month | B95: NIL
A96: 5. Investment in Repo of Corporate Debt Securities during the month ended October 31, 2022 | B96: NIL
A97: 6. Investment in foreign securities/ADRs/GDRs at the end of the month | B97: NIL
A98: 7. Average Portfolio Maturity | B98: 4.2039472
A99: 8. Total gross exposure to derivative instruments (excluding reversed positions) at the end of the month (Rs. in Lakhs) | B99: NIL
A100: 9. Margin Deposits includes Margin money placed on derivatives other than margin money placed with bank | B100: NIL
A101: 10. Value of investment made by other schemes under same management (Rs. In Lakhs) | B101: NIL
A102: 11. Number of instance of deviation In valuation of securities | B102: NIL
A103: 12. Total value and percentage of illiquid equity shares / securities | B103: NIL
A106: Scheme Name | B106: Risk- O - Meter | C106: Benchmark of the Scheme | D106: Benchmark Risk-o-meter
A107: Edelweiss Nifty PSU Bond Plus SDL Apr2027 50 50 Index | C107: Nifty PSU Bond Plus SDL Apr 2027 50:50 Index

Sheet EDNPSF
A1: PORTFOLIO STATEMENT OF EDELWEISS NIFTY PSU BOND PLUS SDL APR 2026 50 50 INDEX FUND AS ON OCTOBER 31, 2022 | H1: =HYPERLINK("[EDEL_Portfolio Monthly Notes 31-Oct-2022.xlsx]Index!A1","Index") -> Index
A2: (An open-ended target Maturuty index fund predominantly investing in the constituents of Nifty PSU Bond Plus SDL April 2026 50:50 Index)
A4: Name of the Instrument | B4: ISIN | C4: Rating/Industry | D4: Quantity | E4: Market/Fair Value(Rs. In Lacs) | F4: % to Net Assets | G4: YIELD
A7: Equity & Equity related | E7: NIL | F7: NIL
A9: Debt Instruments
A10: (a)Listed / Awaiting listing on stock Exchanges
A11: 7.40% NABARD NCD RED 30-01-2026** | B11: INE261F08DO9 | C11: CRISIL AAA | D11: 92500000 | E11: 92043.79 | F11: 0.1228 | G11: 0.07575
A12: 7.10% EXIM NCD RED 18-03-2026 | B12: INE514E08GA6 | C12: CRISIL AAA | D12: 51500000 | E12: 51054.78 | F12: 0.0681 | G12: 0.074
A13: 7.11% SIDBI NCD RED 27-02-2026** | B13: INE556F08KB4 | C13: ICRA AAA | D13: 51000000 | E13: 50265.04 | F13: 0.0671 | G13: 0.0762
A14: 5.94% REC LTD. NCD RED 31-01-2026** | B14: INE020B08DK6 | C14: CRISIL AAA | D14: 19000000 | E14: 18141.5 | F14: 0.0242 | G14: 0.07545
A15: 9.18% NUCLEAR POWER NCD RED 23-01-2026** | B15: INE206D08188 | C15: CRISIL AAA | D15: 11200000 | E15: 11821.53 | F15: 0.0158 | G15: 0.073457
A16: 5.85% REC LTD NCD RED 20-12-2025** | B16: INE020B08DF6 | C16: CRISIL AAA | D16: 12000000 | E16: 11445.86 | F16: 0.0153 | G16: 0.0755
A17: 6.18% MANGALORE REF & PET NCD 29-12-2025 | B17: INE103A08043 | C17: CARE AAA | D17: 11000000 | E17: 10572.14 | F17: 0.0141 | G17: 0.075998
A18: 5.81% REC LTD. NCD RED 31-12-2025** | B18: INE020B08DH2 | C18: CRISIL AAA | D18: 10500000 | E18: 9999.11 | F18: 0.0133 | G18: 0.0755
A19: 7.13% NHPC LTD AA STRPP A NCD 11-02-2026** | B19: INE848E07AY3 | C19: CARE AAA | D19: 7600000 | E19: 7536.08 | F19: 0.0101 | G19: 0.0741
A20: 8.18% EXIM BANK NCD RED 07-12-2025** | B20: INE514E08EU9 | C20: CRISIL AAA | D20: 6500000 | E20: 6632.5 | F20: 0.0088 | G20: 0.0741
A21: 9.09% INDIAN RAIL FIN NCD RED 29-03-2026** | B21: INE053F09HM3 | C21: CRISIL AAA | D21: 6000000 | E21: 6315.73 | F21: 0.0084 | G21: 0.0745
A22: 8.02% EXIM BANK NCD RED 20-04-2026** | B22: INE514E08FB6 | C22: CRISIL AAA | D22: 6000000 | E22: 6097.79 | F22: 0.0081 | G22: 0.07445
... A34: 5.60% INDIAN OIL CORP NCD 23-01-2026** | B34: INE242A08494 | C34: CRISIL AAA | D34: 500000 | E34: 473.05 | F34: 0.0006 | G34: 0.0753
A35: Sub Total | E35: 308818.09 | F35: 0.4119
A37: Government Securities
A38: 5.63% GOVT OF INDIA RED 12-04-2026 | B38: IN0020210012 | C38: SOVEREIGN | D38: 19000000 | E38: 18043.37 | F38: 0.0241 | G38: 0.073071
A39: Sub Total | E39: 18043.37 | F39: 0.0241
A40: State Development Loan
A41: 6.18% GUJARAT SDL RED 31-03-2026 | B41: IN1520200339 | C41: SOVEREIGN | D41: 30000000 | E41: 28882.29 | F41: 0.0385 | G41: 0.07433
A42: 8.38% KARNATAKA SDL RED 27-01-2026 | B42: IN1920150084 | C42: SOVEREIGN | D42: 25000000 | E42: 25647.6 | F42: 0.0342 | G42: 0.074582
A43: 8.54% BIHAR SDL RED 10-02-2026 | B43: IN1320150031 | C43: SOVEREIGN | D43: 24500000 | E43: 25224.81 | F43: 0.0336 | G43: 0.074977
A44: 8.51% MAHARASHTRA SDL RED 09-03-2026 | B44: IN2220150204 | C44: SOVEREIGN | D44: 24000000 | E44: 24729.17 | F44: 0.033 | G44: 0.074643
A45: 8.67% KARNATAKA SDL RED 24-02-2026 | B45: IN1920150092 | C45: SOVEREIGN | D45: 18500000 | E45: 19144.19 | F45: 0.0255 | G45: 0.074583
A46: 8.3% RAJASTHAN SDL RED 13-01-2026 | B46: IN2920150223 | C46: SOVEREIGN | D46: 17500000 | E46: 17885.47 | F46: 0.0239 | G46: 0.075064
A47: 8.53% TAMIL NADU SDL RED 09-03-2026 | B47: IN3120150211 | C47: SOVEREIGN | D47: 16500000 | E47: 17007.41 | F47: 0.0227 | G47: 0.074715
A48: 8.76% MADHYA PRADESH SDL RED 24-02-2026 | B48: IN2120150106 | C48: SOVEREIGN | D48: 15500000 | E48: 16051.85 | F48: 0.0214 | G48: 0.075197
A49: 8.38% TAMILNADU SDL RED 27-01-2026 | B49: IN3120150187 | C49: SOVEREIGN | D49: 15500000 | E49: 15895.62 | F49: 0.0212 | G49: 0.074714
A50: 8.57% ANDHRA PRADESH SDL RED 09-03-2026 | B50: IN1020150141 | C50: SOVEREIGN | D50: 14500000 | E50: 14954.53 | F50: 0.0199 | G50: 0.074907
A51: 8.28% KARNATAKA SDL RED 06-03-2026 | B51: IN1920180198 | C51: SOVEREIGN | D51: 13500000 | E51: 13821.17 | F51: 0.0184 | G51: 0.074582
A52: 8.48% RAJASTHAN SDL RED 10-02-2026 | B52: IN2920150249 | C52: SOVEREIGN | D52: 11500000 | E52: 11817.62 | F52: 0.0158 | G52: 0.075064
... A86: 6.70% ANDHRA PRADESH SDL RED 22-04-2026 | B86: IN1020200078 | C86: SOVEREIGN | D86: 500000 | E86: 488.48 | F86: 0.0007 | G86: 0.074643
A87: Sub Total | E87: 400854.49 | F87: 0.5345
A90: (b)Privately Placed/Unlisted
A91: Sub Total | E91: NIL | F91: NIL
A93: (c)Securitised Debt Instruments
A94: Sub Total | E94: NIL | F94: NIL
A96: TOTAL | E96: 727715.95 | F96: 0.9705
A99: TREPS / Reverse Repo
A100: Clearing Corporation of India Ltd. | E100: 6030.99 | F100: 0.008 | G100: 0.061074
A101: Sub Total | E101: 6030.99 | F101: 0.008
A103: TOTAL | E103: 6030.99 | F103: 0.008
A104: Accrued Interest | E104: 16222.141 | F104: 0.02164
A105: Net Receivables/(Payables) | E105: -344.25106 | F105: -0.00014 | G105: 0.061074
A106: GRAND TOTAL | E106: 749624.83 | F106: 1
A108: **Non Traded Security
A111: Notes:
A112: 1. Security in default beyond its maturiy date | B112: NIL
A113: 2. NAV at the beginning of the period (Rs. per unit)
A114: Plan /option (Face Value 10) | B114: As on | C114: As on
B115: 44834 | C115: 44865
A116: Direct Plan Growth Option | B116: 10.6745 | C116: 10.7285
A117: Direct Plan IDCW Option | B117: 10.675 | C117: 10.729
A118: Regular Plan Growth Option | B118: 10.6485 | C118: 10.7008
A119: Regular Plan IDCW Option | B119: 10.6491 | C119: 10.7015
A121: 3. Total Dividend (Net) declared during the month | B121: NIL
A122: 4. Bonus was declared during the month | B122: NIL
A123: 5. Investment in Repo of Corporate Debt Securities during the month ended October 31, 2022 | B123: NIL
A124: 6. Investment in foreign securities/ADRs/GDRs at the end of the month | B124: NIL
A125: 7. Average Portfolio Maturity | B125: 3.2698712
A126: 8. Total gross exposure to derivative instruments (excluding reversed positions) at the end of the month (Rs. in Lakhs) | B126: NIL
A127: 9. Margin Deposits includes Margin money placed on derivatives other than margin money placed with bank | B127: NIL
A128: 10. Value of investment made by other schemes under same management (Rs. In Lakhs) | B128: NIL
A129: 11. Number of instance of deviation In valuation of securities | B129: NIL
A130: 12. Total value and percentage of illiquid equity shares / securities | B130: NIL
A132: Scheme Name | B132: Risk- O - Meter | C132: Benchmark of the Scheme | D132: Benchmark Risk-o-meter
A133: Edelweiss Nifty PSU Bond Plus SDL Apr2026 50 50 Index Fund | C133: Nifty PSU Bond Plus SDL Apr 2026 50:50 Index

Sheet EDONTF
A1: PORTFOLIO STATEMENT OF EDELWEISS OVERNIGHT FUND AS ON OCTOBER 31, 2022 | H1: =HYPERLINK("[EDEL_Portfolio Monthly Notes 31-Oct-2022.xlsx]Index!A1","Index") -> Index
A2: (An open-ended debt scheme investing in overnight instruments.)
A4: Name of the Instrument | B4: ISIN | C4: Rating/Industry | D4: Quantity | E4: Market/Fair Value(Rs. In Lacs) | F4: % to Net Assets | G4: YIELD
A7: Equity & Equity related | E7: NIL | F7: NIL
A9: Money Market Instruments
A11: Treasury bills
A12: 91 DAYS TBILL RED 03-11-2022 | B12: IN002022X189 | C12: SOVEREIGN | D12: 500000 | E12: 499.84 | F12: 0.0087 | G12: 0.060245
A13: 182 DAYS TBILL RED 24-11-2022 | B13: IN002022Y088 | C13: SOVEREIGN | D13: 500000 | E13: 498.11 | F13: 0.0087 | G13: 0.060247
A14: Sub Total | E14: 997.95 | F14: 0.0174
A16: TOTAL | E16: 997.95 | F16: 0.0174
A19: TREPS / Reverse Repo
A20: Clearing Corporation of India Ltd. | E20: 56547.54 | F20: 0.9838 | G20: 0.061074
A21: Sub Total | E21: 56547.54 | F21: 0.9838
A23: TOTAL | E23: 56547.54 | F23: 0.9838
A24: Accrued Interest | E24: 9.4618749 | F24: 0.000164
A25: Net Receivables/(Payables) | E25: -74.381875 | F25: -0.001364 | G25: 0.061074
A26: GRAND TOTAL | E26: 57480.57 | F26: 1
A31: Notes:
A32: 1. Security in default beyond its maturiy date | B32: NIL
A33: 2. NAV at the beginning of the period (Rs. per unit)
A34: Plan /option (Face Value 1000) | B34: As on | C34: As on
B35: 44834 | C35: 44865
A36: Direct Plan Annual IDCW Option | B36: 1127.24 | C36: 1132.8745
A37: Direct Plan Daily IDCW Option | B37: 1000 | C37: 1000.0265
A38: Direct Plan Fortnightly IDCW Option | B38: ^ | C38: ^
A39: Direct Plan Growth Option | B39: 1126.8954 | C39: 1132.5174
A40: Direct Plan Monthly IDCW Option | B40: 1058.287 | C40: 1058.5359
A41: Direct Plan Weekly IDCW Option | B41: ^ | C41: ^
A42: Regular Annual IDCW Option | B42: 1124.7737 | C42: 1130.3374
A43: Regular Daily IDCW Option | B43: 1008.1128 | C43: 1008.1128
A44: Regular Plan Fortnightly IDCW Option | B44: 1095.2912 | C44: 1095.5047
A45: Regular Plan Growth Option | B45: 1124.7737 | C45: 1130.337
A46: Regular Plan Monthly IDCW Option | B46: 1004.1841 | C46: 1004.424
A47: Regular Plan Weekly IDCW Option | B47: 1016.2401 | C47: 1016.7791
A48: Unclaimed IDCW less than 3 yrs | B48: 1031.0471 | C48: 1036.1909
A49: Unclaimed IDCW more than 3 yrs | B49: 1000 | C49: 1000
A50: Unclaimed Redemption less than 3 yrs | B50: 1031.0471 | C50: 1036.1909
A51: Unclaimed Redemption more than 3 yrs | B51: 1000 | C51: 1000
A52: ^ There were no investors in this option.
A54: 3. Total Dividend (Net) declared during the month
A56: Plan/Option Name | C56: individual & HUF | D56: others
A57: Direct Daily IDCW | C57: 4.9517228 | D57: 4.9517228
A58: Direct Monthly IDCW | C58: 5.0284552 | D58: 5.0284552
A59: Regular Daily IDCW | C59: 4.9792627 | D59: 4.9792627
A60: Regular Fortnightly IDCW | C60: 5.1622244 | D60: 5.1622244
A61: Regular Monthly IDCW | C61: 4.7298459 | D61: 4.7298459
A62: Regular Weekly IDCW | C62: 4.4881723 | D62: 4.4881723
A66: 4. Bonus was declared during the month | B66: NIL
A67: 5. Investment in Repo of Corporate Debt Securities during the month ended October 31, 2022 | B67: NIL
A68: 6. Investment in foreign securities/ADRs/GDRs at the end of the month | B68: NIL
A69: 7. Average Portfolio Maturity | B69: 0.00059370521
A70: 8. Total gross exposure to derivative instruments (excluding reversed positions) at the end of the month (Rs. in Lakhs) | B70: NIL
A71: 9. Margin Deposits includes Margin money placed on derivatives other than margin money placed with bank | B71: NIL
A72: 10. Value of investment made by other schemes under same management (Rs. In Lakhs) | B72: NIL
A73: 11. Number of instance of deviation In valuation of securities | B73: NIL
A74: 12. Total value and percentage of illiquid equity shares / securities | B74: NIL
A76: Scheme Name | B76: Risk- O - Meter | C76: Benchmark of the Scheme | D76: Benchmark Risk-o-meter
A77: EDELWEISS OVERNIGHT FUND | C77: NIFTY 1D Rate Index

Sheet EEARBF
A1: PORTFOLIO STATEMENT OF EDELWEISS ARBITRAGE FUND AS ON OCTOBER 31, 2022 | H1: =HYPERLINK("[EDEL_Portfolio Monthly Notes 31-Oct-2022.xlsx]Index!A1","Index") -> Index
A2: (An open ended scheme investing in arbitrage opportunities)
A4: Name of the Instrument | B4: ISIN | C4: Rating/Industry | D4: Quantity | E4: Market/Fair Value(Rs. In Lacs) | F4: % to Net Assets | G4: YIELD
A6: Equity & Equity related
A7: (a)Listed / Awaiting listing on Stock Exchanges
A8: Adani Ports & Special Economic Zone Ltd. | B8: INE742F01042 | C8: Transport Infrastructure | D8: 2591250 | E8: 21340.24 | F8: 0.0386
A9: Kotak Mahindra Bank Ltd. | B9: INE237A01028 | C9: Banks | D9: 811200 | E9: 15428.62 | F9: 0.0279
A10: Reliance Industries Ltd. | B10: INE002A01018 | C10: Petroleum Products | D10: 544250 | E10: 13876.2 | F10: 0.0251
A11: Ashok Leyland Ltd. | B11: INE208A01029 | C11: Agricultural, Commercial & Construction Vehicles | D11: 8545000 | E11: 13099.49 | F11: 0.0237
A12: Adani Enterprises Ltd. | B12: INE423A01024 | C12: Metals & Minerals Trading | D12: 332000 | E12: 11113.53 | F12: 0.0201
A13: Hindalco Industries Ltd. | B13: INE038A01020 | C13: Non - Ferrous Metals | D13: 2449925 | E13: 9938.12 | F13: 0.018
A14: Hindustan Aeronautics Ltd. | B14: INE066F01012 | C14: Aerospace & Defense | D14: 386175 | E14: 9770.42 | F14: 0.0177
A15: Punjab National Bank | B15: INE160A01022 | C15: Banks | D15: 22048000 | E15: 9403.47 | F15: 0.017
A16: Zee Entertainment Enterprises Ltd. | B16: INE256A01028 | C16: Entertainment | D16: 3396000 | E16: 8912.8 | F16: 0.0161
A17: Housing Development Finance Corporation Ltd. | B17: INE001A01036 | C17: Finance | D17: 345300 | E17: 8528.22 | F17: 0.0154
A18: UPL Ltd. | B18: INE628A01036 | C18: Fertilizers & Agrochemicals | D18: 1063400 | E18: 7764.95 | F18: 0.014
A19: ICICI Bank Ltd. | B19: INE090A01021 | C19: Banks | D19: 851125 | E19: 7734.17 | F19: 0.014
... A161: Whirlpool of India Ltd. | B161: INE716A01013 | C161: Consumer Durables | D161: 700 | E161: 11.03 | F161: 0
A162: Sub Total | E162: 400297.08 | F162: 0.7235
A163: (b) Unlisted
A164: Sub Total | E164: NIL | F164: NIL
A165: TOTAL | E165: 400297.08 | F165: 0.7235
A167: Derivatives
A168: (a) Index/Stock Future
A169: Whirlpool of India Ltd.24/11/2022 | C169: Consumer Durables | D169: -700 | E169: -11.08 | F169: -2e-05
A170: Colgate Palmolive (India) Ltd.24/11/2022 | C170: Personal Products | D170: -1050 | E170: -17.23 | F170: -3.1e-05
A171: United Breweries Ltd.24/11/2022 | C171: Beverages | D171: -1200 | E171: -19.94 | F171: -3.6e-05
A172: Page Industries Ltd.24/11/2022 | C172: Textiles & Apparels | D172: -60 | E172: -29.87 | F172: -5.3e-05
A173: Gujarat Gas Ltd.24/11/2022 | C173: Gas | D173: -6250 | E173: -32.39 | F173: -5.8e-05
A174: Torrent Pharmaceuticals Ltd.24/11/2022 | C174: Pharmaceuticals & Biotechnology | D174: -2000 | E174: -33.1 | F174: -5.9e-05
A175: Granules India Ltd.24/11/2022 | C175: Pharmaceuticals & Biotechnology | D175: -10000 | E175: -37.44 | F175: -6.7e-05
A176: Intellect Design Arena Ltd.24/11/2022 | C176: IT - Software | D176: -9000 | E176: -39.1 | F176: -7e-05
A177: Vodafone Idea Ltd.29/12/2022 | C177: Telecom - Services | D177: -700000 | E177: -60.9 | F177: -0.00011
A178: Alkem Laboratories Ltd.24/11/2022 | C178: Pharmaceuticals & Biotechnology | D178: -2000 | E178: -63.36 | F178: -0.000114
A179: Oil & Natural Gas Corporation Ltd.24/11/2022 | C179: Oil | D179: -57750 | E179: -77.88 | F179: -0.00014
A180: Abbott India Ltd.24/11/2022 | C180: Pharmaceuticals & Biotechnology | D180: -480 | E180: -92.88 | F180: -0.000167
... A323: Adani Ports & Special Economic Zone Ltd.24/11/2022 | C323: Transport Infrastructure | D323: -2591250 | E323: -21440 | F323: -0.038736
A324: Sub Total | E324: -401965.6 | F324: -0.726177
A328: TOTAL | E328: -401965.6 | F328: -0.726177
A330: Debt Instruments
A331: (a)Listed / Awaiting listing on stock Exchanges
A332: 7.21% HDFC LTD NCD RED 30-12-2022** | B332: INE001A07SD3 | C332: CRISIL AAA | D332: 12500000 | E332: 12498.93 | F332: 0.0226 | G332: 0.068498
A333: Sub Total | E333: 12498.93 | F333: 0.0226
A335: Government Securities
A336: 7.16% GOVT OF INDIA RED 20-05-2023 | B336: IN0020130012 | C336: SOVEREIGN | D336: 12500000 | E336: 12516.2 | F336: 0.0226 | G336: 0.069062
A337: 8.83% GOVT OF INDIA RED 25-11-2023 | B337: IN0020130061 | C337: SOVEREIGN | D337: 10000000 | E337: 10180.23 | F337: 0.0184 | G337: 0.070378
A338: 6.84% GOVT OF INDIA RED 19-12-2022 | B338: IN0020160050 | C338: SOVEREIGN | D338: 5000000 | E338: 5003.48 | F338: 0.009 | G338: 0.062455
A339: 3.96% GOVT OF INDIA RED 09-11-2022 | B339: IN0020200260 | C339: SOVEREIGN | D339: 5000000 | E339: 4997.59 | F339: 0.009 | G339: 0.061061
A340: 6.69% GOVT OF INDIA RED 27-06-2024 | B340: IN0020220052 | C340: SOVEREIGN | D340: 5000000 | E340: 4975.38 | F340: 0.009 | G340: 0.070022
A341: Sub Total | E341: 37672.88 | F341: 0.068
A343: (b)Privately Placed/Unlisted
A344: Sub Total | E344: NIL | F344: NIL
A346: (c)Securitised Debt Instruments
A347: Sub Total | E347: NIL | F347: NIL
A349: TOTAL | E349: 50171.81 | F349: 0.0906
A351: Money Market Instruments
A353: Treasury bills
A354: 182 DAYS TBILL RED 15-12-2022 | B354: IN002022Y112 | C354: SOVEREIGN | D354: 10000000 | E354: 9926.41 | F354: 0.0179 | G354: 0.061499
A355: 364 DAYS TBILL RED 19-01-2023 | B355: IN002021Z442 | C355: SOVEREIGN | D355: 10000000 | E355: 9862.85 | F355: 0.0178 | G355: 0.064248
A356: 364 DAYS TBILL RED 16-03-2023 | B356: IN002021Z525 | C356: SOVEREIGN | D356: 10000000 | E356: 9762.77 | F356: 0.0176 | G356: 0.0657
A357: 364 DAYS TBILL RED 29-06-2023 | B357: IN002022Z135 | C357: SOVEREIGN | D357: 10000000 | E357: 9569.91 | F357: 0.0173 | G357: 0.06835
A358: 364 DAYS TBILL RED 22-06-2023 | B358: IN002022Z127 | C358: SOVEREIGN | D358: 7500000 | E358: 7186.45 | F358: 0.013 | G358: 0.06835
A359: 364 DAYS TBILL RED 02-03-2023 | B359: IN002021Z509 | C359: SOVEREIGN | D359: 7000000 | E359: 6850.8 | F359: 0.0124 | G359: 0.065699
A360: 364 DAYS TBILL RED 17-08-2023 | B360: IN002022Z200 | C360: SOVEREIGN | D360: 5000000 | E360: 4741.88 | F360: 0.0086 | G360: 0.06875
A361: 364 DAYS TBILL RED 25-05-2023 | B361: IN002022Z085 | C361: SOVEREIGN | D361: 2500000 | E361: 2408.3 | F361: 0.0044 | G361: 0.0678
A362: 364 DAYS TBILL RED 05-01-2023 | B362: IN002021Z426 | C362: SOVEREIGN | D362: 500000 | E362: 494.41 | F362: 0.0009 | G362: 0.063501
A363: 364 DAYS TBILL RED 17-11-2022 | B363: IN002021Z343 | C363: SOVEREIGN | D363: 300000 | E363: 299.21 | F363: 0.0005 | G363: 0.060247
A364: 182 DAYS TBILL RED 22-12-2022 | B364: IN002022Y120 | C364: SOVEREIGN | D364: 200000 | E364: 198.28 | F364: 0.0004 | G364: 0.062003
A365: Sub Total | E365: 61301.27 | F365: 0.1108
A367: Commercial Paper
A368: ADITYA BIRLA FIN LTD CP RED 18-11-2022** | B368: INE860H14W43 | C368: ICRA A1+ | D368: 15000000 | E368: 14953.34 | F368: 0.027 | G368: 0.067003
A369: LARSEN & TOUBRO LTD CP 29-12-22** | B369: INE018A14IS2 | C369: CRISIL A1+ | D369: 10000000 | E369: 9894.81 | F369: 0.0179 | G369: 0.066901
A370: Sub Total | E370: 24848.15 | F370: 0.0449
A372: TOTAL | E372: 86149.42 | F372: 0.1557
A375: TREPS / Reverse Repo
A376: Clearing Corporation of India Ltd. | E376: 20705.54 | F376: 0.0374 | G376: 0.061074
A377: Sub Total | E377: 20705.54 | F377: 0.0374
A379: TOTAL | E379: 20705.54 | F379: 0.0374
A380: Accrued Interest | E380: 1877.147 | F380: 0.003391
A381: Net Receivables/(Payables) | E381: -5721.187 | F381: -0.010591 | G381: 0.061074
A382: GRAND TOTAL | E382: 553479.81 | F382: 1
A384: Net Receivables/(Payables) include Net Current Assets as well as the Mark to Market on derivative trades.
A385: **Non Traded Security
A387: Notes:
A388: 1. Security in default beyond its maturiy date | B388: NIL
A389: 2. NAV at the beginning of the period (Rs. per unit)
A390: Plan /option (Face Value 10) | B390: As on | C390: As on
B391: 44834 | C391: 44865
A392: Direct Plan Growth Option | B392: 16.8654 | C392: 16.9338
A393: Direct Plan IDCW Option | B393: 12.0567 | C393: 12.1056
A394: Direct Plan Monthly IDCW Option | B394: 13.8548 | C394: 13.9111
A395: Regular Plan Bonus Option | B395: 16.0221 | C395: 16.0775
A396: Regular Plan Growth Option | B396: 16.0184 | C396: 16.0738
A397: Regular Plan IDCW Option | B397: 11.7545 | C397: 11.7952
A398: Regular Plan Monthly IDCW Option | B398: 13.0867 | C398: 13.132
A400: 3. Total Dividend (Net) declared during the month | B400: NIL
A401: 4. Bonus was declared during the month | B401: NIL
A402: 5. Investment in Repo of Corporate Debt Securities during the month ended October 31, 2022 | B402: NIL
A403: 6. Investment in foreign securities/ADRs/GDRs at the end of the month | B403: NIL
A404: 7. Portfolio Turnover Ratio | B404: 14.826858
...

Sheet EEARFD
A1: PORTFOLIO STATEMENT OF EDELWEISS BALANCED ADVANTAGE FUND AS ON OCTOBER 31, 2022 | H1: =HYPERLINK("[EDEL_Portfolio Monthly Notes 31-Oct-2022.xlsx]Index!A1","Index") -> Index
A2: (An open ended dynamic asset allocation fund)
A4: Name of the Instrument | B4: ISIN | C4: Rating/Industry | D4: Quantity | E4: Market/Fair Value(Rs. In Lacs) | F4: % to Net Assets | G4: YIELD
A6: Equity & Equity related
A7: (a)Listed / Awaiting listing on Stock Exchanges
A8: ICICI Bank Ltd. | B8: INE090A01021 | C8: Banks | D8: 6038335 | E8: 54870.35 | F8: 0.0615
A9: Reliance Industries Ltd. | B9: INE002A01018 | C9: Petroleum Products | D9: 1967063 | E9: 50152.24 | F9: 0.0562
A10: HDFC Bank Ltd. | B10: INE040A01034 | C10: Banks | D10: 3152694 | E10: 47186.37 | F10: 0.0529
A11: Axis Bank Ltd. | B11: INE238A01034 | C11: Banks | D11: 3576609 | E11: 32404.08 | F11: 0.0363
A12: Infosys Ltd. | B12: INE009A01021 | C12: IT - Software | D12: 1812649 | E12: 27872.2 | F12: 0.0312
A13: ITC Ltd. | B13: INE154A01025 | C13: Diversified FMCG | D13: 6785246 | E13: 23660.15 | F13: 0.0265
A14: State Bank of India | B14: INE062A01020 | C14: Banks | D14: 3978748 | E14: 22830.06 | F14: 0.0256
A15: Mahindra & Mahindra Ltd. | B15: INE101A01026 | C15: Automobiles | D15: 1089569 | E15: 14693.93 | F15: 0.0165
A16: Housing Development Finance Corporation Ltd. | B16: INE001A01036 | C16: Finance | D16: 571598 | E16: 14117.33 | F16: 0.0158
A17: Larsen & Toubro Ltd. | B17: INE018A01030 | C17: Construction | D17: 686639 | E17: 13891.39 | F17: 0.0156
A18: Bajaj Finance Ltd. | B18: INE296A01024 | C18: Finance | D18: 181807 | E18: 12988.47 | F18: 0.0145
A19: Hindustan Unilever Ltd. | B19: INE030A01027 | C19: Diversified FMCG | D19: 477457 | E19: 12178.5 | F19: 0.0136
... A91: Coforge Ltd. | B91: INE591G01017 | C91: IT - Software | D91: 6 | E91: 0.23 | F91: 0
A92: Sub Total | E92: 644365.42 | F92: 0.7219
A94: (b) Unlisted
A95: NMDC Steel Ltd. | B95: INDUMMY27101 | C95: Metals & Minerals Trading | D95: 3488931 | E95: 922.82 | F95: 0.001
A96: Sub Total | E96: 922.82 | F96: 0.001
A97: TOTAL | E97: 644365.42 | F97: 0.7219
A99: Derivatives
A100: (a) Index/Stock Future
A101: Bharti Airtel Ltd.24/11/2022 | C101: Telecom - Services | D101: 1450650 | E101: 12027.34 | F101: 0.013472
A102: Eicher Motors Ltd.24/11/2022 | C102: Automobiles | D102: 143500 | E102: 5490.31 | F102: 0.00615
A103: United Breweries Ltd.24/11/2022 | C103: Beverages | D103: 179200 | E103: 2978.21 | F103: 0.003336
A104: Coforge Ltd.24/11/2022 | C104: IT - Software | D104: 67200 | E104: 2545.77 | F104: 0.002851
A105: L&T Technology Services Ltd.24/11/2022 | C105: IT - Services | D105: 62400 | E105: 2206.31 | F105: 0.002471
A106: JK Cement Ltd.24/11/2022 | C106: Cement & Cement Products | D106: 27250 | E106: 740.72 | F106: 0.000829
A107: HDFC Bank Ltd.24/11/2022 | C107: Banks | D107: -74800 | E107: -1124.43 | F107: -0.001259
A108: MindTree Ltd.24/11/2022 | C108: IT - Software | D108: -34800 | E108: -1190.6 | F108: -0.001333
A109: Ambuja Cements Ltd.24/11/2022 | C109: Cement & Cement Products | D109: -457200 | E109: -2450.36 | F109: -0.002744
A110: Hindustan Aeronautics Ltd.24/11/2022 | C110: Aerospace & Defense | D110: -97850 | E110: -2485.1 | F110: -0.002783
A111: Sun TV Network Ltd.24/11/2022 | C111: Entertainment | D111: -493500 | E111: -2585.69 | F111: -0.002896
A112: NIFTY 24/11/2022 | C112: INDEX FUTURES | D112: -300000 | E112: -54153.15 | F112: -0.06066
A113: Sub Total | E113: -38000.67 | F113: -0.042566
A116: (B)Index / Stock Option
A117: PUT NIFTY 24/11/2022 18500 | C117: INDEX OPTIONS | D117: 18950 | E117: 100.28 | F117: 0.0001
A118: CALL INDUSIND BANK LTD 24/11/2022 1250 | C118: SHARE OPTIONS | D118: -4500 | E118: -0.39 | F118: 0
A119: CALL HINDALCO IND LTD 24/11/2022 430 | C119: SHARE OPTIONS | D119: -8600 | E119: -0.57 | F119: 0
A120: CALL ITC LTD 24/11/2022 365 | C120: SHARE OPTIONS | D120: -25600 | E120: -0.59 | F120: 0
A121: CALL ONGC 24/11/2022 145 | C121: SHARE OPTIONS | D121: -204050 | E121: -2.14 | F121: 0
A122: CALL RELIANCE IND LTD 24/11/2022 2600 | C122: SHARE OPTIONS | D122: -11500 | E122: -4.43 | F122: 0
A123: CALL COAL INDIA LTD 24/11/2022 265 | C123: SHARE OPTIONS | D123: -483000 | E123: -9.9 | F123: 0
A124: CALL BAJAJ FINANCE LTD 24/11/2022 7600 | C124: SHARE OPTIONS | D124: -16625 | E124: -11.85 | F124: 0
A125: CALL MARUTI SUZUKI IND24/11/2022 10000 | C125: SHARE OPTIONS | D125: -12000 | E125: -12.09 | F125: 0
A126: CALL BAJAJ FINSERV LTD 24/11/2022 1800 | C126: SHARE OPTIONS | D126: -111000 | E126: -15.82 | F126: 0
A127: CALL ULTRATECH CEMENT 24/11/2022 6700 | C127: SHARE OPTIONS | D127: -8700 | E127: -17.06 | F127: 0
A128: CALL NTPC LTD 24/11/2022 180 | C128: SHARE OPTIONS | D128: -1767000 | E128: -27.39 | F128: 0
... A130: CALL MARUTI SUZUKI IND 24/11/2022 9500 | C130: SHARE OPTIONS | D130: -25500 | E130: -72.17 | F130: -0.0001
A131: Sub Total | E131: -106.71 | F131: 0
A133: TOTAL | E133: -106.71 | F133: 0
A134: Debt Instruments
A135: (a)Listed / Awaiting listing on stock Exchanges
A136: 7.20% EXIM NCD RED 05-06-2025** | B136: INE514E08FY8 | C136: CRISIL AAA | D136: 15000000 | E136: 14918.48 | F136: 0.0167 | G136: 0.0741
A137: 5.14% NABARD NCD RED 31-01-2024** | B137: INE261F08CK9 | C137: ICRA AAA | D137: 10000000 | E137: 9722.41 | F137: 0.0109 | G137: 0.0752
A138: 5.7% NABARD NCD RED SR 22D 31-07-2025** | B138: INE261F08DK7 | C138: CRISIL AAA | D138: 10000000 | E138: 9554.62 | F138: 0.0107 | G138: 0.0754
A139: 7.25% SIDBI NCD RED 31-07-2025** | B139: INE556F08KA6 | C139: ICRA AAA | D139: 7500000 | E139: 7442.98 | F139: 0.0083 | G139: 0.07545
A140: 6.72% NABARD NCD RED 14-04-2023** | B140: INE261F08BW6 | C140: ICRA AAA | D140: 5000000 | E140: 4981.73 | F140: 0.0056 | G140: 0.072901
A141: 5.32% NATIONAL HOUSING BANK RED 01-09-23** | B141: INE557F08FK3 | C141: CRISIL AAA | D141: 5000000 | E141: 4919.59 | F141: 0.0055 | G141: 0.07365
A142: 8.2% IND GR TRU SR V CAT III&IV 06-05-31** | B142: INE219X07264 | C142: CRISIL AAA | D142: 2500000 | E142: 2495.2 | F142: 0.0028 | G142: 0.082186
A143: 7.40% IND GR TRU SR K 26-12-25 C 270925** | B143: INE219X07132 | C143: FITCH AAA | D143: 2500000 | E143: 2463.86 | F143: 0.0028 | G143: 0.07923
A144: Sub Total | E144: 56498.87 | F144: 0.0633
A146: Government Securities
A147: 5.63% GOVT OF INDIA RED 12-04-2026 | B147: IN0020210012 | C147: SOVEREIGN | D147: 16000000 | E147: 15194.42 | F147: 0.017 | G147: 0.073071
A148: 5.22% GOVT OF INDIA RED 15-06-2025 | B148: IN0020200112 | C148: SOVEREIGN | D148: 15000000 | E148: 14304.93 | F148: 0.016 | G148: 0.071867
A149: 7.38% GOVT OF INDIA RED 20-06-2027 | B149: IN0020220037 | C149: SOVEREIGN | D149: 10000000 | E149: 9999.41 | F149: 0.0112 | G149: 0.073781
A150: 5.74% GOVT OF INDIA RED 15-11-2026 | B150: IN0020210186 | C150: SOVEREIGN | D150: 10000000 | E150: 9458.58 | F150: 0.0106 | G150: 0.073113
A151: 6.84% GOVT OF INDIA RED 19-12-2022 | B151: IN0020160050 | C151: SOVEREIGN | D151: 5000000 | E151: 5003.48 | F151: 0.0056 | G151: 0.062455
A152: 7.37% GOVT OF INDIA RED 16-04-2023 | B152: IN0020180025 | C152: SOVEREIGN | D152: 2500000 | E152: 2506.35 | F152: 0.0028 | G152: 0.06831
A153: Sub Total | E153: 56467.17 | F153: 0.0632
A155: (b)Privately Placed/Unlisted
A156: Sub Total | E156: NIL | F156: NIL
A158: (c)Securitised Debt Instruments
A159: Sub Total | E159: NIL | F159: NIL
A161: TOTAL | E161: 112966.04 | F161: 0.1265
A163: Money Market Instruments
A165: Treasury bills
A166: 182 DAYS TBILL RED 01-12-2022 | B166: IN002022Y096 | C166: SOVEREIGN | D166: 72500000 | E166: 72136.85 | F166: 0.0808 | G166: 0.06125
A167: 182 DAYS TBILL RED 08-12-2022 | B167: IN002022Y104 | C167: SOVEREIGN | D167: 5000000 | E167: 4969.07 | F167: 0.0056 | G167: 0.061404
A168: 364 DAYS TBILL RED 12-01-2023 | B168: IN002021Z434 | C168: SOVEREIGN | D168: 2500000 | E168: 2469.07 | F168: 0.0028 | G168: 0.0635
A169: 364 DAYS TBILL RED 05-01-2023 | B169: IN002021Z426 | C169: SOVEREIGN | D169: 500000 | E169: 494.41 | F169: 0.0006 | G169: 0.063501
A170: Sub Total | E170: 80069.4 | F170: 0.0898
A171: Certificate of Deposit
A172: AXIS BANK LTD CD RED 09-03-2023#** | B172: INE238A163Z9 | C172: CRISIL A1+ | D172: 7500000 | E172: 7318.67 | F172: 0.0082 | G172: 0.07065
A173: Sub Total | E173: 7318.67 | F173: 0.0082
A175: TOTAL | E175: 87388.07 | F175: 0.098
A177: TREPS / Reverse Repo
A178: Clearing Corporation of India Ltd. | E178: 49305.75 | F178: 0.0552 | G178: 0.061074
A179: Sub Total | E179: 49305.75 | F179: 0.0552
A181: TOTAL | E181: 49305.75 | F181: 0.0552
A182: Accrued Interest | E182: 2693.4041 | F182: 0.003017
A183: Net Receivables/(Payables) | E183: -3886.8441 | F183: -0.004617 | G183: 0.061074
A184: GRAND TOTAL | E184: 892725.13 | F184: 1
A186: Net Receivables/(Payables) include Net Current Assets as well as the Mark to Market on derivative trades.
A187: # Unlisted Security
A188: **Non Traded Security
A189: Notes:
...

Sheet EEDGEF
A1: PORTFOLIO STATEMENT OF EDELWEISS LARGE CAP FUND AS ON OCTOBER 31, 2022 | H1: =HYPERLINK("[EDEL_Portfolio Monthly Notes 31-Oct-2022.xlsx]Index!A1","Index") -> Index
A2: (An open ended equity scheme predominantly investing in large cap stocks)
A4: Name of the Instrument | B4: ISIN | C4: Rating/Industry | D4: Quantity | E4: Market/Fair Value(Rs. In Lacs) | F4: % to Net Assets | G4: YIELD
A6: Equity & Equity related
A7: (a)Listed / Awaiting listing on Stock Exchanges
A8: ICICI Bank Ltd. | B8: INE090A01021 | C8: Banks | D8: 344261 | E8: 3128.3 | F8: 0.0834
A9: HDFC Bank Ltd. | B9: INE040A01034 | C9: Banks | D9: 189310 | E9: 2833.4 | F9: 0.0755
A10: Reliance Industries Ltd. | B10: INE002A01018 | C10: Petroleum Products | D10: 106290 | E10: 2709.97 | F10: 0.0722
A11: Infosys Ltd. | B11: INE009A01021 | C11: IT - Software | D11: 139624 | E11: 2146.93 | F11: 0.0572
A12: Larsen & Toubro Ltd. | B12: INE018A01030 | C12: Construction | D12: 82855 | E12: 1676.24 | F12: 0.0447
A13: Axis Bank Ltd. | B13: INE238A01034 | C13: Banks | D13: 184518 | E13: 1671.73 | F13: 0.0446
A14: State Bank of India | B14: INE062A01020 | C14: Banks | D14: 278018 | E14: 1595.27 | F14: 0.0425
A15: ITC Ltd. | B15: INE154A01025 | C15: Diversified FMCG | D15: 434600 | E15: 1515.45 | F15: 0.0404
A16: Hindustan Unilever Ltd. | B16: INE030A01027 | C16: Diversified FMCG | D16: 35909 | E16: 915.93 | F16: 0.0244
A17: HCL Technologies Ltd. | B17: INE860A01027 | C17: IT - Software | D17: 87324 | E17: 909.17 | F17: 0.0242
A18: Bajaj Finance Ltd. | B18: INE296A01024 | C18: Finance | D18: 11775 | E18: 841.22 | F18: 0.0224
A19: Sun Pharmaceutical Industries Ltd. | B19: INE044A01036 | C19: Pharmaceuticals & Biotechnology | D19: 79000 | E19: 803.35 | F19: 0.0214
... A74: Crompton Greaves Cons Electrical Ltd. | B74: INE299U01018 | C74: Consumer Durables | D74: 780 | E74: 2.83 | F74: 0.0001
A75: Sub Total | E75: 35489.59 | F75: 0.9458
A76: (b) Unlisted
A77: Sub Total | E77: NIL | F77: NIL
A78: TOTAL | E78: 35489.59 | F78: 0.9458
A80: Derivatives
A81: (a) Index/Stock Future
A82: NIFTY 24/11/2022 | C82: INDEX FUTURES | D82: 3400 | E82: 613.74 | F82: 0.016356
A83: Nifty Bank 24/11/2022 | C83: INDEX FUTURES | D83: 875 | E83: 362.83 | F83: 0.009669
A84: Tata Motors Ltd.24/11/2022 | C84: Automobiles | D84: 58425 | E84: 242.32 | F84: 0.006457
A85: Crompton Greaves Cons Electrical Ltd.24/11/2022 | C85: Consumer Durables | D85: 52500 | E85: 190.81 | F85: 0.005085
A86: Sub Total | E86: 1409.7 | F86: 0.037567
A90: TOTAL | E90: 1409.7 | F90: 0.037567
A92: Money Market Instruments
A94: Treasury bills
A95: 182 DAYS TBILL RED 24-11-2022 | B95: IN002022Y088 | C95: SOVEREIGN | D95: 300000 | E95: 298.87 | F95: 0.008 | G95: 0.060247
A96: 364 DAYS TBILL RED 17-11-2022 | B96: IN002021Z343 | C96: SOVEREIGN | D96: 200000 | E96: 199.47 | F96: 0.0053 | G96: 0.060247
A97: Sub Total | E97: 498.34 | F97: 0.0133
A99: TOTAL | E99: 498.34 | F99: 0.0133
A102: TREPS / Reverse Repo
A103: Clearing Corporation of India Ltd. | E103: 1635.73 | F103: 0.0436 | G103: 0.061074
A104: Sub Total | E104: 1635.73 | F104: 0.0436
A106: TOTAL | E106: 1635.73 | F106: 0.0436
A107: Accrued Interest | E107: 0.2736996 | F107: 7e-06
A108: Net Receivables/(Payables) | E108: -100.8437 | F108: -0.002707 | G108: 0.061074
A109: GRAND TOTAL | E109: 37523.09 | F109: 1
A111: Net Receivables/(Payables) include Net Current Assets as well as the Mark to Market on derivative trades.
A114: Notes:
A115: 1. Security in default beyond its maturiy date | B115: NIL
A116: 2. NAV at the beginning of the period (Rs. per unit)
A117: Plan /option (Face Value 10) | B117: As on | C117: As on
B118: 44834 | C118: 44865
A119: Direct Plan Growth Option | B119: 58.89 | C119: 61.92
A120: Direct Plan IDCW Option | B120: 27.7 | C120: 29.13
A121: Plan B - Growth option | B121: 53.85 | C121: 56.56
A122: Plan B - IDCW option | B122: 54.49 | C122: 57.23
A123: Plan C - Growth option | B123: 53.15 | C123: 55.82
A124: Plan C - IDCW option | B124: 43.44 | C124: 45.63
A125: Regular Plan Growth Option | B125: 53.54 | C125: 56.23
A126: Regular Plan IDCW Option | B126: 21.45 | C126: 22.52
A128: 3. Total Dividend (Net) declared during the month | B128: NIL
A129: 4. Bonus was declared during the month | B129: NIL
A130: 5. Investment in Repo of Corporate Debt Securities during the month ended October 31, 2022 | B130: NIL
A131: 6. Investment in foreign securities/ADRs/GDRs at the end of the month | B131: NIL
A132: 7. Portfolio Turnover Ratio | B132: 2.09061
A133: 8. Total gross exposure to derivative instruments (excluding reversed positions) at the end of the month (Rs. in Lakhs) | B133: 1409.6991
A134: 9. Margin Deposits includes Margin money placed on derivatives other than margin money placed with bank | B134: NIL
A135: 10. Value of investment made by other schemes under same management (Rs. In Lakhs) | B135: NIL
A136: 11. Number of instance of deviation In valuation of securities | B136: NIL
A137: 12. Total value and percentage of illiquid equity shares / securities | B137: NIL
A139: Scheme Name | B139: Risk- O - Meter | C139: Benchmark of the Scheme | D139: Benchmark Risk-o-meter
A140: Edelweiss Large Cap Fund | C140: Nifty 100 TRI

Sheet EEECRF
A1: PORTFOLIO STATEMENT OF EDELWEISS FLEXI-CAP FUND AS ON OCTOBER 31, 2022 | H1: =HYPERLINK("[EDEL_Portfolio Monthly Notes 31-Oct-2022.xlsx]Index!A1","Index") -> Index
A2: (An open ended dynamic equity scheme investing across large cap, mid cap, small cap stocks)
A4: Name of the Instrument | B4: ISIN | C4: Rating/Industry | D4: Quantity | E4: Market/Fair Value(Rs. In Lacs) | F4: % to Net Assets | G4: YIELD
A6: Equity & Equity related
A7: (a)Listed / Awaiting listing on Stock Exchanges
A8: ICICI Bank Ltd. | B8: INE090A01021 | C8: Banks | D8: 1055860 | E8: 9594.6 | F8: 0.0893
A9: Infosys Ltd. | B9: INE009A01021 | C9: IT - Software | D9: 433863 | E9: 6671.29 | F9: 0.0621
A10: HDFC Bank Ltd. | B10: INE040A01034 | C10: Banks | D10: 396350 | E10: 5932.17 | F10: 0.0552
A11: State Bank of India | B11: INE062A01020 | C11: Banks | D11: 939916 | E11: 5393.24 | F11: 0.0502
A12: Reliance Industries Ltd. | B12: INE002A01018 | C12: Petroleum Products | D12: 209413 | E12: 5339.19 | F12: 0.0497
A13: Axis Bank Ltd. | B13: INE238A01034 | C13: Banks | D13: 549954 | E13: 4982.58 | F13: 0.0464
A14: Bajaj Finance Ltd. | B14: INE296A01024 | C14: Finance | D14: 48430 | E14: 3459.89 | F14: 0.0322
A15: Bharti Airtel Ltd. | B15: INE397D01024 | C15: Telecom - Services | D15: 370424 | E15: 3081.93 | F15: 0.0287
A16: ITC Ltd. | B16: INE154A01025 | C16: Diversified FMCG | D16: 869085 | E16: 3030.5 | F16: 0.0282
A17: Maruti Suzuki India Ltd. | B17: INE585B01010 | C17: Automobiles | D17: 31525 | E17: 3003.58 | F17: 0.0279
A18: Larsen & Toubro Ltd. | B18: INE018A01030 | C18: Construction | D18: 147912 | E18: 2992.41 | F18: 0.0278
A19: Cummins India Ltd. | B19: INE298A01020 | C19: Industrial Products | D19: 212634 | E19: 2866.09 | F19: 0.0267
... A62: Century Plyboards (India) Ltd. | B62: INE348B01021 | C62: Consumer Durables | D62: 33579 | E62: 200.84 | F62: 0.0019
A63: Sub Total | E63: 102929.43 | F63: 0.9578
A64: (b) Unlisted
A65: Sub Total | E65: NIL | F65: NIL
A66: TOTAL | E66: 102929.43 | F66: 0.9578
A69: TREPS / Reverse Repo
A70: Clearing Corporation of India Ltd. | E70: 4157.3 | F70: 0.0387 | G70: 0.061074
A71: Sub Total | E71: 4157.3 | F71: 0.0387
A73: TOTAL | E73: 4157.3 | F73: 0.0387
A74: Accrued Interest | E74: 0.6956252 | F74: 6e-06
A75: Net Receivables/(Payables) | E75: 404.28437 | F75: 0.003494 | G75: 0.061074
A76: GRAND TOTAL | E76: 107491.71 | F76: 1
A81: Notes:
A82: 1. Security in default beyond its maturiy date | B82: NIL
A83: 2. NAV at the beginning of the period (Rs. per unit)
A84: Plan /option (Face Value 10) | B84: As on | C84: As on
B85: 44834 | C85: 44865
A86: Direct Plan Growth Option | B86: 25.096 | C86: 26.282
A87: Direct Plan IDCW Option | B87: 20.604 | C87: 21.577
A88: Regular Plan Growth Option | B88: 22.676 | C88: 23.713
A89: Regular Plan IDCW Option | B89: 18.619 | C89: 19.47
A91: 3. Total Dividend (Net) declared during the month | B91: NIL
A92: 4. Bonus was declared during the month | B92: NIL
A93: 5. Investment in Repo of Corporate Debt Securities during the month ended October 31, 2022 | B93: NIL
A94: 6. Investment in foreign securities/ADRs/GDRs at the end of the month | B94: NIL
A95: 7. Portfolio Turnover Ratio | B95: 0.420828
A96: 8. Total gross exposure to derivative instruments (excluding reversed positions) at the end of the month (Rs. in Lakhs) | B96: NIL
A97: 9. Margin Deposits includes Margin money placed on derivatives other than margin money placed with bank | B97: NIL
A98: 10. Value of investment made by other schemes under same management (Rs. In Lakhs) | B98: NIL
A99: 11. Number of instance of deviation In valuation of securities | B99: NIL
A100: 12. Total value and percentage of illiquid equity shares / securities | B100: NIL
A102: Scheme Name | B102: Risk- O - Meter | C102: Benchmark of the Scheme | D102: Benchmark Risk-o-meter
A103: Edelweiss Flexi-Cap Fund | C103: Nifty 500 Total Return Index

Sheet EEELSS
A1: PORTFOLIO STATEMENT OF EDELWEISS LONG TERM EQUITY FUND AS ON OCTOBER 31, 2022 | H1: =HYPERLINK("[EDEL_Portfolio Monthly Notes 31-Oct-2022.xlsx]Index!A1","Index") -> Index
A2: (An open ended equity linked saving scheme with a statutory lock in of 3 years and tax benefit)
A4: Name of the Instrument | B4: ISIN | C4: Rating/Industry | D4: Quantity | E4: Market/Fair Value(Rs. In Lacs) | F4: % to Net Assets | G4: YIELD
A6: Equity & Equity related
A7: (a)Listed / Awaiting listing on Stock Exchanges
A8: ICICI Bank Ltd. | B8: INE090A01021 | C8: Banks | D8: 209639 | E8: 1904.99 | F8: 0.0905
A9: Infosys Ltd. | B9: INE009A01021 | C9: IT - Software | D9: 85382 | E9: 1312.88 | F9: 0.0624
A10: HDFC Bank Ltd. | B10: INE040A01034 | C10: Banks | D10: 75700 | E10: 1133 | F10: 0.0538
A11: Reliance Industries Ltd. | B11: INE002A01018 | C11: Petroleum Products | D11: 39755 | E11: 1013.59 | F11: 0.0481
A12: Axis Bank Ltd. | B12: INE238A01034 | C12: Banks | D12: 109142 | E12: 988.83 | F12: 0.047
A13: State Bank of India | B13: INE062A01020 | C13: Banks | D13: 172310 | E13: 988.71 | F13: 0.047
A14: Bajaj Finance Ltd. | B14: INE296A01024 | C14: Finance | D14: 9522 | E14: 680.26 | F14: 0.0323
A15: Maruti Suzuki India Ltd. | B15: INE585B01010 | C15: Automobiles | D15: 6506 | E15: 619.87 | F15: 0.0294
A16: Bharti Airtel Ltd. | B16: INE397D01024 | C16: Telecom - Services | D16: 73549 | E16: 611.93 | F16: 0.0291
A17: ITC Ltd. | B17: INE154A01025 | C17: Diversified FMCG | D17: 172557 | E17: 601.71 | F17: 0.0286
A18: Larsen & Toubro Ltd. | B18: INE018A01030 | C18: Construction | D18: 29367 | E18: 594.12 | F18: 0.0282
A19: Cummins India Ltd. | B19: INE298A01020 | C19: Industrial Products | D19: 42216 | E19: 569.03 | F19: 0.027
... A61: Honeywell Automation India Ltd. | B61: INE671A01010 | C61: Industrial Manufacturing | D61: 143 | E61: 56.25 | F61: 0.0027
A62: Sub Total | E62: 20118.86 | F62: 0.9556
A63: (b) Unlisted
A64: Sub Total | E64: NIL | F64: NIL
A65: TOTAL | E65: 20118.86 | F65: 0.9556
A68: TREPS / Reverse Repo
A69: Clearing Corporation of India Ltd. | E69: 716.88 | F69: 0.034 | G69: 0.061074
A70: Sub Total | E70: 716.88 | F70: 0.034
A72: TOTAL | E72: 716.88 | F72: 0.034
A73: Accrued Interest | E73: 0.1199527 | F73: 5e-06
A74: Net Receivables/(Payables) | E74: 218.18005 | F74: 0.010395 | G74: 0.061074
A75: GRAND TOTAL | E75: 21054.04 | F75: 1
A80: Notes:
A81: 1. Security in default beyond its maturiy date | B81: NIL
A82: 2. NAV at the beginning of the period (Rs. per unit)
A83: Plan /option (Face Value 10) | B83: As on | C83: As on
B84: 44834 | C84: 44865
A85: Direct Plan Growth Option | B85: 78.56 | C85: 82.22
A86: Direct Plan IDCW Option | B86: 27.55 | C86: 28.84
A87: Regular Plan Growth Option | B87: 69.57 | C87: 72.71
A88: Regular Plan IDCW Option | B88: 19.62 | C88: 20.51
A90: 3. Total Dividend (Net) declared during the month
A92: Plan/Option Name | C92: individual & HUF | D92: others
A93: Direct Plan Monthly IDCW | C93: 0.08 | D93: 0.08
A94: Regular Plan Monthly IDCW | C94: 0.08 | D94: 0.08
A96: 4. Bonus was declared during the month | B96: NIL
A97: 5. Investment in Repo of Corporate Debt Securities during the month ended October 31, 2022 | B97: NIL
A98: 6. Investment in foreign securities/ADRs/GDRs at the end of the month | B98: NIL
A99: 7. Portfolio Turnover Ratio | B99: 0.458046
A100: 8. Total gross exposure to derivative instruments (excluding reversed positions) at the end of the month (Rs. in Lakhs) | B100: NIL
A101: 9. Margin Deposits includes Margin money placed on derivatives other than margin money placed with bank | B101: NIL
A102: 10. Value of investment made by other schemes under same management (Rs. In Lakhs) | B102: NIL
A103: 11. Number of instance of deviation In valuation of securities | B103: NIL
A104: 12. Total value and percentage of illiquid equity shares / securities | B104: NIL
A106: Scheme Name | B106: Risk- O - Meter | C106: Benchmark of the Scheme | D106: Benchmark Risk-o-meter
A107: Edelweiss Long Term Equity Fund | C107: Nifty 500 Total Return Index

Sheet EEEQTF
A1: PORTFOLIO STATEMENT OF EDELWEISS LARGE & MID CAP FUND AS ON OCTOBER 31, 2022 | H1: =HYPERLINK("[EDEL_Portfolio Monthly Notes 31-Oct-2022.xlsx]Index!A1","Index") -> Index
A2: (An open ended equity scheme investing in both large cap and mid cap stocks)
A4: Name of the Instrument | B4: ISIN | C4: Rating/Industry | D4: Quantity | E4: Market/Fair Value(Rs. In Lacs) | F4: % to Net Assets | G4: YIELD
A6: Equity & Equity related
A7: (a)Listed / Awaiting listing on Stock Exchanges
A8: ICICI Bank Ltd. | B8: INE090A01021 | C8: Banks | D8: 1346848 | E8: 12238.81 | F8: 0.0748
A9: Reliance Industries Ltd. | B9: INE002A01018 | C9: Petroleum Products | D9: 239188 | E9: 6098.34 | F9: 0.0373
A10: Axis Bank Ltd. | B10: INE238A01034 | C10: Banks | D10: 666248 | E10: 6036.21 | F10: 0.0369
A11: State Bank of India | B11: INE062A01020 | C11: Banks | D11: 934051 | E11: 5359.58 | F11: 0.0328
A12: Infosys Ltd. | B12: INE009A01021 | C12: IT - Software | D12: 338738 | E12: 5208.6 | F12: 0.0318
A13: HDFC Bank Ltd. | B13: INE040A01034 | C13: Banks | D13: 344202 | E13: 5151.67 | F13: 0.0315
A14: Trent Ltd. | B14: INE849A01020 | C14: Retailing | D14: 282482 | E14: 4316.04 | F14: 0.0264
A15: ABB India Ltd. | B15: INE117A01022 | C15: Electrical Equipment | D15: 127371 | E15: 3884.5 | F15: 0.0237
A16: Bajaj Finance Ltd. | B16: INE296A01024 | C16: Finance | D16: 53188 | E16: 3799.8 | F16: 0.0232
A17: Navin Fluorine International Ltd. | B17: INE048G01026 | C17: Chemicals & Petrochemicals | D17: 80656 | E17: 3671.26 | F17: 0.0224
A18: Cummins India Ltd. | B18: INE298A01020 | C18: Industrial Products | D18: 252953 | E18: 3409.55 | F18: 0.0208
A19: Bharti Airtel Ltd. | B19: INE397D01024 | C19: Telecom - Services | D19: 402418 | E19: 3348.12 | F19: 0.0205
... A75: Tech Mahindra Ltd. | B75: INE669C01036 | C75: IT - Software | D75: 45939 | E75: 488.52 | F75: 0.003
A76: Sub Total | E76: 156883.89 | F76: 0.9589
A77: (b) Unlisted
A78: Sub Total | E78: NIL | F78: NIL
A79: TOTAL | E79: 156883.89 | F79: 0.9589
A82: TREPS / Reverse Repo
A83: Clearing Corporation of India Ltd. | E83: 7016.83 | F83: 0.0429 | G83: 0.061074
A84: Sub Total | E84: 7016.83 | F84: 0.0429
A86: TOTAL | E86: 7016.83 | F86: 0.0429
A87: Accrued Interest | E87: 1.1740976 | F87: 7e-06
A88: Net Receivables/(Payables) | E88: -319.8241 | F88: -0.001807 | G88: 0.061074
A89: GRAND TOTAL | E89: 163582.07 | F89: 1
A94: Notes:
A95: 1. Security in default beyond its maturiy date | B95: NIL
A96: 2. NAV at the beginning of the period (Rs. per unit)
A97: Plan /option (Face Value 10) | B97: As on | C97: As on
B98: 44834 | C98: 44865
A99: Direct Plan Growth Option | B99: 59.699 | C99: 61.854
A100: Direct Plan IDCW Option | B100: 23.156 | C100: 23.992
A101: Regular Plan Growth Option | B101: 52.899 | C101: 54.729
A102: Regular Plan IDCW Option | B102: 20.175 | C102: 20.873
A104: 3. Total Dividend (Net) declared during the month | B104: NIL
A105: 4. Bonus was declared during the month | B105: NIL
A106: 5. Investment in Repo of Corporate Debt Securities during the month ended October 31, 2022 | B106: NIL
A107: 6. Investment in foreign securities/ADRs/GDRs at the end of the month | B107: NIL
A108: 7. Portfolio Turnover Ratio | B108: 0.233953
A109: 8. Total gross exposure to derivative instruments (excluding reversed positions) at the end of the month (Rs. in Lakhs) | B109: NIL
A110: 9. Margin Deposits includes Margin money placed on derivatives other than margin money placed with bank | B110: NIL
A111: 10. Value of investment made by other schemes under same management (Rs. In Lakhs) | B111: NIL
A112: 11. Number of instance of deviation In valuation of securities | B112: NIL
A113: 12. Total value and percentage of illiquid equity shares / securities | B113: NIL
A116: Scheme Name | B116: Risk- O - Meter | C116: Benchmark of the Scheme | D116: Benchmark Risk-o-meter
A117: Edelweiss Large & Mid Cap Fund | C117: Nifty Large Midcap 250 Index - Total Return Index

Sheet EEESCF
A1: PORTFOLIO STATEMENT OF EDELWEISS SMALL CAP FUND AS ON OCTOBER 31, 2022 | H1: =HYPERLINK("[EDEL_Portfolio Monthly Notes 31-Oct-2022.xlsx]Index!A1","Index") -> Index
A2: (An open ended scheme predominantly investing in small cap stocks) | I2: INE572A01028
A4: Name of the Instrument | B4: ISIN | C4: Rating/Industry | D4: Quantity | E4: Market/Fair Value(Rs. In Lacs) | F4: % to Net Assets | G4: YIELD
A6: Equity & Equity related
A7: (a)Listed / Awaiting listing on Stock Exchanges
A8: JB Chemicals & Pharmaceuticals Ltd. | B8: INE572A01028 | C8: Pharmaceuticals & Biotechnology | D8: 238150 | E8: 4699.89 | F8: 0.034
A9: Westlife Development Ltd. | B9: INE274F01020 | C9: Leisure Services | D9: 592090 | E9: 4427.65 | F9: 0.032
A10: KEI Industries Ltd. | B10: INE878B01027 | C10: Industrial Products | D10: 253730 | E10: 4098.25 | F10: 0.0297
A11: City Union Bank Ltd. | B11: INE491A01021 | C11: Banks | D11: 1757648 | E11: 3269.23 | F11: 0.0237
A12: GMM Pfaudler Ltd. | B12: INE541A01023 | C12: Industrial Manufacturing | D12: 169350 | E12: 3125.44 | F12: 0.0226
A13: The Federal Bank Ltd. | B13: INE171A01029 | C13: Banks | D13: 2308084 | E13: 3035.13 | F13: 0.022
A14: Max Healthcare Institute Ltd. | B14: INE027H01010 | C14: Healthcare Services | D14: 661786 | E14: 3019.73 | F14: 0.0218
A15: Navin Fluorine International Ltd. | B15: INE048G01026 | C15: Chemicals & Petrochemicals | D15: 64575 | E15: 2939.29 | F15: 0.0213
A16: V-Mart Retail Ltd. | B16: INE665J01013 | C16: Retailing | D16: 96536 | E16: 2905.93 | F16: 0.021
A17: Can Fin Homes Ltd. | B17: INE477A01020 | C17: Finance | D17: 540945 | E17: 2836.45 | F17: 0.0205
A18: Brigade Enterprises Ltd. | B18: INE791I01019 | C18: Realty | D18: 563208 | E18: 2813.51 | F18: 0.0204
A19: Persistent Systems Ltd. | B19: INE262H01013 | C19: IT - Software | D19: 75232 | E19: 2778.36 | F19: 0.0201
... A82: Ashoka Buildcon Ltd. | B82: INE442H01029 | C82: Construction | D82: 258757 | E82: 191.48 | F82: 0.0014
A83: Sub Total | E83: 133324.29 | F83: 0.9647
A84: (b) Unlisted
A85: Sub Total | E85: NIL | F85: NIL
A86: TOTAL | E86: 133324.29 | F86: 0.9647
A89: TREPS / Reverse Repo
A90: Clearing Corporation of India Ltd. | E90: 5485.08 | F90: 0.0397 | G90: 0.061074
A91: Sub Total | E91: 5485.08 | F91: 0.0397
A93: TOTAL | E93: 5485.08 | F93: 0.0397
A94: Accrued Interest | E94: 0.917797 | F94: 6e-06
A95: Net Receivables/(Payables) | E95: -600.7178 | F95: -0.004406 | G95: 0.061074
A96: GRAND TOTAL | E96: 138209.57 | F96: 1
A101: Notes:
A102: 1. Security in default beyond its maturiy date | B102: NIL
A103: 2. NAV at the beginning of the period (Rs. per unit)
A104: Plan /option (Face Value 10) | B104: As on | C104: As on
B105: 44834 | C105: 44865
A106: Direct Plan Growth Option | B106: 26.655 | C106: 27.055
A107: Direct Plan IDCW Option | B107: 23.319 | C107: 23.669
A108: Regular Plan Growth Option | B108: 25.147 | C108: 25.489
A109: Regular Plan IDCW Option | B109: 21.852 | C109: 22.149
A111: 3. Total Dividend (Net) declared during the month | B111: NIL
A112: 4. Bonus was declared during the month | B112: NIL
A113: 5. Investment in Repo of Corporate Debt Securities during the month ended October 31, 2022 | B113: NIL
A114: 6. Investment in foreign securities/ADRs/GDRs at the end of the month | B114: NIL
A115: 7. Portfolio Turnover Ratio | B115: 0.159554
A116: 8. Total gross exposure to derivative instruments (excluding reversed positions) at the end of the month (Rs. in Lakhs) | B116: NIL
A117: 9. Margin Deposits includes Margin money placed on derivatives other than margin money placed with bank | B117: NIL
A118: 10. Value of investment made by other schemes under same management (Rs. In Lakhs) | B118: NIL
A119: 11. Number of instance of deviation In valuation of securities | B119: NIL
A120: 12. Total value and percentage of illiquid equity shares / securities | B120: NIL
A123: Scheme Name | B123: Risk- O - Meter | C123: Benchmark of the Scheme | D123: Benchmark Risk-o-meter
A124: Edelweiss Small Cap Fund | C124: Nifty Smallcap 250 TR Index

Sheet EEESSF
A1: PORTFOLIO STATEMENT OF EDELWEISS EQUITY SAVINGS FUND AS ON OCTOBER 31, 2022 | H1: =HYPERLINK("[EDEL_Portfolio Monthly Notes 31-Oct-2022.xlsx]Index!A1","Index") -> Index
A2: (An Open ended scheme investing in equity, arbitrage and debt)
A4: Name of the Instrument | B4: ISIN | C4: Rating/Industry | D4: Quantity | E4: Market/Fair Value(Rs. In Lacs) | F4: % to Net Assets | G4: YIELD
A6: Equity & Equity related
A7: (a)Listed / Awaiting listing on Stock Exchanges
A8: Reliance Industries Ltd. | B8: INE002A01018 | C8: Petroleum Products | D8: 83654 | E8: 2132.84 | F8: 0.0769
A9: Ambuja Cements Ltd. | B9: INE079A01024 | C9: Cement & Cement Products | D9: 307800 | E9: 1640.42 | F9: 0.0591
A10: Adani Ports & Special Economic Zone Ltd. | B10: INE742F01042 | C10: Transport Infrastructure | D10: 170000 | E10: 1400.04 | F10: 0.0505
A11: ICICI Bank Ltd. | B11: INE090A01021 | C11: Banks | D11: 124333 | E11: 1129.81 | F11: 0.0407
A12: ITC Ltd. | B12: INE154A01025 | C12: Diversified FMCG | D12: 250870 | E12: 874.78 | F12: 0.0315
A13: Axis Bank Ltd. | B13: INE238A01034 | C13: Banks | D13: 75383 | E13: 682.97 | F13: 0.0246
A14: State Bank of India | B14: INE062A01020 | C14: Banks | D14: 112430 | E14: 645.12 | F14: 0.0233
A15: HDFC Bank Ltd. | B15: INE040A01034 | C15: Banks | D15: 42000 | E15: 628.61 | F15: 0.0227
A16: Larsen & Toubro Ltd. | B16: INE018A01030 | C16: Construction | D16: 28948 | E16: 585.65 | F16: 0.0211
A17: Infosys Ltd. | B17: INE009A01021 | C17: IT - Software | D17: 34922 | E17: 536.98 | F17: 0.0194
A18: Adani Enterprises Ltd. | B18: INE423A01024 | C18: Metals & Minerals Trading | D18: 15500 | E18: 518.85 | F18: 0.0187
A19: Maruti Suzuki India Ltd. | B19: INE585B01010 | C19: Automobiles | D19: 4700 | E19: 447.8 | F19: 0.0161
... A79: JK Cement Ltd. | B79: INE823G01014 | C79: Cement & Cement Products | D79: 59 | E79: 1.6 | F79: 0.0001
A80: Sub Total | E80: 18214.6 | F80: 0.6567
A82: (b) Unlisted
A83: BEML LAND ASSETS LTD | B83: INE0N7W01012 | C83: Finance | D83: 4600 | E83: 13.88 | F83: 0.0005
A84: Sub Total | E84: 13.88 | F84: 0.0005
A85: TOTAL | E85: 18214.6 | F85: 0.6567
A87: Derivatives
A88: (a) Index/Stock Future
A89: Crompton Greaves Cons Electrical Ltd.24/11/2022 | C89: Consumer Durables | D89: 22500 | E89: 81.78 | F89: 0.002947
A90: JK Cement Ltd.24/11/2022 | C90: Cement & Cement Products | D90: 2500 | E90: 67.96 | F90: 0.002449
A91: Coforge Ltd.24/11/2022 | C91: IT - Software | D91: 1500 | E91: 56.83 | F91: 0.002048
A92: Kotak Mahindra Bank Ltd.24/11/2022 | C92: Banks | D92: -800 | E92: -15.26 | F92: -0.000549
A93: HCL Technologies Ltd.24/11/2022 | C93: IT - Software | D93: -16800 | E93: -175.5 | F93: -0.006326
A94: National Aluminium Company Ltd.24/11/2022 | C94: Non - Ferrous Metals | D94: -272000 | E94: -191.35 | F94: -0.006897
A95: Sun TV Network Ltd.24/11/2022 | C95: Entertainment | D95: -42000 | E95: -220.06 | F95: -0.007932
A96: Delta Corp Ltd.24/11/2022 | C96: Leisure Services | D96: -170200 | E96: -382.18 | F96: -0.013776
A97: Adani Enterprises Ltd.24/11/2022 | C97: Metals & Minerals Trading | D97: -15500 | E97: -521.54 | F97: -0.0188
A98: NIFTY 24/11/2022 | C98: INDEX FUTURES | D98: -3000 | E98: -541.53 | F98: -0.019521
A99: Reliance Industries Ltd.24/11/2022 | C99: Petroleum Products | D99: -43750 | E99: -1118.6 | F99: -0.040323
A100: Adani Ports & Special Economic Zone Ltd.24/11/2022 | C100: Transport Infrastructure | D100: -170000 | E100: -1406.58 | F100: -0.050704
A101: Ambuja Cements Ltd.24/11/2022 | C101: Cement & Cement Products | D101: -307800 | E101: -1649.65 | F101: -0.059466
A102: Sub Total | E102: -6015.68 | F102: -0.21685
A105: (B)Index / Stock Option
A106: PUT NIFTY 24/11/2022 18500 | C106: INDEX OPTIONS | D106: 10000 | E106: 52.92 | F106: 0.0019
A107: CALL BHARAT PETRO CORP 24/11/2022 325 | C107: SHARE OPTIONS | D107: -3600 | E107: -0.08 | F107: 0
A108: CALL NTPC LTD 24/11/2022 185 | C108: SHARE OPTIONS | D108: -17100 | E108: -0.14 | F108: 0
A109: CALL TATA STEEL LTD 24/11/2022 110 | C109: SHARE OPTIONS | D109: -12750 | E109: -0.16 | F109: 0
A110: CALL HDFC BANK LTD 24/11/2022 1540 | C110: SHARE OPTIONS | D110: -1100 | E110: -0.16 | F110: 0
A111: CALL DIVI'S LABORATORIES 24/11/2022 3800 | C111: SHARE OPTIONS | D111: -450 | E111: -0.16 | F111: 0
A112: CALL INDUSIND BANK LTD 24/11/2022 1230 | C112: SHARE OPTIONS | D112: -1800 | E112: -0.21 | F112: 0
A113: CALL TCS 24/11/2022 3320 | C113: SHARE OPTIONS | D113: -1200 | E113: -0.23 | F113: 0
A114: CALL INFOSYS LTD 24/11/2022 1600 | C114: SHARE OPTIONS | D114: -2400 | E114: -0.25 | F114: 0
A115: CALL DR. REDDY'S LAB 24/11/22 4750 | C115: SHARE OPTIONS | D115: -875 | E115: -0.25 | F115: 0
A116: CALL COAL INDIA LTD 24/11/2022 260 | C116: SHARE OPTIONS | D116: -8400 | E116: -0.26 | F116: 0
A117: CALL HINDUNILVR 24/11/2022 2660 | C117: SHARE OPTIONS | D117: -2400 | E117: -0.32 | F117: 0
... A129: CALL MARUTI SUZUKI IND 24/11/2022 9700 | C129: SHARE OPTIONS | D129: -900 | E129: -1.73 | F129: -0.0001
A130: Sub Total | E130: 40.42 | F130: 0.0017
A132: TOTAL | E132: 40.42 | F132: 0.0017
A133: Debt Instruments
A134: (a)Listed / Awaiting listing on stock Exchanges
A135: 7.34% NHB LTD NCD RED 07-08-2025** | B135: INE557F08FN7 | C135: CRISIL AAA | D135: 500000 | E135: 498.56 | F135: 0.018 | G135: 0.07445
A136: Sub Total | E136: 498.56 | F136: 0.018
A138: Government Securities
A139: 5.63% GOVT OF INDIA RED 12-04-2026 | B139: IN0020210012 | C139: SOVEREIGN | D139: 4900000 | E139: 4653.29 | F139: 0.1677 | G139: 0.073071
A140: Sub Total | E140: 4653.29 | F140: 0.1677
A142: (b)Privately Placed/Unlisted
A143: Sub Total | E143: NIL | F143: NIL
A145: (c)Securitised Debt Instruments
A146: Sub Total | E146: NIL | F146: NIL
A148: TOTAL | E148: 5151.85 | F148: 0.1857
A150: Money Market Instruments
A152: Treasury bills
A153: 364 DAYS TBILL RED 02-03-2023 | B153: IN002021Z509 | C153: SOVEREIGN | D153: 1000000 | E153: 978.69 | F153: 0.0353 | G153: 0.065699
A154: Sub Total | E154: 978.69 | F154: 0.0353
A156: TOTAL | E156: 978.69 | F156: 0.0353
A159: Investment in Mutual fund
A160: EDELWEISS LIQUID FUND - DIRECT PL -GR | B160: INF754K01GM4 | D160: 47098.75 | E160: 1330.7 | F160: 0.048
A162: TOTAL | E162: 1330.7 | F162: 0.048
A164: TREPS / Reverse Repo
A165: Clearing Corporation of India Ltd. | E165: 2278.62 | F165: 0.0821 | G165: 0.061074
A166: Sub Total | E166: 2278.62 | F166: 0.0821
A168: TOTAL | E168: 2278.62 | F168: 0.0821
A169: Accrued Interest | E169: 29.721626 | F169: 0.001071
A170: Net Receivables/(Payables) | E170: -283.81163 | F170: -0.010571 | G170: 0.061074
A171: GRAND TOTAL | E171: 27740.79 | F171: 1
A173: Net Receivables/(Payables) include Net Current Assets as well as the Mark to Market on derivative trades.
A174: **Non Traded Security
A176: Notes:
A177: 1. Security in default beyond its maturiy date | B177: NIL
A178: 2. NAV at the beginning of the period (Rs. per unit)
A179: Plan /option (Face Value 10) | B179: As on | C179: As on
B180: 44834 | C180: 44865
A181: Direct Plan Bonus Option | B181: 19.7934 | C181: 20.1654
A182: Direct Plan Growth Option | B182: 19.7855 | C182: 20.1571
A183: Direct Plan IDCW Option | B183: 14.3823 | C183: 14.6525
A184: Direct Plan Monthly IDCW Option | B184: 13.8725 | C184: 14.0529
A185: Regular Plan Bonus Option | B185: 18.4909 | C185: 18.816
A186: Regular Plan Growth Option | B186: 18.4786 | C186: 18.804
A187: Regular Plan IDCW Option | B187: 12.7711 | C187: 12.996
A188: Regular Plan Monthly IDCW Option | B188: 12.8649 | C188: 13.0112
A190: 3. Total Dividend (Net) declared during the month
A192: Plan/Option Name | C192: individual & HUF | D192: others
A193: Direct Plan Monthly IDCW | C193: 0.08 | D193: 0.08
...

Sheet EEFOCF
A1: PORTFOLIO STATEMENT OF EDELWEISS FOCUSED EQUITY FUND AS ON OCTOBER 31, 2022 | H1: =HYPERLINK("[EDEL_Portfolio Monthly Notes 31-Oct-2022.xlsx]Index!A1","Index") -> Index
A2: (An open-ended equity scheme investing in maximum 30 stocks across market capitalisation)
A4: Name of the Instrument | B4: ISIN | C4: Rating/Industry | D4: Quantity | E4: Market/Fair Value(Rs. In Lacs) | F4: % to Net Assets | G4: YIELD
A6: Equity & Equity related
A7: (a)Listed / Awaiting listing on Stock Exchanges
A8: ICICI Bank Ltd. | B8: INE090A01021 | C8: Banks | D8: 428543 | E8: 3894.17 | F8: 0.0845
A9: Infosys Ltd. | B9: INE009A01021 | C9: IT - Software | D9: 190801 | E9: 2933.85 | F9: 0.0636
A10: HDFC Bank Ltd. | B10: INE040A01034 | C10: Banks | D10: 174473 | E10: 2611.34 | F10: 0.0566
A11: Axis Bank Ltd. | B11: INE238A01034 | C11: Banks | D11: 267612 | E11: 2424.56 | F11: 0.0526
A12: State Bank of India | B12: INE062A01020 | C12: Banks | D12: 381963 | E12: 2191.7 | F12: 0.0475
A13: Reliance Industries Ltd. | B13: INE002A01018 | C13: Petroleum Products | D13: 82192 | E13: 2095.57 | F13: 0.0455
A14: Larsen & Toubro Ltd. | B14: INE018A01030 | C14: Construction | D14: 97256 | E14: 1967.59 | F14: 0.0427
A15: Bajaj Finance Ltd. | B15: INE296A01024 | C15: Finance | D15: 24769 | E15: 1769.52 | F15: 0.0384
A16: Sun Pharmaceutical Industries Ltd. | B16: INE044A01036 | C16: Pharmaceuticals & Biotechnology | D16: 150397 | E16: 1529.39 | F16: 0.0332
A17: Bharti Airtel Ltd. | B17: INE397D01024 | C17: Telecom - Services | D17: 179840 | E17: 1496.27 | F17: 0.0325
A18: Bharat Electronics Ltd. | B18: INE263A01024 | C18: Aerospace & Defense | D18: 1369933 | E18: 1463.77 | F18: 0.0317
A19: Cummins India Ltd. | B19: INE298A01020 | C19: Industrial Products | D19: 107077 | E19: 1443.29 | F19: 0.0313
... A37: Oberoi Realty Ltd. | B37: INE093I01010 | C37: Realty | D37: 56538 | E37: 522.78 | F37: 0.0113
A38: Sub Total | E38: 44190.18 | F38: 0.9586
A39: (b) Unlisted
A40: Sub Total | E40: NIL | F40: NIL
A41: TOTAL | E41: 44190.18 | F41: 0.9586
A44: TREPS / Reverse Repo
A45: Clearing Corporation of India Ltd. | E45: 2253.62 | F45: 0.0489 | G45: 0.061074
A46: Sub Total | E46: 2253.62 | F46: 0.0489
A48: TOTAL | E48: 2253.62 | F48: 0.0489
A49: Accrued Interest | E49: 0.3770898 | F49: 8e-06
A50: Net Receivables/(Payables) | E50: -340.59709 | F50: -0.007508 | G50: 0.061074
A51: GRAND TOTAL | E51: 46103.58 | F51: 1
A56: Notes:
A57: 1. Security in default beyond its maturiy date | B57: NIL
A58: 2. NAV at the beginning of the period (Rs. per unit)
A59: Plan /option (Face Value 10) | B59: As on | C59: As on
B60: 44834 | C60: 44865
A61: Direct Plan Growth Option | B61: 10.063 | C61: 10.548
A62: Direct Plan IDCW Option | B62: 10.063 | C62: 10.548
A63: Regular Plan Growth Option | B63: 10.035 | C63: 10.502
A64: Regular Plan IDCW Option | B64: 10.034 | C64: 10.502
A66: 3. Total Dividend (Net) declared during the month | B66: NIL
A67: 4. Bonus was declared during the month | B67: NIL
A68: 5. Investment in Repo of Corporate Debt Securities during the month ended October 31, 2022 | B68: NIL
A69: 6. Investment in foreign securities/ADRs/GDRs at the end of the month | B69: NIL
A70: 7. Portfolio Turnover Ratio | B70: 0.472307
A71: 8. Total gross exposure to derivative instruments (excluding reversed positions) at the end of the month (Rs. in Lakhs) | B71: NIL
A72: 9. Margin Deposits includes Margin money placed on derivatives other than margin money placed with bank | B72: NIL
A73: 10. Value of investment made by other schemes under same management (Rs. In Lakhs) | B73: NIL
A74: 11. Number of instance of deviation In valuation of securities | B74: NIL
A75: 12. Total value and percentage of illiquid equity shares / securities | B75: NIL
A77: Scheme Name | B77: Risk- O - Meter | C77: Benchmark of the Scheme | D77: Benchmark Risk-o-meter
A78: Edelweiss Focused Equity Fund | C78: NIFTY 500 Total Return Index

Sheet EEIF30
A1: PORTFOLIO STATEMENT OF EDELWEISS NIFTY 100 QUALITY 30 INDEX FND AS ON OCTOBER 31, 2022 | H1: =HYPERLINK("[EDEL_Portfolio Monthly Notes 31-Oct-2022.xlsx]Index!A1","Index") -> Index
A2: (An open ended scheme replicating Nifty 100 Quality 30 Index)
A4: Name of the Instrument | B4: ISIN | C4: Rating/Industry | D4: Quantity | E4: Market/Fair Value(Rs. In Lacs) | F4: % to Net Assets | G4: YIELD
A6: Equity & Equity related
A7: (a)Listed / Awaiting listing on Stock Exchanges
A8: Infosys Ltd. | B8: INE009A01021 | C8: IT - Software | D8: 4168 | E8: 64.09 | F8: 0.0535
A9: Nestle India Ltd. | B9: INE239A01016 | C9: Food Products | D9: 311 | E9: 63.33 | F9: 0.0528
A10: HDFC Bank Ltd. | B10: INE040A01034 | C10: Banks | D10: 4108 | E10: 61.48 | F10: 0.0513
A11: Tata Consultancy Services Ltd. | B11: INE467B01029 | C11: IT - Software | D11: 1925 | E11: 61.47 | F11: 0.0513
A12: ITC Ltd. | B12: INE154A01025 | C12: Diversified FMCG | D12: 17345 | E12: 60.48 | F12: 0.0505
A13: HCL Technologies Ltd. | B13: INE860A01027 | C13: IT - Software | D13: 5705 | E13: 59.4 | F13: 0.0496
A14: Hindustan Unilever Ltd. | B14: INE030A01027 | C14: Diversified FMCG | D14: 2168 | E14: 55.3 | F14: 0.0461
A15: Asian Paints Ltd. | B15: INE021A01026 | C15: Consumer Durables | D15: 1673 | E15: 51.99 | F15: 0.0434
A16: Maruti Suzuki India Ltd. | B16: INE585B01010 | C16: Automobiles | D16: 507 | E16: 48.3 | F16: 0.0403
A17: Coal India Ltd. | B17: INE522F01014 | C17: Consumable Fuels | D17: 18219 | E17: 44.81 | F17: 0.0374
A18: Bajaj Finance Ltd. | B18: INE296A01024 | C18: Finance | D18: 625 | E18: 44.65 | F18: 0.0372
A19: Britannia Industries Ltd. | B19: INE216A01030 | C19: Food Products | D19: 1074 | E19: 40.45 | F19: 0.0337
... A37: Bosch Ltd. | B37: INE323A01026 | C37: Auto Components | D37: 110 | E37: 18.14 | F37: 0.0151
A38: Sub Total | E38: 1192.02 | F38: 0.9943
A39: (b) Unlisted
A40: Sub Total | E40: NIL | F40: NIL
A41: TOTAL | E41: 1192.02 | F41: 0.9943
A44: TREPS / Reverse Repo
A45: Clearing Corporation of India Ltd. | E45: 8 | F45: 0.0067 | G45: 0.061074
A46: Sub Total | E46: 8 | F46: 0.0067
A48: TOTAL | E48: 8 | F48: 0.0067
A49: Accrued Interest | E49: 0.0013384 | F49: 1e-06
A50: Net Receivables/(Payables) | E50: -1.3213384 | F50: -0.001001 | G50: 0.061074
A51: GRAND TOTAL | E51: 1198.7 | F51: 1
A56: Notes:
A57: 1. Security in default beyond its maturiy date | B57: NIL
A58: 2. NAV at the beginning of the period (Rs. per unit)
A59: Plan /option (Face Value 10) | B59: As on | C59: As on
B60: 44834 | C60: 44865
A61: Direct Plan Growth Option | B61: 9.6704 | C61: 9.9107
A62: Direct Plan IDCW Option | B62: 9.5351 | C62: 9.772
A63: Regular Plan Growth Option | B63: 9.6123 | C63: 9.8461
A64: Regular Plan IDCW Option | B64: 9.6119 | C64: 9.8458
A66: 3. Total Dividend (Net) declared during the month | B66: NIL
A67: 4. Bonus was declared during the month | B67: NIL
A68: 5. Investment in Repo of Corporate Debt Securities during the month ended October 31, 2022 | B68: NIL
A69: 6. Investment in foreign securities/ADRs/GDRs at the end of the month | B69: NIL
A70: 7. Portfolio Turnover Ratio | B70: 0.826609
A71: 8. Total gross exposure to derivative instruments (excluding reversed positions) at the end of the month (Rs. in Lakhs) | B71: NIL
A72: 9. Margin Deposits includes Margin money placed on derivatives other than margin money placed with bank | B72: NIL
A73: 10. Value of investment made by other schemes under same management (Rs. In Lakhs) | B73: NIL
A74: 11. Number of instance of deviation In valuation of securities | B74: NIL
A75: 12. Total value and percentage of illiquid equity shares / securities | B75: NIL
A77: Scheme Name | B77: Risk- O - Meter | C77: Benchmark of the Scheme | D77: Benchmark Risk-o-meter
A78: Edelweiss Nifty 100 Quality 30 Index Fnd | C78: Nifty 100 Quality 30 TRI

Sheet EEIF50
A1: PORTFOLIO STATEMENT OF EDELWEISS NIFTY 50 INDEX FUND AS ON OCTOBER 31, 2022 | H1: =HYPERLINK("[EDEL_Portfolio Monthly Notes 31-Oct-2022.xlsx]Index!A1","Index") -> Index
A2: (An open ended scheme replicating Nifty 50 Index)
A4: Name of the Instrument | B4: ISIN | C4: Rating/Industry | D4: Quantity | E4: Market/Fair Value(Rs. In Lacs) | F4: % to Net Assets | G4: YIELD
A6: Equity & Equity related
A7: (a)Listed / Awaiting listing on Stock Exchanges
A8: Reliance Industries Ltd. | B8: INE002A01018 | C8: Petroleum Products | D8: 4001 | E8: 102.01 | F8: 0.11
A9: HDFC Bank Ltd. | B9: INE040A01034 | C9: Banks | D9: 5102 | E9: 76.36 | F9: 0.0823
A10: ICICI Bank Ltd. | B10: INE090A01021 | C10: Banks | D10: 8079 | E10: 73.41 | F10: 0.0792
A11: Infosys Ltd. | B11: INE009A01021 | C11: IT - Software | D11: 4245 | E11: 65.27 | F11: 0.0704
A12: Housing Development Finance Corporation Ltd. | B12: INE001A01036 | C12: Finance | D12: 2103 | E12: 51.94 | F12: 0.056
A13: Tata Consultancy Services Ltd. | B13: INE467B01029 | C13: IT - Software | D13: 1188 | E13: 37.93 | F13: 0.0409
A14: ITC Ltd. | B14: INE154A01025 | C14: Diversified FMCG | D14: 10208 | E14: 35.6 | F14: 0.0384
A15: Kotak Mahindra Bank Ltd. | B15: INE237A01028 | C15: Banks | D15: 1703 | E15: 32.39 | F15: 0.0349
A16: Larsen & Toubro Ltd. | B16: INE018A01030 | C16: Construction | D16: 1401 | E16: 28.34 | F16: 0.0306
A17: Axis Bank Ltd. | B17: INE238A01034 | C17: Banks | D17: 3063 | E17: 27.75 | F17: 0.0299
A18: Hindustan Unilever Ltd. | B18: INE030A01027 | C18: Diversified FMCG | D18: 1035 | E18: 26.4 | F18: 0.0285
A19: State Bank of India | B19: INE062A01020 | C19: Banks | D19: 4450 | E19: 25.53 | F19: 0.0275
... A58: Yes Bank Ltd.@ | B58: INE528G01035 | C58: Banks | D58: 643 | E58: 0 | F58: 0
A59: Sub Total | E59: 923.96 | F59: 0.9962
A60: (b) Unlisted
A61: Sub Total | E61: NIL | F61: NIL
A62: TOTAL | E62: 923.96 | F62: 0.9962
A65: TREPS / Reverse Repo
A66: Clearing Corporation of India Ltd. | E66: 6 | F66: 0.0065 | G66: 0.061074
A67: Sub Total | E67: 6 | F67: 0.0065
A69: TOTAL | E69: 6 | F69: 0.0065
A70: Accrued Interest | E70: 0.0010038 | F70: 1e-06
A71: Net Receivables/(Payables) | E71: -2.5710038 | F71: -0.002701 | G71: 0.061074
A72: GRAND TOTAL | E72: 927.39 | F72: 1
A74: @ These equity shares are under lock-in of three years till March 12, 2023 pursuant to the Gazette notification (Reference no: G.S.R.174(E)) issued by Ministry of Finance on March 13, 2020, for Yes Bank Limited Reconstruction Scheme, 2020. Further, in accordance with AMFI guidance, these equity shares are valued at ZERO with effect from March 16, 2020. For any realisation beyond the carrying value shall be distributed to the set of investors existing the unit holders’ register /BENPOS as on March 13, 2020.
A77: Notes:
A78: 1. Security in default beyond its maturiy date | B78: NIL
A79: 2. NAV at the beginning of the period (Rs. per unit)
A80: Plan /option (Face Value 10) | B80: As on | C80: As on
B81: 44834 | C81: 44865
A82: Direct Plan Growth Option | B82: 9.7968 | C82: 10.3293
A83: Direct Plan IDCW Option | B83: 9.6612 | C83: 10.1864
A84: Regular Plan Growth Option | B84: 9.6108 | C84: 10.1296
A85: Regular Plan IDCW Option | B85: 9.6107 | C85: 10.1295
A87: 3. Total Dividend (Net) declared during the month | B87: NIL
A88: 4. Bonus was declared during the month | B88: NIL
A89: 5. Investment in Repo of Corporate Debt Securities during the month ended October 31, 2022 | B89: NIL
A90: 6. Investment in foreign securities/ADRs/GDRs at the end of the month | B90: NIL
A91: 7. Portfolio Turnover Ratio | B91: 1.225924
A92: 8. Total gross exposure to derivative instruments (excluding reversed positions) at the end of the month (Rs. in Lakhs) | B92: NIL
A93: 9. Margin Deposits includes Margin money placed on derivatives other than margin money placed with bank | B93: NIL
A94: 10. Value of investment made by other schemes under same management (Rs. In Lakhs) | B94: 168.80959
A95: 11. Number of instance of deviation In valuation of securities | B95: NIL
A96: 12. Total value and percentage of illiquid equity shares / securities | B96: NIL
A98: Scheme Name | B98: Risk- O - Meter | C98: Benchmark of the Scheme | D98: Benchmark Risk-o-meter
A99: Edelweiss Nifty 50 Index Fund | C99: Nifty 50 TRI

Sheet EELMIF
A1: PORTFOLIO STATEMENT OF EDELWEISS NIFTY LARGE MID CAP 250 INDEX FUND AS ON OCTOBER 31, 2022 | H1: =HYPERLINK("[EDEL_Portfolio Monthly Notes 31-Oct-2022.xlsx]Index!A1","Index") -> Index
A2: (An Open-ended Equity Scheme replicating Nifty LargeMidcap 250 Index)
A4: Name of the Instrument | B4: ISIN | C4: Rating/Industry | D4: Quantity | E4: Market/Fair Value(Rs. In Lacs) | F4: % to Net Assets | G4: YIELD
A6: Equity & Equity related
A7: (a)Listed / Awaiting listing on Stock Exchanges
A8: Reliance Industries Ltd. | B8: INE002A01018 | C8: Petroleum Products | D8: 8495 | E8: 216.59 | F8: 0.0471
A9: HDFC Bank Ltd. | B9: INE040A01034 | C9: Banks | D9: 10833 | E9: 162.14 | F9: 0.0353
A10: ICICI Bank Ltd. | B10: INE090A01021 | C10: Banks | D10: 17154 | E10: 155.88 | F10: 0.0339
A11: Infosys Ltd. | B11: INE009A01021 | C11: IT - Software | D11: 9013 | E11: 138.59 | F11: 0.0302
A12: Housing Development Finance Corporation Ltd. | B12: INE001A01036 | C12: Finance | D12: 4465 | E12: 110.28 | F12: 0.024
A13: Tata Consultancy Services Ltd. | B13: INE467B01029 | C13: IT - Software | D13: 2522 | E13: 80.53 | F13: 0.0175
A14: ITC Ltd. | B14: INE154A01025 | C14: Diversified FMCG | D14: 21674 | E14: 75.58 | F14: 0.0164
A15: Kotak Mahindra Bank Ltd. | B15: INE237A01028 | C15: Banks | D15: 3618 | E15: 68.81 | F15: 0.015
A16: Larsen & Toubro Ltd. | B16: INE018A01030 | C16: Construction | D16: 2975 | E16: 60.19 | F16: 0.0131
A17: Axis Bank Ltd. | B17: INE238A01034 | C17: Banks | D17: 6504 | E17: 58.93 | F17: 0.0128
A18: Hindustan Unilever Ltd. | B18: INE030A01027 | C18: Diversified FMCG | D18: 2198 | E18: 56.06 | F18: 0.0122
A19: State Bank of India | B19: INE062A01020 | C19: Banks | D19: 9448 | E19: 54.21 | F19: 0.0118
... A257: One 97 Communications Ltd. | B257: INE982J01020 | C257: Financial Technology (Fintech) | D257: 224 | E257: 1.43 | F257: 0.0003
A258: Sub Total | E258: 4574.66 | F258: 0.9963
A259: (b) Unlisted
A260: Sub Total | E260: NIL | F260: NIL
A261: TOTAL | E261: 4574.66 | F261: 0.9963
A264: TREPS / Reverse Repo
A265: Clearing Corporation of India Ltd. | E265: 33.99 | F265: 0.0074 | G265: 0.061074
A266: Sub Total | E266: 33.99 | F266: 0.0074
A268: TOTAL | E268: 33.99 | F268: 0.0074
A269: Accrued Interest | E269: 0.0056881 | F269: 1e-06
A270: Net Receivables/(Payables) | E270: -14.225688 | F270: -0.003701 | G270: 0.061074
A271: GRAND TOTAL | E271: 4594.43 | F271: 1
A276: Notes:
A277: 1. Security in default beyond its maturiy date | B277: NIL
A278: 2. NAV at the beginning of the period (Rs. per unit)
A279: Plan /option (Face Value 10) | B279: As on | C279: As on
B280: 44834 | C280: 44865
A281: Direct Plan Growth Option | B281: 10.0744 | C281: 10.3971
A282: Direct Plan IDCW Option | B282: 10.0744 | C282: 10.3971
A283: Regular Plan Growth Option | B283: 10.0195 | C283: 10.3347
A284: Regular Plan IDCW Option | B284: 10.019 | C284: 10.3342
A286: 3. Total Dividend (Net) declared during the month | B286: NIL
A287: 4. Bonus was declared during the month | B287: NIL
A288: 5. Investment in Repo of Corporate Debt Securities during the month ended October 31, 2022 | B288: NIL
A289: 6. Investment in foreign securities/ADRs/GDRs at the end of the month | B289: NIL
A290: 7. Portfolio Turnover Ratio | B290: 0.592158
A291: 8. Total gross exposure to derivative instruments (excluding reversed positions) at the end of the month (Rs. in Lakhs) | B291: NIL
A292: 9. Margin Deposits includes Margin money placed on derivatives other than margin money placed with bank | B292: NIL
A293: 10. Value of investment made by other schemes under same management (Rs. In Lakhs) | B293: NIL
A294: 11. Number of instance of deviation In valuation of securities | B294: NIL
A295: 12. Total value and percentage of illiquid equity shares / securities | B295: NIL
A297: Scheme Name | B297: Risk- O - Meter | C297: Benchmark of the Scheme | D297: Benchmark Risk-o-meter
A298: Edelweiss NIFTY Large Mid Cap 250 Index Fund | C298: NIFTY LargeMidcap 250 Index Total Return Index

Sheet EEMOF1
A1: PORTFOLIO STATEMENT OF EDELWEISS RECENTLY LISTED IPO FUND AS ON OCTOBER 31, 2022 | H1: =HYPERLINK("[EDEL_Portfolio Monthly Notes 31-Oct-2022.xlsx]Index!A1","Index") -> Index
A2: (An open ended equity scheme following investment theme of investing in recently listed 100 companies or upcoming Initial Public Offer (IPOs).)
A4: Name of the Instrument | B4: ISIN | C4: Rating/Industry | D4: Quantity | E4: Market/Fair Value(Rs. In Lacs) | F4: % to Net Assets | G4: YIELD
A6: Equity & Equity related
A7: (a)Listed / Awaiting listing on Stock Exchanges
A8: Computer Age Management Services Ltd. | B8: INE596I01012 | C8: Capital Markets | D8: 207925 | E8: 5300.32 | F8: 0.0528
A9: SBI Cards & Payment Services Ltd. | B9: INE018E01016 | C9: Finance | D9: 567948 | E9: 4694.94 | F9: 0.0467
A10: Data Patterns (India) Ltd. | B10: INE0IX101010 | C10: Aerospace & Defense | D10: 320000 | E10: 4271.84 | F10: 0.0425
A11: Metro Brands Ltd. | B11: INE317I01021 | C11: Consumer Durables | D11: 492425 | E11: 4267.36 | F11: 0.0425
A12: Sona BLW Precision Forgings Ltd. | B12: INE073K01018 | C12: Auto Components | D12: 890000 | E12: 4142.06 | F12: 0.0412
A13: MTAR Technologies Ltd. | B13: INE864I01014 | C13: Aerospace & Defense | D13: 254000 | E13: 4076.19 | F13: 0.0406
A14: Go Fashion (India) Ltd. | B14: INE0BJS01011 | C14: Retailing | D14: 285000 | E14: 3988.29 | F14: 0.0397
A15: Vedant Fashions Ltd. | B15: INE825V01034 | C15: Retailing | D15: 270000 | E15: 3912.44 | F15: 0.0389
A16: Devyani International Ltd. | B16: INE872J01023 | C16: Leisure Services | D16: 1800000 | E16: 3483.9 | F16: 0.0347
A17: Tarsons Products Ltd. | B17: INE144Z01023 | C17: Healthcare Equipment & Supplies | D17: 422570 | E17: 3288.65 | F17: 0.0327
A18: C.E. Info Systems Ltd. | B18: INE0BV301023 | C18: IT - Software | D18: 250000 | E18: 3270.63 | F18: 0.0326
A19: Happiest Minds Technologies Ltd. | B19: INE419U01012 | C19: IT - Software | D19: 328000 | E19: 3182.75 | F19: 0.0317
... A51: Krsnaa Diagnostics Ltd. | B51: INE08LI01020 | C51: Healthcare Services | D51: 90000 | E51: 425.84 | F51: 0.0042
A52: Sub Total | E52: 94188.32 | F52: 0.9376
A53: (b) Unlisted
A54: Sub Total | E54: NIL | F54: NIL
A55: TOTAL | E55: 94188.32 | F55: 0.9376
A57: Derivatives
A58: (a) Index/Stock Future
A59: Polycab India Ltd.24/11/2022 | C59: Industrial Products | D59: 54900 | E59: 1526.82 | F59: 0.015199
A60: NIFTY 24/11/2022 | C60: INDEX FUTURES | D60: 7950 | E60: 1435.06 | F60: 0.014286
A61: Bandhan Bank Ltd.24/11/2022 | C61: Banks | D61: 198000 | E61: 475.1 | F61: 0.004729
A62: SBI Life Insurance Company Ltd.24/11/2022 | C62: Insurance | D62: 15750 | E62: 200.46 | F62: 0.001995
A63: SBI Cards & Payment Services Ltd.24/11/2022 | C63: Finance | D63: 4800 | E63: 39.86 | F63: 0.000396
A64: Sub Total | E64: 3677.3 | F64: 0.036605
A68: TOTAL | E68: 3677.3 | F68: 0.036605
A70: Money Market Instruments
A72: Treasury bills
A73: 182 DAYS TBILL RED 22-12-2022 | B73: IN002022Y120 | C73: SOVEREIGN | D73: 300000 | E73: 297.42 | F73: 0.003 | G73: 0.062003
A74: 182 DAYS TBILL RED 24-11-2022 | B74: IN002022Y088 | C74: SOVEREIGN | D74: 200000 | E74: 199.24 | F74: 0.002 | G74: 0.060247
A75: Sub Total | E75: 496.66 | F75: 0.005
A77: TOTAL | E77: 496.66 | F77: 0.005
A80: TREPS / Reverse Repo
A81: Clearing Corporation of India Ltd. | E81: 4191.3 | F81: 0.0417 | G81: 0.061074
A82: Sub Total | E82: 4191.3 | F82: 0.0417
A84: TOTAL | E84: 4191.3 | F84: 0.0417
A85: Accrued Interest | E85: 0.7013134 | F85: 6e-06
A86: Net Receivables/(Payables) | E86: 1573.8687 | F86: 0.015694 | G86: 0.061074
A87: GRAND TOTAL | E87: 100450.85 | F87: 1
A89: Net Receivables/(Payables) include Net Current Assets as well as the Mark to Market on derivative trades.
A92: Notes:
A93: 1. Security in default beyond its maturiy date | B93: NIL
A94: 2. NAV at the beginning of the period (Rs. per unit)
A95: Plan /option (Face Value 10) | B95: As on | C95: As on
B96: 44834 | C96: 44865
A97: Direct Plan Growth Option | B97: 18.5284 | C97: 18.1919
A98: Direct Plan IDCW Option | B98: 18.5283 | C98: 18.1919
A99: Regular Plan Growth Option | B99: 17.9476 | C99: 17.6017
A100: Regular Plan IDCW Option | B100: 17.9467 | C100: 17.6008
A102: 3. Total Dividend (Net) declared during the month | B102: NIL
A103: 4. Bonus was declared during the month | B103: NIL
A104: 5. Investment in Repo of Corporate Debt Securities during the month ended October 31, 2022 | B104: NIL
A105: 6. Investment in foreign securities/ADRs/GDRs at the end of the month | B105: NIL
A106: 7. Portfolio Turnover Ratio | B106: 1.487996
A107: 8. Total gross exposure to derivative instruments (excluding reversed positions) at the end of the month (Rs. in Lakhs) | B107: 3677.3007
A108: 9. Margin Deposits includes Margin money placed on derivatives other than margin money placed with bank | B108: NIL
A109: 10. Value of investment made by other schemes under same management (Rs. In Lakhs) | B109: NIL
A110: 11. Number of instance of deviation In valuation of securities | B110: NIL
A111: 12. Total value and percentage of illiquid equity shares / securities | B111: NIL
A114: Scheme Name | B114: Risk- O - Meter | C114: Benchmark of the Scheme | D114: Benchmark Risk-o-meter
A115: EDELWEISS RECENTLY LISTED IPO FUND | C115: India Recent 100 IPO Index TRI

Sheet EENFBA
A1: PORTFOLIO STATEMENT OF EDELWEISS ETF - NIFTY BANK AS ON OCTOBER 31, 2022 | H1: =HYPERLINK("[EDEL_Portfolio Monthly Notes 31-Oct-2022.xlsx]Index!A1","Index") -> Index
A2: (An open ended scheme tracking Nifty Bank Index)
A4: Name of the Instrument | B4: ISIN | C4: Rating/Industry | D4: Quantity | E4: Market/Fair Value(Rs. In Lacs) | F4: % to Net Assets | G4: YIELD
A6: Equity & Equity related
A7: (a)Listed / Awaiting listing on Stock Exchanges
A8: HDFC Bank Ltd. | B8: INE040A01034 | C8: Banks | D8: 2664 | E8: 39.87 | F8: 0.2549
A9: ICICI Bank Ltd. | B9: INE090A01021 | C9: Banks | D9: 4219 | E9: 38.34 | F9: 0.2451
A10: Axis Bank Ltd. | B10: INE238A01034 | C10: Banks | D10: 2171 | E10: 19.67 | F10: 0.1257
A11: State Bank of India | B11: INE062A01020 | C11: Banks | D11: 2984 | E11: 17.12 | F11: 0.1095
A12: Kotak Mahindra Bank Ltd. | B12: INE237A01028 | C12: Banks | D12: 890 | E12: 16.93 | F12: 0.1082
A13: IndusInd Bank Ltd. | B13: INE095A01012 | C13: Banks | D13: 759 | E13: 8.67 | F13: 0.0554
A14: AU Small Finance Bank Ltd. | B14: INE949L01017 | C14: Banks | D14: 550 | E14: 3.24 | F14: 0.0207
A15: Bank of Baroda | B15: INE028A01039 | C15: Banks | D15: 2169 | E15: 3.2 | F15: 0.0205
A16: The Federal Bank Ltd. | B16: INE171A01029 | C16: Banks | D16: 2335 | E16: 3.07 | F16: 0.0196
A17: Bandhan Bank Ltd. | B17: INE545U01014 | C17: Banks | D17: 882 | E17: 2.1 | F17: 0.0135
A18: IDFC First Bank Ltd. | B18: INE092T01019 | C18: Banks | D18: 3623 | E18: 2.03 | F18: 0.013
A19: Punjab National Bank | B19: INE160A01022 | C19: Banks | D19: 3463 | E19: 1.48 | F19: 0.0094
A20: Yes Bank Ltd.@ | B20: INE528G01035 | C20: Banks | D20: 1752 | E20: 0 | F20: 0
A21: Sub Total | E21: 155.72 | F21: 0.9955
A22: (b) Unlisted
A23: Sub Total | E23: NIL | F23: NIL
A24: TOTAL | E24: 155.72 | F24: 0.9955
A27: TREPS / Reverse Repo
A28: Clearing Corporation of India Ltd. | E28: 1 | F28: 0.0064 | G28: 0.061074
A29: Sub Total | E29: 1 | F29: 0.0064
A31: TOTAL | E31: 1 | F31: 0.0064
A32: Accrued Interest | E32: 0.0001673 | F32: 1e-06
A33: Net Receivables/(Payables) | E33: -0.2901673 | F33: -0.001901 | G33: 0.061074
A34: GRAND TOTAL | E34: 156.43 | F34: 1
A36: @ These equity shares are under lock-in of three years till March 12, 2023 pursuant to the Gazette notification (Reference no: G.S.R.174(E)) issued by Ministry of Finance on March 13, 2020, for Yes Bank Limited Reconstruction Scheme, 2020. Further, in accordance with AMFI guidance, these equity shares are valued at ZERO with effect from March 16, 2020. For any realisation beyond the carrying value shall be distributed to the set of investors existing the unit holders’ register /BENPOS as on March 13, 2020.
A39: Notes:
A40: 1. Security in default beyond its maturiy date | B40: NIL
A41: 2. NAV at the beginning of the period (Rs. per unit)
A42: Plan /option (Face Value 10) | B42: As on | C42: As on
B43: 44834 | C43: 44865
A44: Growth Option | B44: 3941.6429 | C44: 4212.9931
A46: 3. Total Dividend (Net) declared during the month | B46: NIL
A47: 4. Bonus was declared during the month | B47: NIL
A48: 5. Investment in Repo of Corporate Debt Securities during the month ended October 31, 2022 | B48: NIL
A49: 6. Investment in foreign securities/ADRs/GDRs at the end of the month | B49: NIL
A50: 8. Total gross exposure to derivative instruments (excluding reversed positions) at the end of the month (Rs. in Lakhs) | B50: NIL
A51: 9. Margin Deposits includes Margin money placed on derivatives other than margin money placed with bank | B51: NIL
A52: 10. Value of investment made by other schemes under same management (Rs. In Lakhs) | B52: NIL
A53: 11. Number of instance of deviation In valuation of securities | B53: NIL
A54: 12. Total value and percentage of illiquid equity shares / securities | B54: NIL
A56: Scheme Name | B56: Risk- O - Meter | C56: Benchmark of the Scheme | D56: Benchmark Risk-o-meter
A57: Edelweiss ETF - Nifty Bank | C57: Nifty Bank TRI

Sheet EEPRUA
A1: PORTFOLIO STATEMENT OF EDELWEISS AGGRESSIVE HYBRID FUND AS ON OCTOBER 31, 2022 | H1: =HYPERLINK("[EDEL_Portfolio Monthly Notes 31-Oct-2022.xlsx]Index!A1","Index") -> Index
A2: (An open ended hybrid scheme investing predominantly in equity and equity related instruments)
A4: Name of the Instrument | B4: ISIN | C4: Rating/Industry | D4: Quantity | E4: Market/Fair Value(Rs. In Lacs) | F4: % to Net Assets | G4: YIELD
A6: Equity & Equity related
A7: (a)Listed / Awaiting listing on Stock Exchanges
A8: ICICI Bank Ltd. | B8: INE090A01021 | C8: Banks | D8: 242863 | E8: 2206.9 | F8: 0.0577
A9: HDFC Bank Ltd. | B9: INE040A01034 | C9: Banks | D9: 103727 | E9: 1552.48 | F9: 0.0406
A10: Reliance Industries Ltd. | B10: INE002A01018 | C10: Petroleum Products | D10: 59013 | E10: 1504.6 | F10: 0.0394
A11: Infosys Ltd. | B11: INE009A01021 | C11: IT - Software | D11: 84990 | E11: 1306.85 | F11: 0.0342
A12: State Bank of India | B12: INE062A01020 | C12: Banks | D12: 199274 | E12: 1143.43 | F12: 0.0299
A13: ITC Ltd. | B13: INE154A01025 | C13: Diversified FMCG | D13: 310000 | E13: 1080.97 | F13: 0.0283
A14: Larsen & Toubro Ltd. | B14: INE018A01030 | C14: Construction | D14: 44000 | E14: 890.16 | F14: 0.0233
A15: Sun Pharmaceutical Industries Ltd. | B15: INE044A01036 | C15: Pharmaceuticals & Biotechnology | D15: 77000 | E15: 783.01 | F15: 0.0205
A16: Axis Bank Ltd. | B16: INE238A01034 | C16: Banks | D16: 84877 | E16: 768.99 | F16: 0.0201
A17: Hindustan Unilever Ltd. | B17: INE030A01027 | C17: Diversified FMCG | D17: 26950 | E17: 687.41 | F17: 0.018
A18: NTPC Ltd. | B18: INE733E01010 | C18: Power | D18: 347732 | E18: 601.92 | F18: 0.0157
A19: HCL Technologies Ltd. | B19: INE860A01027 | C19: IT - Software | D19: 52000 | E19: 541.4 | F19: 0.0142
... A75: Coforge Ltd. | B75: INE591G01017 | C75: IT - Software | D75: 143 | E75: 5.45 | F75: 0.0001
A76: Sub Total | E76: 25453.85 | F76: 0.666
A77: (b) Unlisted
A78: Sub Total | E78: NIL | F78: NIL
A79: TOTAL | E79: 25453.85 | F79: 0.666
A81: Derivatives
A82: (a) Index/Stock Future
A83: NIFTY 24/11/2022 | C83: INDEX FUTURES | D83: 11400 | E83: 2057.82 | F83: 0.053828
A84: Nifty Bank 24/11/2022 | C84: INDEX FUTURES | D84: 800 | E84: 331.73 | F84: 0.008677
A85: Bharti Airtel Ltd.24/11/2022 | C85: Telecom - Services | D85: 28500 | E85: 236.29 | F85: 0.006181
A86: Coforge Ltd.24/11/2022 | C86: IT - Software | D86: 4650 | E86: 176.16 | F86: 0.004607
A87: Polycab India Ltd.24/11/2022 | C87: Industrial Products | D87: 6000 | E87: 166.87 | F87: 0.004364
A88: Mahindra & Mahindra Financial Services Ltd24/11/2022 | C88: Finance | D88: 80000 | E88: 160.52 | F88: 0.004198
A89: Sub Total | E89: 3129.39 | F89: 0.081855
A93: TOTAL | E93: 3129.39 | F93: 0.081855
A95: Debt Instruments
A96: (a)Listed / Awaiting listing on stock Exchanges
A97: 7.34% NHB LTD NCD RED 07-08-2025** | B97: INE557F08FN7 | C97: CRISIL AAA | D97: 2000000 | E97: 1994.25 | F97: 0.0522 | G97: 0.07445
A98: Sub Total | E98: 1994.25 | F98: 0.0522
A100: Government Securities
A101: 5.63% GOVT OF INDIA RED 12-04-2026 | B101: IN0020210012 | C101: SOVEREIGN | D101: 1600000 | E101: 1519.44 | F101: 0.0397 | G101: 0.073071
A102: 7.38% GOVT OF INDIA RED 20-06-2027 | B102: IN0020220037 | C102: SOVEREIGN | D102: 1500000 | E102: 1499.91 | F102: 0.0392 | G102: 0.073781
A103: 7.10% GOVT OF INDIA RED 18-04-2029 | B103: IN0020220011 | C103: SOVEREIGN | D103: 1000000 | E103: 983.36 | F103: 0.0257 | G103: 0.07428
A104: Sub Total | E104: 4002.71 | F104: 0.1046
A106: (b)Privately Placed/Unlisted
A107: Sub Total | E107: NIL | F107: NIL
A109: (c)Securitised Debt Instruments
A110: Sub Total | E110: NIL | F110: NIL
A112: TOTAL | E112: 5996.96 | F112: 0.1568
A115: Investment in Mutual fund
A116: EDELWEISS LIQUID FUND - DIRECT PL -GR | B116: INF754K01GM4 | D116: 13802.076 | E116: 389.95 | F116: 0.0102
A117: EDELWEISS-NIFTY 50-INDEX FUND | B117: INF754K01NB3 | D117: 1634279.1 | E117: 168.81 | F117: 0.0044
A119: TOTAL | E119: 558.76 | F119: 0.0146
A121: TREPS / Reverse Repo
A122: Clearing Corporation of India Ltd. | E122: 6327.94 | F122: 0.1655 | G122: 0.061074
A123: Sub Total | E123: 6327.94 | F123: 0.1655
A125: TOTAL | E125: 6327.94 | F125: 0.1655
A126: Accrued Interest | E126: 107.78163 | F126: 0.002819
A127: Net Receivables/(Payables) | E127: -216.38163 | F127: -0.005719 | G127: 0.061074
A128: GRAND TOTAL | E128: 38228.91 | F128: 1
A130: Net Receivables/(Payables) include Net Current Assets as well as the Mark to Market on derivative trades.
A131: **Non Traded Security
A133: Notes:
A134: 1. Security in default beyond its maturiy date | B134: NIL
A135: 2. NAV at the beginning of the period (Rs. per unit)
A136: Plan /option (Face Value 10) | B136: As on | C136: As on
B137: 44834 | C137: 44865
A138: Direct Plan Growth Option | B138: 42.83 | C138: 44.54
A139: Direct Plan IDCW Option | B139: 24.19 | C139: 25.01
A140: Plan B - Growth option | B140: 38.53 | C140: 40.02
A141: Plan B - IDCW option | B141: 39.28 | C141: 40.79
A142: Regular Plan Growth Option | B142: 39.02 | C142: 40.51
A143: Regular Plan IDCW Option | B143: 21.41 | C143: 22.08
A145: 3. Total Dividend (Net) declared during the month
A147: Plan/Option Name | C147: individual & HUF | D147: others
A148: Direct Plan IDCW | C148: 0.15 | D148: 0.15
A149: Regular Plan IDCW | C149: 0.15 | D149: 0.15
A151: 4. Bonus was declared during the month | B151: NIL
A152: 5. Investment in Repo of Corporate Debt Securities during the month ended October 31, 2022 | B152: NIL
A153: 6. Investment in foreign securities/ADRs/GDRs at the end of the month | B153: NIL
A154: 7. Portfolio Turnover Ratio | B154: 1.851982
A155: 8. Total gross exposure to derivative instruments (excluding reversed positions) at the end of the month (Rs. in Lakhs) | B155: 3129.3919
A156: 9. Margin Deposits includes Margin money placed on derivatives other than margin money placed with bank | B156: NIL
A157: 10. Value of investment made by other schemes under same management (Rs. In Lakhs) | B157: NIL
A158: 11. Number of instance of deviation In valuation of securities | B158: NIL
A159: 12. Total value and percentage of illiquid equity shares / securities | B159: NIL
A161: Scheme Name | B161: Risk- O - Meter | C161: Benchmark of the Scheme | D161: Benchmark Risk-o-meter
A162: Edelweiss Aggressive Hybrid Fund | C162: CRISIL Hybrid 35+65 - Aggressive Index

Sheet EESMCF
A1: PORTFOLIO STATEMENT OF EDELWEISS MID CAP FUND AS ON OCTOBER 31, 2022 | H1: =HYPERLINK("[EDEL_Portfolio Monthly Notes 31-Oct-2022.xlsx]Index!A1","Index") -> Index
A2: (An open ended equity scheme predominantly investing in mid cap stocks)
A4: Name of the Instrument | B4: ISIN | C4: Rating/Industry | D4: Quantity | E4: Market/Fair Value(Rs. In Lacs) | F4: % to Net Assets | G4: YIELD
A6: Equity & Equity related
A7: (a)Listed / Awaiting listing on Stock Exchanges
A8: Cummins India Ltd. | B8: INE298A01020 | C8: Industrial Products | D8: 754305 | E8: 10167.28 | F8: 0.0424
A9: ABB India Ltd. | B9: INE117A01022 | C9: Electrical Equipment | D9: 325034 | E9: 9912.72 | F9: 0.0414
A10: The Federal Bank Ltd. | B10: INE171A01029 | C10: Banks | D10: 7536052 | E10: 9909.91 | F10: 0.0413
A11: City Union Bank Ltd. | B11: INE491A01021 | C11: Banks | D11: 4784424 | E11: 8899.03 | F11: 0.0371
A12: Trent Ltd. | B12: INE849A01020 | C12: Retailing | D12: 579149 | E12: 8848.82 | F12: 0.0369
A13: Navin Fluorine International Ltd. | B13: INE048G01026 | C13: Chemicals & Petrochemicals | D13: 175381 | E13: 7982.9 | F13: 0.0333
A14: Cholamandalam Investment & Finance Company Ltd. | B14: INE121A01024 | C14: Finance | D14: 1112125 | E14: 7888.86 | F14: 0.0329
A15: Indian Bank | B15: INE562A01011 | C15: Banks | D15: 3079607 | E15: 7819.12 | F15: 0.0326
A16: Max Healthcare Institute Ltd. | B16: INE027H01010 | C16: Healthcare Services | D16: 1408142 | E16: 6425.35 | F16: 0.0268
A17: Crompton Greaves Cons Electrical Ltd. | B17: INE299U01018 | C17: Consumer Durables | D17: 1688009 | E17: 6115.66 | F17: 0.0255
A18: P I INDUSTRIES LIMITED | B18: INE603J01030 | C18: Fertilizers & Agrochemicals | D18: 188241 | E18: 6102.68 | F18: 0.0255
A19: Ashok Leyland Ltd. | B19: INE208A01029 | C19: Agricultural, Commercial & Construction Vehicles | D19: 3790577 | E19: 5810.95 | F19: 0.0242
... A68: Vinati Organics Ltd. | B68: INE410B01037 | C68: Chemicals & Petrochemicals | D68: 6000 | E68: 114.44 | F68: 0.0005
A69: Sub Total | E69: 228530.62 | F69: 0.9536
A70: (b) Unlisted
A71: Sub Total | E71: NIL | F71: NIL
A72: TOTAL | E72: 228530.62 | F72: 0.9536
A75: TREPS / Reverse Repo
A76: Clearing Corporation of India Ltd. | E76: 11070.15 | F76: 0.0462 | G76: 0.061074
A77: Sub Total | E77: 11070.15 | F77: 0.0462
A79: TOTAL | E79: 11070.15 | F79: 0.0462
A80: Accrued Interest | E80: 1.8523238 | F80: 7e-06
A81: Net Receivables/(Payables) | E81: 56.927676 | F81: 0.000193 | G81: 0.061074
A82: GRAND TOTAL | E82: 239659.55 | F82: 1
A87: Notes:
A88: 1. Security in default beyond its maturiy date | B88: NIL
A89: 2. NAV at the beginning of the period (Rs. per unit)
A90: Plan /option (Face Value 10) | B90: As on | C90: As on
B91: 44834 | C91: 44865
A92: Direct Plan Growth Option | B92: 58.707 | C92: 60.146
A93: Direct Plan IDCW Option | B93: 42.807 | C93: 43.856
A94: Regular Plan Growth Option | B94: 52.306 | C94: 53.515
A95: Regular Plan IDCW Option | B95: 30.156 | C95: 30.854
A97: 3. Total Dividend (Net) declared during the month | B97: NIL
A98: 4. Bonus was declared during the month | B98: NIL
A99: 5. Investment in Repo of Corporate Debt Securities during the month ended October 31, 2022 | B99: NIL
A100: 6. Investment in foreign securities/ADRs/GDRs at the end of the month | B100: NIL
A101: 7. Portfolio Turnover Ratio | B101: 0.386552
A102: 8. Total gross exposure to derivative instruments (excluding reversed positions) at the end of the month (Rs. in Lakhs) | B102: NIL
A103: 9. Margin Deposits includes Margin money placed on derivatives other than margin money placed with bank | B103: NIL
A104: 10. Value of investment made by other schemes under same management (Rs. In Lakhs) | B104: NIL
A105: 11. Number of instance of deviation In valuation of securities | B105: NIL
A106: 12. Total value and percentage of illiquid equity shares / securities | B106: NIL
A108: Scheme Name | B108: Risk- O - Meter | C108: Benchmark of the Scheme | D108: Benchmark Risk-o-meter
A109: Edelweiss Mid Cap Fund | C109: Nifty Midcap 150 Total Return Index

Sheet EGSFOF
A1: PORTFOLIO STATEMENT OF EDELWEISS GOLD AND SILVER ETF FOF AS ON OCTOBER 31, 2022 | H1: =HYPERLINK("[EDEL_Portfolio Monthly Notes 31-Oct-2022.xlsx]Index!A1","Index") -> Index
A2: (An open-ended fund of funds scheme investing in units of Gold ETF and Silver ETF)
A4: Name of the Instrument | B4: ISIN | C4: Rating/Industry | D4: Quantity | E4: Market/Fair Value(Rs. In Lacs) | F4: % to Net Assets | G4: YIELD
A7: Equity & Equity related | E7: NIL | F7: NIL
A10: Investment in Mutual fund
A11: ADITYA BIRLA SUNLIFE SILVER ETF | B11: INF209KB19F6 | D11: 2145410 | E11: 1264.5 | F11: 0.4992
A12: ICICI PRUDENTIAL GOLD ETF | B12: INF109KC1NT3 | D12: 2828299 | E12: 1257.46 | F12: 0.4964
A13: Sub Total | E13: 2521.96 | F13: 0.9956
A15: TOTAL | E15: 2521.96 | F15: 0.9956
A17: TREPS / Reverse Repo
A18: Clearing Corporation of India Ltd. | E18: 20 | F18: 0.0079 | G18: 0.061074
A19: Sub Total | E19: 20 | F19: 0.0079
A21: TOTAL | E21: 20 | F21: 0.0079
A22: Accrued Interest | E22: 0.003346 | F22: 1e-06
A23: Net Receivables/(Payables) | E23: -8.843346 | F23: -0.003501 | G23: 0.061074
A24: GRAND TOTAL | E24: 2533.12 | F24: 1
A29: Notes:
A30: 1. Security in default beyond its maturiy date | B30: NIL
A31: 2. NAV at the beginning of the period (Rs. per unit)
A32: Plan /option (Face Value 10) | B32: As on | C32: As on
B33: 44834 | C33: 44865
A34: Direct Plan Growth Option | B34: 9.956 | C34: 10.049
A35: Direct Plan IDCW Option | B35: 9.955 | C35: 10.049
A36: Regular Plan Growth Option | B36: 9.954 | C36: 10.044
A37: Regular Plan IDCW Option | B37: 9.954 | C37: 10.044
A39: 3. Total Dividend (Net) declared during the month | B39: NIL
A40: 4. Bonus was declared during the month | B40: NIL
A41: 5. Investment in Repo of Corporate Debt Securities during the month ended October 31, 2022 | B41: NIL
A42: 6. Investment in foreign securities/ADRs/GDRs at the end of the month | B42: NIL
A43: 7. Average Portfolio Maturity | B43: NIL
A44: 8. Total gross exposure to derivative instruments (excluding reversed positions) at the end of the month (Rs. in Lakhs) | B44: NIL
A45: 9. Margin Deposits includes Margin money placed on derivatives other than margin money placed with bank | B45: NIL
A46: 10. Value of investment made by other schemes under same management (Rs. In Lakhs) | B46: NIL
A47: 11. Number of instance of deviation In valuation of securities | B47: NIL
A48: 12. Total value and percentage of illiquid equity shares / securities | B48: NIL
A50: Scheme Name | B50: Risk- O - Meter | C50: Benchmark of the Scheme | D50: Benchmark Risk-o-meter
A51: Edelweiss Gold and Silver ETF FOF | C51: LBMA Prices

Sheet ELLIQF
A1: PORTFOLIO STATEMENT OF EDELWEISS LIQUID FUND AS ON OCTOBER 31, 2022 | H1: =HYPERLINK("[EDEL_Portfolio Monthly Notes 31-Oct-2022.xlsx]Index!A1","Index") -> Index
A2: (An open-ended liquid scheme)
A4: Name of the Instrument | B4: ISIN | C4: Rating/Industry | D4: Quantity | E4: Market/Fair Value(Rs. In Lacs) | F4: % to Net Assets | G4: YIELD
A7: Equity & Equity related | E7: NIL | F7: NIL
A9: Money Market Instruments
A11: Treasury bills
A12: 182 DAYS TBILL RED 15-12-2022 | B12: IN002022Y112 | C12: SOVEREIGN | D12: 10000000 | E12: 9926.41 | F12: 0.075 | G12: 0.061499
A13: 182 DAYS TBILL RED 22-12-2022 | B13: IN002022Y120 | C13: SOVEREIGN | D13: 5000000 | E13: 4957.06 | F13: 0.0374 | G13: 0.062003
A14: 182 DAYS TBILL RED 01-12-2022 | B14: IN002022Y096 | C14: SOVEREIGN | D14: 2500000 | E14: 2487.48 | F14: 0.0188 | G14: 0.06125
A15: Sub Total | E15: 17370.95 | F15: 0.1312
A16: Certificate of Deposit
A17: IDFC FIRST BANK LTD. CD RED 23-01-2023#** | B17: INE092T16TC3 | C17: CRISIL A1+ | D17: 7500000 | E17: 7380.5 | F17: 0.0558 | G17: 0.071201
A18: HDFC BANK CD RED 10-11-2022# | B18: INE040A16DC6 | C18: CARE A1+ | D18: 5000000 | E18: 4992.37 | F18: 0.0377 | G18: 0.062023
A19: PUNJAB NATIONAL BANK CD RED 30-11-2022#** | B19: INE160A16MP5 | C19: CRISIL A1+ | D19: 5000000 | E19: 4974.12 | F19: 0.0376 | G19: 0.065498
A20: UNION BANK OF INDIA CD 20-01-23#** | B20: INE692A16FN6 | C20: ICRA A1+ | D20: 5000000 | E20: 4925.46 | F20: 0.0372 | G20: 0.069052
A21: AXIS BANK LTD CD RED 09-11-2022#** | B21: INE238A162Y4 | C21: CRISIL A1+ | D21: 2500000 | E21: 2496.56 | F21: 0.0189 | G21: 0.062912
A22: PUNJAB NATIONAL BNK CD R 25-11-22# | B22: INE160A16MN0 | C22: CRISIL A1+ | D22: 2500000 | E22: 2489.28 | F22: 0.0188 | G22: 0.065494
A23: CANARA BANK CD RED 03-01-2023# | B23: INE476A16TO3 | C23: CRISIL A1+ | D23: 2500000 | E23: 2471.13 | F23: 0.0187 | G23: 0.067699
A24: Sub Total | E24: 29729.42 | F24: 0.2247
A26: Commercial Paper
A27: RELIANCE RETAIL VENTU CP 05-12-22** | B27: INE929O14776 | C27: CRISIL A1+ | D27: 7500000 | E27: 7453.31 | F27: 0.0563 | G27: 0.067246
A28: BAJAJ FINANCE LTD CP RED 21-11-2022** | B28: INE296A14TL6 | C28: CRISIL A1+ | D28: 5000000 | E28: 4981.88 | F28: 0.0376 | G28: 0.066397
A29: HDFC LTD. CP RED 25-11-2022** | B29: INE001A14YY3 | C29: CRISIL A1+ | D29: 5000000 | E29: 4978.3 | F29: 0.0376 | G29: 0.0663
A30: LARSEN & TOUBRO LTD CP RED 28-11-2022** | B30: INE018A14IY0 | C30: CRISIL A1+ | D30: 5000000 | E30: 4975.88 | F30: 0.0376 | G30: 0.06555
A31: LARSEN & TOUBRO LTD CP RED 30-11-2022** | B31: INE018A14IW4 | C31: CRISIL A1+ | D31: 5000000 | E31: 4974.1 | F31: 0.0376 | G31: 0.065549
A32: ICICI SECURITIES CP RED 12-12-2022** | B32: INE763G14NH3 | C32: CRISIL A1+ | D32: 5000000 | E32: 4960.82 | F32: 0.0375 | G32: 0.070324
A33: NABARD CP RED 15-12-2022** | B33: INE261F14JD7 | C33: CRISIL A1+ | D33: 5000000 | E33: 4960.54 | F33: 0.0375 | G33: 0.065997
A34: RELIANCE JIO INFO LTD CP RED 15-12-2022** | B34: INE110L14RA3 | C34: CRISIL A1+ | D34: 5000000 | E34: 4960 | F34: 0.0375 | G34: 0.066899
A35: HDFC LTD. CP RED 15-12-2022** | B35: INE001A14ZP8 | C35: CRISIL A1+ | D35: 5000000 | E35: 4959.85 | F35: 0.0375 | G35: 0.067152
A36: ICICI SECURITIES CP RED 09-11-2022** | B36: INE763G14MY0 | C36: CRISIL A1+ | D36: 2500000 | E36: 2496.33 | F36: 0.0189 | G36: 0.067167
A37: GODREJ INDUSTRIES LTD CP RED 11-11-2022** | B37: INE233A14VW2 | C37: CRISIL A1+ | D37: 2500000 | E37: 2495.5 | F37: 0.0189 | G37: 0.065892
A38: EXIM BANK CP RED 05-12-2022** | B38: INE514E14QP1 | C38: CRISIL A1+ | D38: 2500000 | E38: 2484.78 | F38: 0.0188 | G38: 0.065746
... A42: BAJAJ FINANCE LTD CP 13-01-2023** | B42: INE296A14TV5 | C42: CRISIL A1+ | D42: 2500000 | E42: 2464.77 | F42: 0.0186 | G42: 0.071475
A43: GODREJ AGROVET CP 27-01-23 VD0111** | B43: INDUMMY31101 | C43: ICRA A1+ | D43: 2500000 | E43: 2457.94 | F43: 0.0186
A44: Sub Total | E44: 67017.38 | F44: 0.5066
A46: TOTAL | E46: 114117.75 | F46: 0.8625
A49: TREPS / Reverse Repo
A50: Clearing Corporation of India Ltd. | E50: 20662.54 | F50: 0.1561 | G50: 0.061074
A51: Sub Total | E51: 20662.54 | F51: 0.1561
A53: TOTAL | E53: 20662.54 | F53: 0.1561
A54: Accrued Interest | E54: 3.4573812 | F54: 2.6e-05
A55: Net Receivables/(Payables) | E55: -2400.8474 | F55: -0.018626 | G55: 0.061074
A56: GRAND TOTAL | E56: 132382.9 | F56: 1
A58: # Unlisted Security
A59: **Non Traded Security
A61: Notes:
A62: 1. Security in default beyond its maturiy date | B62: NIL
A63: 2. NAV at the beginning of the period (Rs. per unit)
A64: Plan /option (Face Value 1000) | B64: As on | C64: As on
B65: 44834 | C65: 44865
A66: Direct Plan Annual IDCW Option | B66: 2810.9571 | C66: 2825.3245
A67: Direct Plan Bonus Option | B67: 1635.3745 | C67: 1643.7332
A68: Direct Plan Daily IDCW Option | B68: 1016.7534 | C68: 1021.9502
A69: Direct Plan Fortnightly IDCW Option | B69: 2221.6272 | C69: 2232.9822
A70: Direct Plan Growth Option | B70: 2810.9659 | C70: 2825.3332
A71: Direct Plan IDCW Option | B71: 2810.9802 | C71: 2825.3478
A72: Direct Plan Monthly IDCW Option | B72: 1005.0818 | C72: 1005.3184
A73: Direct Plan Weekly IDCW Option | B73: 2174.4832 | C73: 2175.1085
A74: Regular Plan Annual IDCW | B74: 1915.8172 | C74: 1925.2147
A75: Regular Plan Bonus Option | B75: 1612.7244 | C75: 1620.6347
A76: Regular Plan Daily IDCW | B76: 1025.2305 | C76: 1030.2607
A77: Regular Plan Fortnightly IDCW | B77: 2154.0936 | C77: 2153.7938
... A81: Regular Plan Weekly IDCW | B81: 1039.159 | C81: 1044.2575
A82: Retail Annual IDCW Option | B82: ^ | C82: ^
A83: Retail Bonus Option | B83: ^ | C83: ^
A84: Retail Daily IDCW Option | B84: 1024.9956 | C84: 1030.0244
A85: Retail Fortnightly IDCW Option | B85: ^ | C85: ^
A86: Retail Growth Option | B86: 2518.0912 | C86: 2530.4455
A87: Retail IDCW Option | B87: ^ | C87: ^
A88: Retail Monthly IDCW Option | B88: 1244.3558 | C88: 1244.6387
A89: Retail Weekly IDCW Option | B89: 1231.8682 | C89: 1232.1988
A90: Unclaimed IDCW less than 3 yrs | B90: ^ | C90: ^
A91: Unclaimed IDCW more than 3 yrs | B91: ^ | C91: ^
A92: Unclaimed Redemption less than 3 yrs | B92: ^ | C92: ^
A93: Unclaimed Redemption more than 3 yrs | B93: ^ | C93: ^
A94: ^ There were no investors in this option.
A96: 3. Total Dividend (Net) declared during the month
A98: Plan/Option Name | C98: individual & HUF | D98: others
A99: Direct Plan Monthly IDCW | C99: 4.894711 | D99: 4.894711
A100: Direct Plan weekly IDCW | C100: 10.459902 | D100: 10.459902
A101: Regular Plan Fortnightly IDCW | C101: 10.891064 | D101: 10.891064
A102: Retail Plan Monthly IDCW | C102: 5.8198695 | D102: 5.8198695
A103: Retail Plan Weekly IDCW | C103: 5.6987172 | D103: 5.6987172
A105: 4. Bonus was declared during the month | B105: NIL
A106: 5. Investment in Repo of Corporate Debt Securities during the month ended October 31, 2022 | B106: NIL
A107: 6. Investment in foreign securities/ADRs/GDRs at the end of the month | B107: NIL
A108: 7. Average Portfolio Maturity | B108: 0.099129487
A109: 8. Total gross exposure to derivative instruments (excluding reversed positions) at the end of the month (Rs. in Lakhs) | B109: NIL
A110: 9. Margin Deposits includes Margin money placed on derivatives other than margin money placed with bank | B110: NIL
A111: 10. Value of investment made by other schemes under same management (Rs. In Lakhs) | B111: 1720.6513
A112: 11. Number of instance of deviation In valuation of securities | B112: NIL
A113: 12. Total value and percentage of illiquid equity shares / securities | B113: NIL
A116: Scheme Name | B116: Risk- O - Meter | C116: Benchmark of the Scheme | D116: Benchmark Risk-o-meter | E116: Benchmark of the Scheme | F116: Benchmark Risk-o-meter
A117: Edelweiss Liquid Fund | C117: NIFTY Liquid Index B-I (TIER-1) | E117: NIFTY Liquid Index A-I (TIER-2)

Sheet EOASEF
A1: PORTFOLIO STATEMENT OF EDELWEISS ASEAN EQUITY OFF-SHORE FUND AS ON OCTOBER 31, 2022 | H1: =HYPERLINK("[EDEL_Portfolio Monthly Notes 31-Oct-2022.xlsx]Index!A1","Index") -> Index
A2: (An open ended fund of fund scheme investing in JPMorgan Funds – ASEAN Equity Fund)
A4: Name of the Instrument | B4: ISIN | C4: Rating/Industry | D4: Quantity | E4: Market/Fair Value(Rs. In Lacs) | F4: % to Net Assets | G4: YIELD
A7: Foreign Securities and/or Overseas ETFs
A8: International Mutual Fund Units
A9: JPM ASEAN EQUITY-I ACC USD | B9: LU0441852299 | D9: 50178.133 | E9: 6413.2 | F9: 0.9893
A10: Sub Total | E10: 6413.2 | F10: 0.9893
A12: TOTAL | E12: 6413.2 | F12: 0.9893
A14: TREPS / Reverse Repo
A15: Clearing Corporation of India Ltd. | E15: 94.98 | F15: 0.0147 | G15: 0.061074
A16: Sub Total | E16: 94.98 | F16: 0.0147
A18: TOTAL | E18: 94.98 | F18: 0.0147
A19: Accrued Interest | E19: 0.0158933 | F19: 2e-06
A20: Net Receivables/(Payables) | E20: -25.875893 | F20: -0.004002 | G20: 0.061074
A21: GRAND TOTAL | E21: 6482.32 | F21: 1
A26: Notes:
A27: 1. Security in default beyond its maturiy date | B27: NIL
A28: 2. NAV at the beginning of the period (Rs. per unit)
A29: Plan /option (Face Value 10) | B29: As on | C29: As on
B30: 44834 | C30: 44865
A31: Direct Plan Growth Option | B31: 24.387 | C31: 24.795
A32: Regular Plan Growth Option | B32: 22.286 | C32: 22.646
A34: 3. Total Dividend (Net) declared during the month | B34: NIL
A35: 4. Bonus was declared during the month | B35: NIL
A36: 5. Investment in Repo of Corporate Debt Securities during the month ended October 31, 2022 | B36: NIL
A37: 6. Investment in foreign securities/ADRs/GDRs at the end of the month | B37: 6413.199
A38: 7. Total gross exposure to derivative instruments (excluding reversed positions) at the end of the month (Rs. in Lakhs) | B38: NIL
A39: 8. Margin Deposits includes Margin money placed on derivatives other than margin money placed with bank | B39: NIL
A40: 9. Number of instance of deviation In valuation of securities | B40: NIL
A41: 10. Total value and percentage of illiquid equity shares / securities | B41: NIL
A44: Scheme Name | B44: Risk- O - Meter | C44: Benchmark of the Scheme | D44: Benchmark Risk-o-meter
A45: Edelweiss ASEAN Equity Off-shore Fund | C45: MSCI AC ASEAN 10/40 Index (Total Return Net)

Sheet EOCHIF
A1: PORTFOLIO STATEMENT OF EDELWEISS GREATER CHINA EQUITY OFF-SHORE FUND AS ON OCTOBER 31, 2022 | H1: =HYPERLINK("[EDEL_Portfolio Monthly Notes 31-Oct-2022.xlsx]Index!A1","Index") -> Index
A2: (An open ended fund of fund scheme investing in JPMorgan Funds – Greater China Fund)
A4: Name of the Instrument | B4: ISIN | C4: Rating/Industry | D4: Quantity | E4: Market/Fair Value(Rs. In Lacs) | F4: % to Net Assets | G4: YIELD
A7: Foreign Securities and/or Overseas ETFs
A8: International Mutual Fund Units
A9: JPM GREATER CHINA-I-I2 USD | B9: LU1727356906 | D9: 1391663.8 | E9: 126428.43 | F9: 0.9962
A10: Sub Total | E10: 126428.43 | F10: 0.9962
A12: TOTAL | E12: 126428.43 | F12: 0.9962
A14: TREPS / Reverse Repo
A15: Clearing Corporation of India Ltd. | E15: 1481.75 | F15: 0.0117 | G15: 0.061074
A16: Sub Total | E16: 1481.75 | F16: 0.0117
A18: TOTAL | E18: 1481.75 | F18: 0.0117
A19: Accrued Interest | E19: 0.2479357 | F19: 1e-06
A20: Net Receivables/(Payables) | E20: -1001.4579 | F20: -0.007901 | G20: 0.061074
A21: GRAND TOTAL | E21: 126908.97 | F21: 1
A26: Notes:
A27: 1. Security in default beyond its maturiy date | B27: NIL
A28: 2. NAV at the beginning of the period (Rs. per unit)
A29: Plan /option (Face Value 10) | B29: As on | C29: As on
B30: 44834 | C30: 44865
A31: Direct Plan Growth Option | B31: 35.145 | C31: 30.888
A32: Regular Plan Growth Option | B32: 32.089 | C32: 28.181
A34: 3. Total Dividend (Net) declared during the month | B34: NIL
A35: 4. Bonus was declared during the month | B35: NIL
A36: 5. Investment in Repo of Corporate Debt Securities during the month ended October 31, 2022 | B36: NIL
A37: 6. Investment in foreign securities/ADRs/GDRs at the end of the month | B37: 126428.43
A38: 7. Total gross exposure to derivative instruments (excluding reversed positions) at the end of the month (Rs. in Lakhs) | B38: NIL
A39: 8. Margin Deposits includes Margin money placed on derivatives other than margin money placed with bank | B39: NIL
A40: 9. Number of instance of deviation In valuation of securities | B40: NIL
A41: 10. Total value and percentage of illiquid equity shares / securities | B41: NIL
A44: Scheme Name | B44: Risk- O - Meter | C44: Benchmark of the Scheme | D44: Benchmark Risk-o-meter
A45: Edelweiss Greater China Equity Off-shore Fund | C45: MSCI Golden Dragon Index (Total Return Net)

Sheet EODWHF
A1: PORTFOLIO STATEMENT OF EDELWEISS MSCI INDIA DOMESTIC & WORLD HEALTHCARE 45 INDEX AS ON OCTOBER 31, 2022 | H1: =HYPERLINK("[EDEL_Portfolio Monthly Notes 31-Oct-2022.xlsx]Index!A1","Index") -> Index
A2: (An Open-ended Equity Scheme replicating MSCI India Domestic & World Healthcare 45 Index)
A4: Name of the Instrument | B4: ISIN | C4: Rating/Industry | D4: Quantity | E4: Market/Fair Value(Rs. In Lacs) | F4: % to Net Assets | G4: YIELD
A6: Equity & Equity related
A7: (a)Listed / Awaiting listing on Stock Exchanges
A8: Sun Pharmaceutical Industries Ltd. | B8: INE044A01036 | C8: Pharmaceuticals & Biotechnology | D8: 200561 | E8: 2039.5 | F8: 0.1348
A9: Cipla Ltd. | B9: INE059A01026 | C9: Pharmaceuticals & Biotechnology | D9: 101171 | E9: 1181.07 | F9: 0.0781
A10: Dr. Reddy's Laboratories Ltd. | B10: INE089A01023 | C10: Pharmaceuticals & Biotechnology | D10: 24345 | E10: 1079.38 | F10: 0.0714
A11: Divi's Laboratories Ltd. | B11: INE361B01024 | C11: Pharmaceuticals & Biotechnology | D11: 27739 | E11: 1001.07 | F11: 0.0662
A12: Apollo Hospitals Enterprise Ltd. | B12: INE437A01024 | C12: Healthcare Services | D12: 21033 | E12: 950.17 | F12: 0.0628
A13: Max Healthcare Institute Ltd. | B13: INE027H01010 | C13: Healthcare Services | D13: 147398 | E13: 672.58 | F13: 0.0445
A14: Torrent Pharmaceuticals Ltd. | B14: INE685A01028 | C14: Pharmaceuticals & Biotechnology | D14: 21219 | E14: 350.11 | F14: 0.0231
A15: Laurus Labs Ltd. | B15: INE947Q01028 | C15: Pharmaceuticals & Biotechnology | D15: 72992 | E15: 331.79 | F15: 0.0219
A16: Lupin Ltd. | B16: INE326A01037 | C16: Pharmaceuticals & Biotechnology | D16: 42747 | E16: 298.8 | F16: 0.0198
A17: Aurobindo Pharma Ltd. | B17: INE406A01037 | C17: Pharmaceuticals & Biotechnology | D17: 55103 | E17: 296.54 | F17: 0.0196
A18: IPCA Laboratories Ltd. | B18: INE571A01038 | C18: Pharmaceuticals & Biotechnology | D18: 29155 | E18: 263.88 | F18: 0.0174
A19: Fortis Healthcare Ltd. | B19: INE061F01013 | C19: Healthcare Services | D19: 94663 | E19: 262.64 | F19: 0.0174
... A32: Alembic Pharmaceuticals Ltd. | B32: INE901L01018 | C32: Pharmaceuticals & Biotechnology | D32: 12323 | E32: 67.79 | F32: 0.0045
A33: Sub Total | E33: 10450.1 | F33: 0.6909
A34: (b) Unlisted
A35: Sub Total | E35: NIL | F35: NIL
A36: (c) Listed / Awaiting listing on International Stock Exchanges
A37: JOHNSON & JOHNSON | B37: US4781601046 | C37: Pharmaceuticals | D37: 4745 | E37: 680.15 | F37: 0.045
A38: ELI LILLY & CO | B38: US5324571083 | C38: Pharmaceuticals | D38: 1457 | E38: 434.68 | F38: 0.0287
A39: PFIZER INC | B39: US7170811035 | C39: Pharmaceuticals | D39: 10117 | E39: 388.03 | F39: 0.0257
A40: ABBVIE INC | B40: US00287Y1091 | C40: Biotechnology | D40: 3187 | E40: 384.43 | F40: 0.0254
A41: MERCK & CO.INC | B41: US58933Y1055 | C41: Pharmaceuticals | D41: 4561 | E41: 380.31 | F41: 0.0251
A42: THERMO FISHER SCIENTIFIC INC | B42: US8835561023 | C42: Life Sciences Tools & Services | D42: 707 | E42: 299.4 | F42: 0.0198
A43: NOVARTIS AG | B43: US66987V1098 | C43: Pharmaceuticals | D43: 3901 | E43: 260.77 | F43: 0.0172
A44: DANAHER CORP | B44: US2358511028 | C44: Health Care Equipment & Supplies | D44: 1245 | E44: 258.16 | F44: 0.0171
A45: ABBOTT LABORATORIES | B45: US0028241000 | C45: Health Care Equipment & Supplies | D45: 3158 | E45: 257.44 | F45: 0.017
A46: AMGEN INC | B46: US0311621009 | C46: Biotechnology | D46: 964 | E46: 214.73 | F46: 0.0142
A47: MEDTRONIC PLC | B47: IE00BTN1Y115 | C47: Health Care Equipment & Supplies | D47: 2400 | E47: 172.71 | F47: 0.0114
A48: GILEAD SCIENCES INC | B48: US3755581036 | C48: Biotechnology | D48: 2261 | E48: 146.16 | F48: 0.0097
... A56: ILLUMINA INC | B56: US4523271090 | C56: Life Sciences Tools & Services | D56: 283 | E56: 53.35 | F56: 0.0035
A58: Sub Total | E58: =SUM(E37:E57) -> 4592.71 | F58: =SUM(F37:F57) -> 0.3036
A60: TOTAL | E60: 15042.81 | F60: 0.9945
A63: TREPS / Reverse Repo
A64: Clearing Corporation of India Ltd. | E64: 12 | F64: 0.0008 | G64: 0.061074
A65: Sub Total | E65: 12 | F65: 0.0008
A67: TOTAL | E67: 12 | F67: 0.0008
A68: Accrued Interest | E68: 0.0020076 | F68: 0
A69: Net Receivables/(Payables) | E69: 72.927992 | F69: 0.0047 | G69: 0.061074
A70: GRAND TOTAL | E70: 15127.74 | F70: 1
A75: Notes:
A76: 1. Security in default beyond its maturiy date | B76: NIL
A77: 2. NAV at the beginning of the period (Rs. per unit)
A78: Plan /option (Face Value 10) | B78: As on | C78: As on
B79: 44834 | C79: 44865
A80: Direct Plan Growth Option | B80: 12.0316 | C80: 12.6449
A81: Direct Plan IDCW Option | B81: 12.0316 | C81: 12.6449
A82: Regular Plan Growth Option | B82: 11.8931 | C82: 12.4932
A83: Regular Plan IDCW Option | B83: 11.8931 | C83: 12.4932
A85: 3. Total Dividend (Net) declared during the month | B85: NIL
A86: 4. Bonus was declared during the month | B86: NIL
A87: 5. Investment in Repo of Corporate Debt Securities during the month ended October 31, 2022 | B87: NIL
A88: 6. Investment in foreign securities/ADRs/GDRs at the end of the month | B88: =E58 -> 4592.71
A89: 7. Total gross exposure to derivative instruments (excluding reversed positions) at the end of the month (Rs. in Lakhs) | B89: NIL
A90: 8. Margin Deposits includes Margin money placed on derivatives other than margin money placed with bank | B90: NIL
A91: 9. Number of instance of deviation In valuation of securities | B91: NIL
A92: 10. Total value and percentage of illiquid equity shares / securities | B92: NIL
A95: Scheme Name | B95: Risk- O - Meter | C95: Benchmark of the Scheme | D95: Benchmark Risk-o-meter
A96: Edelweiss MSCI (I) DM & WD HC 45 ID Fund | C96: MSCI India Domestic & World Healthcare 45 Index

Sheet EOEDOF
A1: PORTFOLIO STATEMENT OF EDELWEISS EUROPE DYNAMIC EQUITY OFF-SHORE FUND AS ON OCTOBER 31, 2022 | H1: =HYPERLINK("[EDEL_Portfolio Monthly Notes 31-Oct-2022.xlsx]Index!A1","Index") -> Index
A2: (An open ended fund of fund scheme investing in JPMorgan Funds – Europe Dynamic Fund)
